Workbook

Sheet OOMRSC-05
A1: OOMRSC-05
A2: Rev. 37 | C2: Cuadro de Control de Desempeño de Procesos
A3: Última Revisión: Abril 2026
R4: Mes/año: | S4: Julio 2026
A5: No. | B5: Proceso: | C5: Dirección: | D5: Área: | E5: # | F5: Indicador o Índice: | G5: Periodicidad | H5: Unidad de Medida | I5: Meta Anual | J5: Meta | K5: Meta | L5: Meta | M5: Meta | N5: Impacto | P5: Cumple: Sí/No | Q5: Cumplimiento | R5: Observación: | S5: Acción: | V5: Responsable: | AD5: META 1ER TRIM | AE5: 1ER PEM | AJ5: META ACUM 2DO TRIM | AK5: 2DO PEM | AL5: 2DO PEM ACUM | AQ5: META ACUM 3ER TRIM | AR5: 3ER PEM | AS5: 3ER PEM ACUM | AX5: META ACUM 4TO TRIM | AY5: 4TO PEM | AZ5: 4TO PEM ACUM
J6: 1er Trim. | K6: 2do Trim. | L6: 3er Trim. | M6: 4to Trim. | N6: Bajo | O6: Alto | S6: c | T6: ac | U6: snc | Z6: Enero | AA6: Febrero | AB6: Marzo | AC6: 1er Trimestre | AF6: Abril | AG6: Mayo | AH6: Junio | AI6: 2do Trimestre | AM6: Julio | AN6: Agosto | AO6: Septiembre | AP6: 3er Trimestre | AT6: Octubre | AU6: Noviembre | AV6: Diciembre | AW6: 4TO Trimestre
A7: 1 | B7: Responsabilidad de la Dirección | C7: General | D7: Sistema de Gestión de Calidad | E7: 0 | F7: Lograr el grado de eficacia del SGC determinado por auditorías e indicadores. | G7: Trimestral | H7: Porcentaje | I7: 85 | J7: 20 | K7: 20 | L7: 20 | M7: 25 | N7: n/a | P7: SI | Q7: 91 | R7: El grado de eficacia del SGC resultó en un 91% de cumplimiento. El resultado por indicadores fue del 90%, quedando en rango aceptable; y por auditorías fue de 92%, quedando en rango aceptable. | S7: NA | T7: NA | U7: NA | V7: Mariana Pérez | Z7: 92 | AA7: 91 | AB7: 90 | AC7: =AVERAGE(Z7:AB7) -> 91 | AD7: =J7 -> 20 | AE7: =(J7*AC7)/I7 -> 21.411765 | AF7: 90 | AG7: 90 | AH7: 91 | AI7: =AVERAGE(AF7:AH7) -> 90.333333 | AJ7: =J7+K7 -> 40 | AK7: =(K7*AI7)/I7 -> 21.254902 | AL7: =AE7+AK7 -> 42.666667 | AM7: =Q7 -> 91 | AP7: =AVERAGE(AM7:AO7) -> 91 | AQ7: =J7+K7+L7 -> 60 | AR7: =(L7*AP7)/I7 -> 21.411765 | AS7: =AE7+AK7+AR7 -> 64.078431 | AW7: =AVERAGE(AT7:AV7) -> #DIV/0! | AX7: =J7+K7+L7+M7 -> 85 | AY7: =(M7*AW7)/I7 -> #DIV/0! | AZ7: =AE7+AK7+AR7+AY7 -> #DIV/0!
D8: Dirección General | E8: 1 | F8: Cumplir con las metas establecidas por las direcciones adscritas a la Dirección General | G8: Trimestral | H8: Porcentaje | I8: 85 | J8: 20 | K8: 20 | L8: 20 | M8: 25 | N8: X | P8: SI | Q8: 0 | R8: Se cumplió con las metas de las direcciones adscritas a la Dirección General. | S8: NA | T8: NA | U8: NA | V8: Mariana Pérez | Z8: 0 | AA8: 0 | AB8: 88 | AC8: =SUM(Z8:AB8) -> 88 | AD8: =J8 -> 20 | AE8: =(J8*AC8)/I8 -> 20.705882 | AF8: 0 | AG8: 0 | AH8: 85 | AI8: =SUM(AF8:AH8) -> 85 | AJ8: =J8+K8 -> 40 | AK8: =(K8*AI8)/I8 -> 20 | AL8: =AE8+AK8 -> 40.705882 | AM8: =Q8 -> 0 | AP8: =SUM(AM8:AO8) -> 0 | AQ8: =J8+K8+L8 -> 60 | AR8: =(L8*AP8)/I8 -> 0 | AS8: =AE8+AK8+AR8 -> 40.705882 | AW8: =SUM(AT8:AV8) -> 0 | AX8: =J8+K8+L8+M8 -> 85 | AY8: =(M8*AW8)/I8 -> 0 | AZ8: =AE8+AK8+AR8+AY8 -> 40.705882
E9: 2 | F9: Mantener una relación de comunicación con el Consejo Consultivo. | G9: Trimestral | H9: Actas | I9: 11 | J9: 3 | K9: 3 | L9: 2 | M9: 3 | N9: X | P9: SI | Q9: 0 | R9: Se cumplió con 3 reuniones con el Consejo Consultivo. | S9: NA | T9: NA | U9: NA | V9: Mariana Pérez | Z9: 0 | AA9: 0 | AB9: 3 | AC9: =SUM(Z9:AB9) -> 3 | AD9: =J9 -> 3 | AE9: =AC9 -> 3 | AF9: 0 | AG9: 0 | AH9: 3 | AI9: =SUM(AF9:AH9) -> 3 | AJ9: =J9+K9 -> 6 | AK9: =AI9 -> 3 | AL9: =AE9+AK9 -> 6 | AM9: =Q9 -> 0 | AP9: =SUM(AM9:AO9) -> 0 | AQ9: =J9+K9+L9 -> 8 | AR9: =AP9 -> 0 | AS9: =AE9+AK9+AR9 -> 6 | AW9: =SUM(AT9:AV9) -> 0 | AX9: =J9+K9+L9+M9 -> 11 | AY9: =AW9 -> 0 | AZ9: =AE9+AK9+AR9+AY9 -> 6
A10: 2 | B10: Gestión de Recursos | C10: Administrativa | D10: Recursos Humanos | E10: 3 | F10: Remuneración del personal. | G10: Trimestral | H10: Cantidad | I10: 28 | J10: 6 | K10: 6 | L10: 8 | M10: 8 | N10: X | P10: SI | Q10: 0 | R10: Se cumplió con la remuneración del personal. | S10: NA | T10: NA | U10: NA | V10: Vicente Castro | Z10: 0 | AA10: 0 | AB10: 6 | AC10: =SUM(Z10:AB10) -> 6 | AD10: =J10 -> 6 | AE10: =AC10 -> 6 | AF10: 0 | AG10: 0 | AH10: 6 | AI10: =SUM(AF10:AH10) -> 6 | AJ10: =J10+K10 -> 12 | AK10: =AI10 -> 6 | AL10: =AE10+AK10 -> 12 | AM10: =Q10 -> 0 | AP10: =SUM(AM10:AO10) -> 0 | AQ10: =J10+K10+L10 -> 20 | AR10: =AP10 -> 0 | AS10: =AE10+AK10+AR10 -> 12 | AW10: =SUM(AT10:AV10) -> 0 | AX10: =J10+K10+L10+M10 -> 28 | AY10: =AW10 -> 0 | AZ10: =AE10+AK10+AR10+AY10 -> 12
E11: 4 | F11: Remuneración a jubilados y pensionados | G11: Trimestral | H11: Cantidad | I11: 28 | J11: 6 | K11: 6 | L11: 8 | M11: 8 | N11: X | P11: SI | Q11: 0 | R11: Se cumplió con la remuneración de jubilados y pensionados. | S11: NA | T11: NA | U11: NA | V11: Vicente Castro | Z11: 0 | AA11: 0 | AB11: 6 | AC11: =SUM(Z11:AB11) -> 6 | AD11: =J11 -> 6 | AE11: =AC11 -> 6 | AF11: 0 | AG11: 0 | AH11: 6 | AI11: =SUM(AF11:AH11) -> 6 | AJ11: =J11+K11 -> 12 | AK11: =AI11 -> 6 | AL11: =AE11+AK11 -> 12 | AM11: =Q11 -> 0 | AP11: =SUM(AM11:AO11) -> 0 | AQ11: =J11+K11+L11 -> 20 | AR11: =AP11 -> 0 | AS11: =AE11+AK11+AR11 -> 12 | AW11: =SUM(AT11:AV11) -> 0 | AX11: =J11+K11+L11+M11 -> 28 | AY11: =AW11 -> 0 | AZ11: =AE11+AK11+AR11+AY11 -> 12
E12: 5 | F12: Cumplir con el programa trimestral de capacitación. | G12: Trimestral | H12: Porcentaje | I12: 100 | J12: 25 | K12: 25 | L12: 25 | M12: 25 | N12: X | P12: SI | Q12: 0 | R12: Se cumplió con el programa tirmestral de capacitación. | S12: RC 04/2026 | T12: NA | U12: NA | V12: Ana Cecilia Ruiz | Z12: 0 | AA12: 0 | AB12: 86 | AC12: =SUM(Z12:AB12) -> 86 | AD12: =J12 -> 25 | AE12: =(J12*AC12)/I12 -> 21.5 | AF12: 0 | AG12: 0 | AH12: 100 | AI12: =SUM(AF12:AH12) -> 100 | AJ12: =J12+K12 -> 50 | AK12: =(K12*AI12)/I12 -> 25 | AL12: =AE12+AK12 -> 46.5 | AM12: =Q12 -> 0 | AP12: =SUM(AM12:AO12) -> 0 | AQ12: =J12+K12+L12 -> 75 | AR12: =(L12*AP12)/I12 -> 0 | AS12: =AE12+AK12+AR12 -> 46.5 | AW12: =SUM(AT12:AV12) -> 0 | AX12: =J12+K12+L12+M12 -> 100 | AY12: =(M12*AW12)/I12 -> 0 | AZ12: =AE12+AK12+AR12+AY12 -> 46.5
E13: 6 | F13: Evaluación del ambiente de trabajo. | G13: Anual | H13: Porcentaje | I13: 95 | J13: 0 | K13: 0 | L13: 0 | M13: 95 | N13: X | P13: SI | Q13: 0 | R13: El indicador es anual. | S13: NA | T13: NA | U13: NA | V13: Erika Acosta | Z13: 0 | AA13: 0 | AB13: 0 | AC13: =AVERAGE(Z13:AB13) -> 0 | AD13: =J13 -> 0 | AE13: =(J13*AC13)/I13 -> 0 | AF13: 0 | AG13: 0 | AH13: 0 | AI13: =AVERAGE(AF13:AH13) -> 0 | AJ13: =J13+K13 -> 0 | AK13: =(K13*AI13)/I13 -> 0 | AL13: =AE13+AK13 -> 0 | AM13: =Q13 -> 0 | AP13: =AVERAGE(AM13:AO13) -> 0 | AQ13: =J13+K13+L13 -> 0 | AR13: =(L13*AP13)/I13 -> 0 | AS13: =AE13+AK13+AR13 -> 0 | AW13: =AVERAGE(AT13:AV13) -> #DIV/0! | AX13: =J13+K13+L13+M13 -> 95 | AY13: =(M13*AW13)/I13 -> #DIV/0! | AZ13: =AE13+AK13+AR13+AY13 -> #DIV/0!
D14: Recursos Materiales | E14: 7 | F14: Evaluar el desempeño de proveedores de productos químicos críticos | G14: Mensual | H14: Porcentaje | I14: 100 | J14: 25 | K14: 25 | L14: 25 | M14: 25 | O14: X | P14: SI | Q14: 100 | R14: Se cumplió al 100% con la evaluación del desempeño de proveedores de productos químicos críticos. | S14: NA | T14: NA | U14: NA | V14: Xiomara López | Z14: 100 | AA14: 100 | AB14: 100 | AC14: =AVERAGE(Z14:AB14) -> 100 | AD14: =J14 -> 25 | AE14: =(J14*AC14)/I14 -> 25 | AF14: 100 | AG14: 100 | AH14: 100 | AI14: =AVERAGE(AF14:AH14) -> 100 | AJ14: =J14+K14 -> 50 | AK14: =(K14*AI14)/I14 -> 25 | AL14: =AE14+AK14 -> 50 | AM14: =Q14 -> 100 | AP14: =AVERAGE(AM14:AO14) -> 100 | AQ14: =J14+K14+L14 -> 75 | AR14: =(L14*AP14)/I14 -> 25 | AS14: =AE14+AK14+AR14 -> 75 | AW14: =AVERAGE(AT14:AV14) -> #DIV/0! | AX14: =J14+K14+L14+M14 -> 100 | AY14: =(M14*AW14)/I14 -> #DIV/0! | AZ14: =AE14+AK14+AR14+AY14 -> #DIV/0!
E15: 8 | F15: Atender las solicitudes de compra en el tiempo establecido. | G15: Mensual | H15: Porcentaje | I15: 100 | J15: 25 | K15: 25 | L15: 25 | M15: 25 | N15: X | P15: SI | Q15: 100 | R15: Se atendieron al 100% las solicitudes de compra en el tiempo establecido. | S15: NA | T15: NA | U15: NA | V15: Xiomara López | Z15: 100 | AA15: 100 | AB15: 100 | AC15: =AVERAGE(Z15:AB15) -> 100 | AD15: =J15 -> 25 | AE15: =(J15*AC15)/I15 -> 25 | AF15: 100 | AG15: 100 | AH15: 100 | AI15: =AVERAGE(AF15:AH15) -> 100 | AJ15: =J15+K15 -> 50 | AK15: =(K15*AI15)/I15 -> 25 | AL15: =AE15+AK15 -> 50 | AM15: =Q15 -> 100 | AP15: =AVERAGE(AM15:AO15) -> 100 | AQ15: =J15+K15+L15 -> 75 | AR15: =(L15*AP15)/I15 -> 25 | AS15: =AE15+AK15+AR15 -> 75 | AW15: =AVERAGE(AT15:AV15) -> #DIV/0! | AX15: =J15+K15+L15+M15 -> 100 | AY15: =(M15*AW15)/I15 -> #DIV/0! | AZ15: =AE15+AK15+AR15+AY15 -> #DIV/0!
E16: 9 | F16: Cumplir con el programa de verificación de activos fijos | G16: Mensual | H16: Porcentaje | I16: 100 | J16: 25 | K16: 25 | L16: 25 | M16: 25 | N16: X | P16: SI | Q16: 100 | R16: Se cumplió al 100% con el programa de verificación de activos fijos. | S16: NA | T16: NA | U16: NA | V16: Xiomara López | Z16: 100 | AA16: 100 | AB16: 100 | AC16: =AVERAGE(Z16:AB16) -> 100 | AD16: =J16 -> 25 | AE16: =(J16*AC16)/I16 -> 25 | AF16: 100 | AG16: 100 | AH16: 100 | AI16: =AVERAGE(AF16:AH16) -> 100 | AJ16: =J16+K16 -> 50 | AK16: =(K16*AI16)/I16 -> 25 | AL16: =AE16+AK16 -> 50 | AM16: =Q16 -> 100
D17: Contabilidad | E17: 10 | F17: Cumplir con el calendario contable y presupuestal. | G17: Mensual | H17: Documentos | I17: 29 | J17: 8 | K17: 7 | L17: 7 | M17: 7 | N17: X | P17: SI | Q17: 3 | R17: Se cumplió con el envío de los documentos del mes. | S17: NA | T17: NA | U17: NA | V17: María Fernanda Luzanilla | Z17: 3 | AA17: 2 | AB17: 3 | AC17: =SUM(Z17:AB17) -> 8 | AD17: =J17 -> 8 | AE17: =AC17 -> 8 | AF17: 3 | AG17: 2 | AH17: 2 | AI17: =SUM(AF17:AH17) -> 7 | AJ17: =J17+K17 -> 15 | AK17: =AI17 -> 7 | AL17: =AE17+AK17 -> 15 | AM17: =Q17 -> 3 | AP17: =SUM(AM17:AO17) -> 3 | AQ17: =J17+K17+L17 -> 22 | AR17: =AP17 -> 3 | AS17: =AE17+AK17+AR17 -> 18 | AW17: =SUM(AT17:AV17) -> 0 | AX17: =J17+K17+L17+M17 -> 29 | AY17: =AW17 -> 0 | AZ17: =AE17+AK17+AR17+AY17 -> 18
D18: Seguridad Industrial | E18: 11 | F18: Accidentes de trabajo | G18: Mensual | H18: Cantidad | I18: 0 | J18: 0 | K18: 0 | L18: 0 | M18: 0 | N18: n/a | P18: SI | Q18: 0 | R18: No hubo accidentes en el mes. | S18: NA | T18: NA | U18: NA | V18: Martín Ávila | Z18: 0 | AA18: 1 | AB18: 0 | AC18: =SUM(Z18:AB18) -> 1 | AD18: =J18 -> 0 | AE18: =AC18 -> 1 | AF18: 3 | AG18: 0 | AH18: 1 | AI18: =SUM(AF18:AH18) -> 4 | AJ18: =J18+K18 -> 0 | AK18: =AI18 -> 4 | AL18: =AE18+AK18 -> 5 | AM18: =Q18 -> 0 | AP18: =SUM(AM18:AO18) -> 0 | AQ18: =J18+K18+L18 -> 0 | AR18: =AP18 -> 0 | AS18: =AE18+AK18+AR18 -> 5 | AW18: =SUM(AT18:AV18) -> 0 | AX18: =J18+K18+L18+M18 -> 0 | AY18: =AW18 -> 0 | AZ18: =AE18+AK18+AR18+AY18 -> 5
D19: Licitaciones | E19: 12 | F19: Cumplir con el proceso de licitación pública o simplificada | G19: Mensual | H19: Porcentaje | I19: 100 | J19: 25 | K19: 25 | L19: 25 | M19: 25 | N19: X | P19: SI | Q19: 100 | R19: Se cumplió al 100% con el proceso de licitación pública o simplificada. | S19: NA | T19: NA | U19: NA | V19: Daniel Sandoval | Z19: 100 | AA19: 100 | AB19: 100 | AC19: =AVERAGE(Z19:AB19) -> 100 | AD19: =J19 -> 25 | AE19: =(J19*AC19)/I19 -> 25 | AF19: 100 | AG19: 100 | AH19: 100 | AI19: =AVERAGE(AF19:AH19) -> 100 | AJ19: =J19+K19 -> 50 | AK19: =(K19*AI19)/I19 -> 25 | AL19: =AE19+AK19 -> 50 | AM19: =Q19 -> 100 | AP19: =AVERAGE(AM19:AO19) -> 100 | AQ19: =J19+K19+L19 -> 75 | AR19: =(L19*AP19)/I19 -> 25 | AS19: =AE19+AK19+AR19 -> 75 | AW19: =AVERAGE(AT19:AV19) -> #DIV/0! | AX19: =J19+K19+L19+M19 -> 100 | AY19: =(M19*AW19)/I19 -> #DIV/0! | AZ19: =AE19+AK19+AR19+AY19 -> #DIV/0!
E20: 13 | F20: Cumplir con el proceso de adjudicación directa. | G20: Mensual | H20: Porcentaje | I20: 100 | J20: 25 | K20: 25 | L20: 25 | M20: 25 | N20: X | P20: SI | Q20: 100 | R20: Se cumplió al 100% con el proceso de adjudicación directa. | S20: NA | T20: NA | U20: NA | V20: Daniel Sandoval | Z20: 100 | AA20: 100 | AB20: 100 | AC20: =AVERAGE(Z20:AB20) -> 100 | AD20: =J20 -> 25 | AE20: =(J20*AC20)/I20 -> 25 | AF20: 100 | AG20: 100 | AH20: 100 | AI20: =AVERAGE(AF20:AH20) -> 100 | AJ20: =J20+K20 -> 50 | AK20: =(K20*AI20)/I20 -> 25 | AL20: =AE20+AK20 -> 50 | AM20: =Q20 -> 100 | AP20: =AVERAGE(AM20:AO20) -> 100 | AQ20: =J20+K20+L20 -> 75 | AR20: =(L20*AP20)/I20 -> 25 | AS20: =AE20+AK20+AR20 -> 75 | AW20: =AVERAGE(AT20:AV20) -> #DIV/0! | AX20: =J20+K20+L20+M20 -> 100 | AY20: =(M20*AW20)/I20 -> #DIV/0! | AZ20: =AE20+AK20+AR20+AY20 -> #DIV/0!
C21: Técnica | D21: Trámites Técnicos | E21: 14 | F21: Índice de programas federales gestionados | G21: Semestral | H21: Programa | I21: 1 | J21: 1 | K21: 0 | L21: 0 | M21: 0 | N21: X | P21: SI | Q21: 0 | R21: Durante el mes de marzo el organismo se adherió al programa federal PEAS. | S21: NA | T21: NA | U21: NA | V21: Lety Valle | Z21: 0 | AA21: 0 | AB21: 0 | AC21: =SUM(Z21:AB21) -> 0 | AD21: =J21 -> 1 | AE21: =AC21 -> 0 | AF21: 0 | AG21: 0 | AH21: 1 | AI21: =SUM(AF21:AH21) -> 1 | AJ21: =J21+K21 -> 1 | AK21: =AI21 -> 1 | AL21: =AE21+AK21 -> 1 | AM21: =Q21 -> 0 | AP21: =SUM(AM21:AO21) -> 0 | AQ21: =J21+K21+L21 -> 1 | AR21: =AP21 -> 0 | AS21: =AE21+AK21+AR21 -> 1 | AW21: =SUM(AT21:AV21) -> 0 | AX21: =J21+K21+L21+M21 -> 1 | AY21: =AW21 -> 0 | AZ21: =AE21+AK21+AR21+AY21 -> 1
A22: 3 | B22: Mantenimiento y Calibración | C22: Administrativa | D22: Informática | E22: 15 | F22: Cumplir con el programa de mantenimiento preventivo de los equipos de cómputo. | G22: Mensual | H22: Porcentaje | I22: 100 | J22: 25 | K22: 25 | L22: 25 | M22: 25 | N22: X | P22: SI | Q22: 100 | R22: Se cumplió al 100% con el programa de mantenimiento a los equipos de cómputo. | S22: NA | T22: NA | U22: NA | V22: Lizbeth Campa | Z22: 100 | AA22: 100 | AB22: 100 | AC22: =AVERAGE(Z22:AB22) -> 100 | AD22: =J22 -> 25 | AE22: =(J22*AC22)/I22 -> 25 | AF22: 100 | AG22: 100 | AH22: 100 | AI22: =AVERAGE(AF22:AH22) -> 100 | AJ22: =J22+K22 -> 50 | AK22: =(K22*AI22)/I22 -> 25 | AL22: =AE22+AK22 -> 50 | AM22: =Q22 -> 100 | AP22: =AVERAGE(AM22:AO22) -> 100 | AQ22: =J22+K22+L22 -> 75 | AR22: =(L22*AP22)/I22 -> 25 | AS22: =AE22+AK22+AR22 -> 75 | AW22: =AVERAGE(AT22:AV22) -> #DIV/0! | AX22: =J22+K22+L22+M22 -> 100 | AY22: =(M22*AW22)/I22 -> #DIV/0! | AZ22: =AE22+AK22+AR22+AY22 -> #DIV/0!
E23: 16 | F23: Solucionar las solicitudes de servicio. | G23: Mensual | H23: Porcentaje | I23: 95 | J23: 24 | K23: 24 | L23: 24 | M23: 23 | N23: X | P23: SI | Q23: 97 | R23: Se cumplió al 97% con la solución de las solicitudes de servicio. | S23: NA | T23: NA | U23: NA | V23: Lizbeth Campa | Z23: 96 | AA23: 100 | AB23: 96 | AC23: =AVERAGE(Z23:AB23) -> 97.333333 | AD23: =J23 -> 24 | AE23: =(J23*AC23)/I23 -> 24.589474 | AF23: 95 | AG23: 100 | AH23: 100 | AI23: =AVERAGE(AF23:AH23) -> 98.333333 | AJ23: =J23+K23 -> 48 | AK23: =(K23*AI23)/I23 -> 24.842105 | AL23: =AE23+AK23 -> 49.431579 | AM23: =Q23 -> 97 | AP23: =AVERAGE(AM23:AO23) -> 97 | AQ23: =J23+K23+L23 -> 72 | AR23: =(L23*AP23)/I23 -> 24.505263 | AS23: =AE23+AK23+AR23 -> 73.936842 | AW23: =AVERAGE(AT23:AV23) -> #DIV/0! | AX23: =J23+K23+L23+M23 -> 95 | AY23: =(M23*AW23)/I23 -> #DIV/0! | AZ23: =AE23+AK23+AR23+AY23 -> #DIV/0!
E24: 17 | F24: Asegurar la disponibilidad de los servicios críticos de informática. | G24: Mensual | H24: Porcentaje | I24: 95 | J24: 24 | K24: 24 | L24: 24 | M24: 23 | O24: X | P24: SI | Q24: 100 | R24: Se cumplió al 100% con la disponibilidad de los servicios críticos de informática. | S24: NA | T24: NA | U24: NA | V24: Lizbeth Campa | Z24: 100 | AA24: 100 | AB24: 100 | AC24: =AVERAGE(Z24:AB24) -> 100 | AD24: =J24 -> 24 | AE24: =(J24*AC24)/I24 -> 25.263158 | AF24: 100 | AG24: 100 | AH24: 100 | AI24: =AVERAGE(AF24:AH24) -> 100 | AJ24: =J24+K24 -> 48 | AK24: =(K24*AI24)/I24 -> 25.263158 | AL24: =AE24+AK24 -> 50.526316 | AM24: =Q24 -> 100 | AP24: =AVERAGE(AM24:AO24) -> 100 | AQ24: =J24+K24+L24 -> 72 | AR24: =(L24*AP24)/I24 -> 25.263158 | AS24: =AE24+AK24+AR24 -> 75.789474 | AW24: =AVERAGE(AT24:AV24) -> #DIV/0! | AX24: =J24+K24+L24+M24 -> 95 | AY24: =(M24*AW24)/I24 -> #DIV/0! | AZ24: =AE24+AK24+AR24+AY24 -> #DIV/0!
D25: Seguridad Industrial | E25: 18 | F25: Revisión de instalaciones | G25: Mensual | H25: Porcentaje | I25: 100 | J25: 25 | K25: 25 | L25: 25 | M25: 25 | N25: X | P25: SI | Q25: 100 | R25: Se cumplió al 100% con el programa de revisión de instalaciones. | S25: NA | T25: NA | U25: NA | V25: Martín Ávila | Z25: 100 | AA25: 100 | AB25: 100 | AC25: =AVERAGE(Z25:AB25) -> 100 | AD25: =J25 -> 25 | AE25: =(J25*AC25)/I25 -> 25 | AF25: 100 | AG25: 100 | AH25: 100 | AI25: =AVERAGE(AF25:AH25) -> 100 | AJ25: =J25+K25 -> 50 | AK25: =(K25*AI25)/I25 -> 25 | AL25: =AE25+AK25 -> 50 | AM25: =Q25 -> 100 | AP25: =AVERAGE(AM25:AO25) -> 100 | AQ25: =J25+K25+L25 -> 75 | AR25: =(L25*AP25)/I25 -> 25 | AS25: =AE25+AK25+AR25 -> 75 | AW25: =AVERAGE(AT25:AV25) -> #DIV/0! | AX25: =J25+K25+L25+M25 -> 100 | AY25: =(M25*AW25)/I25 -> #DIV/0! | AZ25: =AE25+AK25+AR25+AY25 -> #DIV/0!
D26: Mtto. y servicios generales | E26: 19 | F26: Cumplimiento al programa anual de mantenimiento preventivo a edificios. | G26: Mensual | H26: Cantidad | I26: 804 | J26: 202 | K26: 203 | L26: 202 | M26: 197 | N26: X | P26: NO | Q26: 30 | R26: Se cumplió con el programa anual de mantenimiento preventivo a edificios. | S26: RC 09/2026 | T26: NA | U26: NA | V26: Jazmín Sortillón | Z26: 65 | AA26: 65 | AB26: 72 | AC26: =SUM(Z26:AB26) -> 202 | AD26: =J26 -> 202 | AE26: =AC26 -> 202 | AF26: 66 | AG26: 63 | AH26: 74 | AI26: =SUM(AF26:AH26) -> 203 | AJ26: =J26+K26 -> 405 | AK26: =AI26 -> 203 | AL26: =AE26+AK26 -> 405 | AM26: =Q26 -> 30 | AP26: =SUM(AM26:AO26) -> 30 | AQ26: =J26+K26+L26 -> 607 | AR26: =AP26 -> 30 | AS26: =AE26+AK26+AR26 -> 435 | AW26: =SUM(AT26:AV26) -> 0 | AX26: =J26+K26+L26+M26 -> 804 | AY26: =AW26 -> 0 | AZ26: =AE26+AK26+AR26+AY26 -> 435
E27: 20 | F27: Cumplimiento al programa anual de mantenimiento preventivo para vehículos de transporte | G27: Mensual | H27: Porcentaje | I27: 95 | J27: 24 | K27: 24 | L27: 24 | M27: 23 | O27: X | P27: SI | Q27: 100 | R27: Se cumplió al 100% con el programa anual de mantenimiento preventivo para vehículos de transporte. | S27: NA | T27: NA | U27: NA | V27: Jazmín Sortillón | Z27: 100 | AA27: 100 | AB27: 100 | AC27: =AVERAGE(Z27:AB27) -> 100 | AD27: =J27 -> 24 | AE27: =(J27*AC27)/I27 -> 25.263158 | AF27: 100 | AG27: 100 | AH27: 100 | AI27: =AVERAGE(AF27:AH27) -> 100 | AJ27: =J27+K27 -> 48 | AK27: =(K27*AI27)/I27 -> 25.263158 | AL27: =AE27+AK27 -> 50.526316 | AM27: =Q27 -> 100 | AP27: =AVERAGE(AM27:AO27) -> 100 | AQ27: =J27+K27+L27 -> 72 | AR27: =(L27*AP27)/I27 -> 25.263158 | AS27: =AE27+AK27+AR27 -> 75.789474 | AW27: =AVERAGE(AT27:AV27) -> #DIV/0! | AX27: =J27+K27+L27+M27 -> 95 | AY27: =(M27*AW27)/I27 -> #DIV/0! | AZ27: =AE27+AK27+AR27+AY27 -> #DIV/0!
E28: 21 | F28: Cumplimiento al abastecimiento de las dotaciones de gasolina autorizadas. | G28: Mensual | H28: Reportes | I28: 59 | J28: 14 | K28: 15 | L28: 15 | M28: 15 | N28: X | P28: SI | Q28: 5 | R28: Se cumplió con el abastecimiento de las dotaciones de gasolina. | S28: NA | T28: NA | U28: NA | V28: Jazmín Sortillón | Z28: 5 | AA28: 4 | AB28: 5 | AC28: =SUM(Z28:AB28) -> 14 | AD28: =J28 -> 14 | AE28: =AC28 -> 14 | AF28: 5 | AG28: 5 | AH28: 5 | AI28: =SUM(AF28:AH28) -> 15 | AJ28: =J28+K28 -> 29 | AK28: =AI28 -> 15 | AL28: =AE28+AK28 -> 29 | AM28: =Q28 -> 5 | AP28: =SUM(AM28:AO28) -> 5 | AQ28: =J28+K28+L28 -> 44 | AR28: =AP28 -> 5 | AS28: =AE28+AK28+AR28 -> 34 | AW28: =SUM(AT28:AV28) -> 0 | AX28: =J28+K28+L28+M28 -> 59 | AY28: =AW28 -> 0 | AZ28: =AE28+AK28+AR28+AY28 -> 34
E29: 22 | F29: Cumplimiento a las solicitudes de mantenimiento correctivo para vehículos de transporte | G29: Trimestral | H29: Porcentaje | I29: 95 | J29: 24 | K29: 24 | L29: 24 | M29: 23 | O29: X | P29: SI | Q29: 100 | R29: Se cumplió al 100% con las solicitudes de mantenimiento correctivo para vehículos de transporte. | S29: NA | T29: NA | U29: NA | V29: Jazmín Sortillón | Z29: 100 | AA29: 100 | AB29: 100 | AC29: =AVERAGE(Z29:AB29) -> 100 | AD29: =J29 -> 24 | AE29: =(J29*AC29)/I29 -> 25.263158 | AF29: 100 | AG29: 100 | AH29: 100 | AI29: =AVERAGE(AF29:AH29) -> 100 | AJ29: =J29+K29 -> 48 | AK29: =(K29*AI29)/I29 -> 25.263158 | AL29: =AE29+AK29 -> 50.526316 | AM29: =Q29 -> 100 | AP29: =AVERAGE(AM29:AO29) -> 100 | AQ29: =J29+K29+L29 -> 72 | AR29: =(L29*AP29)/I29 -> 25.263158 | AS29: =AE29+AK29+AR29 -> 75.789474 | AW29: =AVERAGE(AT29:AV29) -> #DIV/0! | AX29: =J29+K29+L29+M29 -> 95 | AY29: =(M29*AW29)/I29 -> #DIV/0! | AZ29: =AE29+AK29+AR29+AY29 -> #DIV/0!
E30: 23 | F30: Cumplimiento al programa anual de intendencia | G30: Mensual | H30: Registros | I30: 1768 | J30: 442 | K30: 442 | L30: 442 | M30: 442 | N30: X | P30: SI | Q30: 136 | R30: Se cumplió con el programa anual de intendencia. | S30: NA | T30: NA | U30: NA | V30: Jazmín Sortillón | Y30: 170 | Z30: 136 | AA30: 136 | AB30: 170 | AC30: =SUM(Z30:AB30) -> 442 | AD30: =J30 -> 442 | AE30: =AC30 -> 442 | AF30: 136 | AG30: 136 | AH30: 170 | AI30: =SUM(AF30:AH30) -> 442 | AJ30: =J30+K30 -> 884 | AK30: =AI30 -> 442 | AL30: =AE30+AK30 -> 884 | AM30: =Q30 -> 136 | AP30: =SUM(AM30:AO30) -> 136 | AQ30: =J30+K30+L30 -> 1326 | AR30: =AP30 -> 136 | AS30: =AE30+AK30+AR30 -> 1020 | AW30: =SUM(AT30:AV30) -> 0 | AX30: =J30+K30+L30+M30 -> 1768 | AY30: =AW30 -> 0 | AZ30: =AE30+AK30+AR30+AY30 -> 1020
C31: Técnica | D31: Mantenimiento de Redes | E31: 24 | F31: Atender los reportes de los usuarios de la ciudad. | G31: Mensual | H31: Porcentaje | I31: 100 | J31: 25 | K31: 25 | L31: 25 | M31: 25 | O31: X | P31: SI | Q31: 103 | R31: Se cumplió con la atención de reportes de los usuarios. | S31: NA | T31: AC 14/2025 | U31: NA | V31: Denis Arias | W31: Vence 30 Diciembre 2025. Replanteo al 31 Diciembre 2026. | Z31: 108 | AA31: 109 | AB31: 143 | AC31: =AVERAGE(Z31:AB31) -> 120 | AD31: =J31 -> 25 | AE31: =(J31*AC31)/I31 -> 30 | AF31: 120 | AG31: 120 | AH31: 101 | AI31: =AVERAGE(AF31:AH31) -> 113.66667 | AJ31: =J31+K31 -> 50 | AK31: =(K31*AI31)/I31 -> 28.416667 | AL31: =AE31+AK31 -> 58.416667 | AM31: =Q31 -> 103 | AP31: =AVERAGE(AM31:AO31) -> 103 | AQ31: =J31+K31+L31 -> 75 | AR31: =(L31*AP31)/I31 -> 25.75 | AS31: =AE31+AK31+AR31 -> 84.166667 | AW31: =AVERAGE(AT31:AV31) -> #DIV/0! | AX31: =J31+K31+L31+M31 -> 100 | AY31: =(M31*AW31)/I31 -> #DIV/0! | AZ31: =AE31+AK31+AR31+AY31 -> #DIV/0!
D32: Control de Calidad | E32: 25 | F32: Cumplir con programa de calibración y verificación de equipos de medición. | G32: Trimestral | H32: Calibraciones y/o Verificaciones | I32: 157 | J32: 31 | K32: 43 | L32: 47 | M32: 36 | O32: X | P32: SI | Q32: 0 | R32: Se cumple con el programa de calibraciones de equipos de medición. | S32: NA | T32: NA | U32: NA | V32: Lenia Luzanilla | Z32: 0 | AA32: 0 | AB32: 28 | AC32: =SUM(Z32:AB32) -> 28 | AD32: =J32 -> 31 | AE32: =AC32 -> 28 | AF32: 0 | AG32: 0 | AH32: 45 | AI32: =SUM(AF32:AH32) -> 45 | AJ32: =J32+K32 -> 74 | AK32: =AI32 -> 45 | AL32: =AE32+AK32 -> 73 | AM32: =Q32 -> 0 | AP32: =SUM(AM32:AO32) -> 0 | AQ32: =J32+K32+L32 -> 121 | AR32: =AP32 -> 0 | AS32: =AE32+AK32+AR32 -> 73 | AW32: =SUM(AT32:AV32) -> 0 | AX32: =J32+K32+L32+M32 -> 157 | AY32: =AW32 -> 0 | AZ32: =AE32+AK32+AR32+AY32 -> 73
D33: Plantas Potabilizadoras | E33: 26 | F33: Índice de cumplimiento de los programas de mantenimiento a instalaciones y mantenimiento electromecánico preventivo y correctivo | G33: Mensual | H33: Porcentaje | I33: 100 | J33: 25 | K33: 25 | L33: 25 | M33: 25 | O33: X | P33: SI | Q33: 100 | R33: Se cumplió al 100% con los programas de mantenimiento a instalaciones y mantenimiento electromecánico preventivo y correctivo. | S33: NA | T33: AC 06/2026 | U33: NA | V33: Aracely Galvez | W33: Vence 31 Diciembre 2026. | Z33: 100 | AA33: 100 | AB33: 100 | AC33: =AVERAGE(Z33:AB33) -> 100 | AD33: =J33 -> 25 | AE33: =(J33*AC33)/I33 -> 25 | AF33: 100 | AG33: 100 | AH33: 100 | AI33: =AVERAGE(AF33:AH33) -> 100 | AJ33: =J33+K33 -> 50 | AK33: =(K33*AI33)/I33 -> 25 | AL33: =AE33+AK33 -> 50 | AM33: =Q33 -> 100 | AP33: =AVERAGE(AM33:AO33) -> 100 | AQ33: =J33+K33+L33 -> 75 | AR33: =(L33*AP33)/I33 -> 25 | AS33: =AE33+AK33+AR33 -> 75 | AW33: =AVERAGE(AT33:AV33) -> #DIV/0! | AX33: =J33+K33+L33+M33 -> 100 | AY33: =(M33*AW33)/I33 -> #DIV/0! | AZ33: =AE33+AK33+AR33+AY33 -> #DIV/0!
D34: Alcantarillado y Saneamiento | E34: 27 | F34: Programa de mantenimiento de redes sanitaria | G34: Mensual | H34: Porcentaje | I34: 100 | J34: 25 | K34: 25 | L34: 25 | M34: 25 | O34: X | P34: SI | Q34: 107 | R34: Se cumplió con el programa de mantenimiento de redes sanitaria. | S34: NA | T34: NA | U34: NA | V34: Jorge Fernández | Z34: 107 | AA34: 105 | AB34: 107 | AC34: =AVERAGE(Z34:AB34) -> 106.33333 | AD34: =J34 -> 25 | AE34: =(J34*AC34)/I34 -> 26.583333 | AF34: 110 | AG34: 105 | AH34: 107 | AI34: =AVERAGE(AF34:AH34) -> 107.33333 | AJ34: =J34+K34 -> 50 | AK34: =(K34*AI34)/I34 -> 26.833333 | AL34: =AE34+AK34 -> 53.416667 | AM34: =Q34 -> 107 | AP34: =AVERAGE(AM34:AO34) -> 107 | AQ34: =J34+K34+L34 -> 75 | AR34: =(L34*AP34)/I34 -> 26.75 | AS34: =AE34+AK34+AR34 -> 80.166667 | AW34: =AVERAGE(AT34:AV34) -> #DIV/0! | AX34: =J34+K34+L34+M34 -> 100 | AY34: =(M34*AW34)/I34 -> #DIV/0! | AZ34: =AE34+AK34+AR34+AY34 -> #DIV/0!
D35: Suburbano Técnico | E35: 28 | F35: Cumplir con el programa anual de mantenimiento preventivo a equipos de cloración y dosificación | G35: Semestral | H35: Porcentaje | I35: 100 | J35: 0 | K35: 50 | L35: 0 | M35: 50 | O35: X | P35: SI | Q35: 0 | R35: Se cumplió al 100% con el programa de mantenimiento preventivo a equipos de cloración y dosificación del semestre. | S35: NA | T35: NA | U35: NA | V35: Mario Mendoza | Z35: 0 | AA35: 0 | AB35: 0 | AC35: =AVERAGE(Z35:AB35) -> 0 | AD35: =J35 -> 0 | AE35: =(J35*AC35)/I35 -> 0 | AF35: 0 | AG35: 0 | AH35: 100 | AI35: =AH35 -> 100 | AJ35: =J35+K35 -> 50 | AK35: =(K35*AI35)/I35 -> 50 | AL35: =AE35+AK35 -> 50 | AM35: =Q35 -> 0 | AP35: =AVERAGE(AM35:AO35) -> 0 | AQ35: =J35+K35+L35 -> 50 | AR35: =(L35*AP35)/I35 -> 0 | AS35: =AE35+AK35+AR35 -> 50 | AW35: =AV35 -> 0 | AX35: =J35+K35+L35+M35 -> 100 | AY35: =(M35*AW35)/I35 -> 0 | AZ35: =AE35+AK35+AR35+AY35 -> 50
E36: 29 | F36: Cumplir con el programa anual de mantenimiento preventivo y toma de parámetros eléctricos y mecánicos | G36: Mensual | H36: Porcentaje | I36: 100 | J36: 25 | K36: 25 | L36: 25 | M36: 25 | O36: X | P36: SI | Q36: 100 | R36: Se cumplió al 100% con el programa de mantenimiento preventivo. | S36: NA | T36: NA | U36: NA | V36: Mario Mendoza | Z36: 100 | AA36: 100 | AB36: 100 | AC36: =AVERAGE(Z36:AB36) -> 100 | AD36: =J36 -> 25 | AE36: =(J36*AC36)/I36 -> 25 | AF36: 100 | AG36: 100 | AH36: 100 | AI36: =AVERAGE(AF36:AH36) -> 100 | AJ36: =J36+K36 -> 50 | AK36: =(K36*AI36)/I36 -> 25 | AL36: =AE36+AK36 -> 50 | AM36: =Q36 -> 100 | AP36: =AVERAGE(AM36:AO36) -> 100 | AQ36: =J36+K36+L36 -> 75 | AR36: =(L36*AP36)/I36 -> 25 | AS36: =AE36+AK36+AR36 -> 75 | AW36: =AVERAGE(AT36:AV36) -> #DIV/0! | AX36: =J36+K36+L36+M36 -> 100 | AY36: =(M36*AW36)/I36 -> #DIV/0! | AZ36: =AE36+AK36+AR36+AY36 -> #DIV/0!
A37: 4 | B37: Comercialización | C37: Comercial | D37: Padrón de Usuarios | E37: 30 | F37: Cumplir con el programa de mantenimiento anual de padrón de usuarios. | G37: Mensual | H37: Visitas | I37: 250000 | J37: 62500 | K37: 62500 | L37: 62500 | M37: 62500 | N37: X | P37: SI | Q37: 29892 | R37: Se cumplió con el programa anual de padrón de usuarios. | S37: NA | T37: NA | U37: NA | V37: Ana Lilián Núñez | Z37: 22496 | AA37: 23800 | AB37: 29089 | AC37: =SUM(Z37:AB37) -> 75385 | AD37: =J37 -> 62500 | AE37: =AC37 -> 75385 | AF37: 26161 | AG37: 24760 | AH37: 22733 | AI37: =SUM(AF37:AH37) -> 73654 | AJ37: =J37+K37 -> 125000 | AK37: =AI37 -> 73654 | AL37: =AE37+AK37 -> 149039 | AM37: =Q37 -> 29892 | AP37: =SUM(AM37:AO37) -> 29892 | AQ37: =J37+K37+L37 -> 187500 | AR37: =AP37 -> 29892 | AS37: =AE37+AK37+AR37 -> 178931 | AW37: =SUM(AT37:AV37) -> 0 | AX37: =J37+K37+L37+M37 -> 250000 | AY37: =AW37 -> 0 | AZ37: =AE37+AK37+AR37+AY37 -> 178931
E38: 31 | F38: Cobertura de Agua Potable | G38: Trimestral | H38: Porcentaje | I38: 95 | J38: 24 | K38: 24 | L38: 24 | M38: 23 | N38: X | P38: SI | Q38: 0 | R38: Se cumplió con la cobertura de agua potable. | S38: NA | T38: NA | U38: NA | V38: Ana Lilián Núñez | Z38: 0 | AA38: 0 | AB38: 98.34 | AC38: =SUM(Z38:AB38) -> 98.34 | AD38: =J38 -> 24 | AE38: =(J38*AC38)/I38 -> 24.843789 | AF38: 0 | AG38: 0 | AH38: 96.62 | AI38: =SUM(AF38:AH38) -> 96.62 | AJ38: =J38+K38 -> 48 | AK38: =(K38*AI38)/I38 -> 24.409263 | AL38: =AE38+AK38 -> 49.253053 | AM38: =Q38 -> 0 | AP38: =SUM(AM38:AO38) -> 0 | AQ38: =J38+K38+L38 -> 72 | AR38: =(L38*AP38)/I38 -> 0 | AS38: =AE38+AK38+AR38 -> 49.253053 | AW38: =SUM(AT38:AV38) -> 0 | AX38: =J38+K38+L38+M38 -> 95 | AY38: =(M38*AW38)/I38 -> 0 | AZ38: =AE38+AK38+AR38+AY38 -> 49.253053
D39: Control y Servicios | E39: 32 | F39: Recaudación por visitas efectivas. | G39: Mensual | H39: Pesos | I39: 100000000 | J39: 25000000 | K39: 25000000 | L39: 25000000 | M39: 25000000 | O39: X | P39: SI | Q39: 17355517 | R39: Se logró superar la meta de recaudación por visitas efectivas. | S39: NA | T39: NA | U39: NA | V39: Irasema Moreno | Z39: 17624327 | AA39: 15259649 | AB39: 17252966 | AC39: =SUM(Z39:AB39) -> 50136942 | AD39: =J39 -> 25000000 | AE39: =AC39 -> 50136942 | AF39: 15378065 | AG39: 17262698 | AH39: 16074509 | AI39: =SUM(AF39:AH39) -> 48715271 | AJ39: =J39+K39 -> 50000000 | AK39: =AI39 -> 48715271 | AL39: =AE39+AK39 -> 98852213 | AM39: =Q39 -> 17355517 | AP39: =SUM(AM39:AO39) -> 17355517 | AQ39: =J39+K39+L39 -> 75000000 | AR39: =AP39 -> 17355517 | AS39: =AE39+AK39+AR39 -> 1.1620773e+08 | AW39: =SUM(AT39:AV39) -> 0 | AX39: =J39+K39+L39+M39 -> 100000000 | AY39: =AW39 -> 0 | AZ39: =AE39+AK39+AR39+AY39 -> 1.1620773e+08
E40: 33 | F40: Recaudación por cobranza especial. | G40: Mensual | H40: Pesos | I40: 80000000 | J40: 20000000 | K40: 20000000 | L40: 20000000 | M40: 20000000 | O40: X | P40: SI | Q40: 11539795 | R40: Se logró superar la meta de recaudación por cobranza especial. | S40: NA | T40: NA | U40: NA | V40: Irasema Moreno | Z40: 10383362 | AA40: 8990596.7 | AB40: 12356619 | AC40: =SUM(Z40:AB40) -> 31730578 | AD40: =J40 -> 20000000 | AE40: =AC40 -> 31730578 | AF40: 10308285 | AG40: 10347694 | AH40: 11095969 | AI40: =SUM(AF40:AH40) -> 31751948 | AJ40: =J40+K40 -> 40000000 | AK40: =AI40 -> 31751948 | AL40: =AE40+AK40 -> 63482526 | AM40: =Q40 -> 11539795 | AP40: =SUM(AM40:AO40) -> 11539795 | AQ40: =J40+K40+L40 -> 60000000 | AR40: =AP40 -> 11539795 | AS40: =AE40+AK40+AR40 -> 75022320 | AW40: =SUM(AT40:AV40) -> 0 | AX40: =J40+K40+L40+M40 -> 80000000 | AY40: =AW40 -> 0 | AZ40: =AE40+AK40+AR40+AY40 -> 75022320
D41: Verificación y Lectura | E41: 34 | F41: Cumplir con el calendario mensual de facturación. | G41: Mensual | H41: Sectores | I41: 216 | J41: 54 | K41: 54 | L41: 54 | M41: 54 | O41: X | P41: SI | Q41: 18 | R41: Se cumplió con el calendario mensual de facturación. | S41: NA | T41: NA | U41: NA | V41: Angélica Meraz | Z41: 18 | AA41: 18 | AB41: 18 | AC41: =SUM(Z41:AB41) -> 54 | AD41: =J41 -> 54 | AE41: =AC41 -> 54 | AF41: 18 | AG41: 18 | AH41: 18 | AI41: =SUM(AF41:AH41) -> 54 | AJ41: =J41+K41 -> 108 | AK41: =AI41 -> 54 | AL41: =AE41+AK41 -> 108 | AM41: =Q41 -> 18 | AP41: =SUM(AM41:AO41) -> 18 | AQ41: =J41+K41+L41 -> 162 | AR41: =AP41 -> 18 | AS41: =AE41+AK41+AR41 -> 126 | AW41: =SUM(AT41:AV41) -> 0 | AX41: =J41+K41+L41+M41 -> 216 | AY41: =AW41 -> 0 | AZ41: =AE41+AK41+AR41+AY41 -> 126
E42: 35 | F42: Porcentaje de error en toma de lectura. | G42: Mensual | H42: Porcentaje | I42: 0.5 | J42: 0.125 | K42: 0.125 | L42: 0.125 | M42: 0.125 | O42: X | P42: SI | Q42: 0.5 | R42: Se cumplió con el porcentaje de error en toma de lectura. | S42: NA | T42: NA | U42: NA | V42: Martha Valenzuela | Z42: 0.45 | AA42: 0.42 | AB42: 0.41 | AC42: =AVERAGE(Z42:AB42) -> 0.42666667 | AD42: =J42 -> 0.125 | AE42: =(J42*AC42)/I42 -> 0.10666667 | AF42: 0.48 | AG42: 0.48 | AH42: 0.48 | AI42: =AVERAGE(AF42:AH42) -> 0.48 | AJ42: =J42+K42 -> 0.25 | AK42: =(K42*AI42)/I42 -> 0.12 | AL42: =AE42+AK42 -> 0.22666667 | AM42: =Q42 -> 0.5 | AP42: =AVERAGE(AM42:AO42) -> 0.5 | AQ42: =J42+K42+L42 -> 0.375 | AR42: =(L42*AP42)/I42 -> 0.125 | AS42: =AE42+AK42+AR42 -> 0.35166667 | AW42: =AVERAGE(AT42:AV42) -> #DIV/0! | AX42: =J42+K42+L42+M42 -> 0.5 | AY42: =(M42*AW42)/I42 -> #DIV/0! | AZ42: =AE42+AK42+AR42+AY42 -> #DIV/0!
E43: 36 | F43: Cobertura de Micromedición en área urbana | G43: Mensual | H43: Porcentaje | I43: 60 | J43: 15 | K43: 15 | L43: 15 | M43: 15 | O43: X | P43: SI | Q43: 61.71 | R43: Se cumplió con la cobertura de Micromedición del área urbana, | S43: NA | T43: NA | U43: NA | V43: Martha Valenzuela | Z43: 61.08 | AA43: 61.09 | AB43: 61.22 | AC43: =AVERAGE(Z43:AB43) -> 61.13 | AD43: =J43 -> 15 | AE43: =(J43*AC43)/I43 -> 15.2825 | AF43: 61.26 | AG43: 61.49 | AH43: 61.72 | AI43: =AVERAGE(AF43:AH43) -> 61.49 | AJ43: =J43+K43 -> 30 | AK43: =(K43*AI43)/I43 -> 15.3725 | AL43: =AE43+AK43 -> 30.655 | AM43: =Q43 -> 61.71 | AP43: =AVERAGE(AM43:AO43) -> 61.71 | AQ43: =J43+K43+L43 -> 45 | AR43: =(L43*AP43)/I43 -> 15.4275 | AS43: =AE43+AK43+AR43 -> 46.0825 | AW43: =AVERAGE(AT43:AV43) -> #DIV/0! | AX43: =J43+K43+L43+M43 -> 60 | AY43: =(M43*AW43)/I43 -> #DIV/0! | AZ43: =AE43+AK43+AR43+AY43 -> #DIV/0!
D44: Agencia Providencia | E44: 37 | F44: Cumplir con el presupuesto de ingresos en la gerencia Providencia. | G44: Mensual | H44: Porcentaje | I44: 100 | J44: 25 | K44: 25 | L44: 25 | M44: 25 | O44: X | P44: NO | Q44: 54.16 | R44: No se cumplió con el presupuesto programado de ingresos del mes. | S44: NA | T44: AC 05/2026 | U44: NA | V44: Juan Compián | W44: Vence 19 Junio 2026. Replanteada al 13 de Enero 2027. | Z44: 55.63 | AA44: 44.87 | AB44: 60.21 | AC44: =AVERAGE(Z44:AB44) -> 53.57 | AD44: =J44 -> 25 | AE44: =(J44*AC44)/I44 -> 13.3925 | AF44: 45.25 | AG44: 39.84 | AH44: 60.3 | AI44: =AVERAGE(AF44:AH44) -> 48.463333 | AJ44: =J44+K44 -> 50 | AK44: =(K44*AI44)/I44 -> 12.115833 | AL44: =AE44+AK44 -> 25.508333 | AM44: =Q44 -> 54.16 | AP44: =AVERAGE(AM44:AO44) -> 54.16 | AQ44: =J44+K44+L44 -> 75 | AR44: =(L44*AP44)/I44 -> 13.54 | AS44: =AE44+AK44+AR44 -> 39.048333 | AW44: =AVERAGE(AT44:AV44) -> #DIV/0! | AX44: =J44+K44+L44+M44 -> 100 | AY44: =(M44*AW44)/I44 -> #DIV/0! | AZ44: =AE44+AK44+AR44+AY44 -> #DIV/0!
D45: Agencia Esperanza | E45: 38 | F45: Cumplir con el presupuesto de ingresos en la gerencia Esperanza | G45: Mensual | H45: Porcentaje | I45: 100 | J45: 25 | K45: 25 | L45: 25 | M45: 25 | O45: X | P45: NO | Q45: 79.39 | R45: No se cumplió con el presupuesto programado de ingresos del mes. | S45: NA | T45: AC 03/2026 | U45: NA | V45: Raúl Reichel | W45: Vence 19 Junio 2026. Replanteada al 13 de Enero 2027. | Z45: 113.41 | AA45: 75.67 | AB45: 82.49 | AC45: =AVERAGE(Z45:AB45) -> 90.523333 | AD45: =J45 -> 25 | AE45: =(J45*AC45)/I45 -> 22.630833 | AF45: 71.48 | AG45: 70.91 | AH45: 63.5 | AI45: =AVERAGE(AF45:AH45) -> 68.63 | AJ45: =J45+K45 -> 50 | AK45: =(K45*AI45)/I45 -> 17.1575 | AL45: =AE45+AK45 -> 39.788333 | AM45: =Q45 -> 79.39 | AP45: =AVERAGE(AM45:AO45) -> 79.39 | AQ45: =J45+K45+L45 -> 75 | AR45: =(L45*AP45)/I45 -> 19.8475 | AS45: =AE45+AK45+AR45 -> 59.635833 | AW45: =AVERAGE(AT45:AV45) -> #DIV/0! | AX45: =J45+K45+L45+M45 -> 100 | AY45: =(M45*AW45)/I45 -> #DIV/0! | AZ45: =AE45+AK45+AR45+AY45 -> #DIV/0!
D46: Agencia Pueblo Yaqui | E46: 39 | F46: Cumplir con el presupuesto de ingresos en la gerencia Pueblo Yaqui. | G46: Mensual | H46: Porcentaje | I46: 100 | J46: 25 | K46: 25 | L46: 25 | M46: 25 | O46: X | P46: NO | Q46: 84.96 | R46: No se cumplió con el presupuesto programado de ingresos del mes. | S46: NA | T46: AC 02/2026 | U46: NA | V46: Raquel Estrada | W46: Vence 19 Junio 2026. Replanteada al 13 de Enero 2027. | Z46: 105.09 | AA46: 84.6 | AB46: 87.17 | AC46: =AVERAGE(Z46:AB46) -> 92.286667 | AD46: =J46 -> 25 | AE46: =(J46*AC46)/I46 -> 23.071667 | AF46: 73.59 | AG46: 80.1 | AH46: 75.15 | AI46: =AVERAGE(AF46:AH46) -> 76.28 | AJ46: =J46+K46 -> 50 | AK46: =(K46*AI46)/I46 -> 19.07 | AL46: =AE46+AK46 -> 42.141667 | AM46: =Q46 -> 84.96 | AP46: =AVERAGE(AM46:AO46) -> 84.96 | AQ46: =J46+K46+L46 -> 75 | AR46: =(L46*AP46)/I46 -> 21.24 | AS46: =AE46+AK46+AR46 -> 63.381667 | AW46: =AVERAGE(AT46:AV46) -> #DIV/0! | AX46: =J46+K46+L46+M46 -> 100 | AY46: =(M46*AW46)/I46 -> #DIV/0! | AZ46: =AE46+AK46+AR46+AY46 -> #DIV/0!
D47: Agencia Marte R. Gómez | E47: 40 | F47: Cumplir con el presupuesto de ingresos en la gerencia Marte R. Gomez. | G47: Mensual | H47: Porcentaje | I47: 100 | J47: 25 | K47: 25 | L47: 25 | M47: 25 | O47: X | P47: NO | Q47: 76.67 | R47: No se cumplió con el presupuesto programado de ingresos del mes. | S47: NA | T47: AC 04/2026 | U47: NA | V47: Guadalupe Alcaráz | W47: Vence 19 Junio 2026. Replanteada al 13 de Enero 2027. | Z47: 91.84 | AA47: 70.37 | AB47: 81.33 | AC47: =AVERAGE(Z47:AB47) -> 81.18 | AD47: =J47 -> 25 | AE47: =(J47*AC47)/I47 -> 20.295 | AF47: 90.58 | AG47: 85.93 | AH47: 78.57 | AI47: =AVERAGE(AF47:AH47) -> 85.026667 | AJ47: =J47+K47 -> 50 | AK47: =(K47*AI47)/I47 -> 21.256667 | AL47: =AE47+AK47 -> 41.551667 | AM47: =Q47 -> 76.67 | AP47: =AVERAGE(AM47:AO47) -> 76.67 | AQ47: =J47+K47+L47 -> 75 | AR47: =(L47*AP47)/I47 -> 19.1675 | AS47: =AE47+AK47+AR47 -> 60.719167 | AW47: =AVERAGE(AT47:AV47) -> #DIV/0! | AX47: =J47+K47+L47+M47 -> 100 | AY47: =(M47*AW47)/I47 -> #DIV/0! | AZ47: =AE47+AK47+AR47+AY47 -> #DIV/0!
D48: Dirección Comercial | E48: 41 | F48: Cumplir con el presupuesto programado de ingresos. | G48: Mensual | H48: Porcentaje | I48: 100 | J48: 25 | K48: 25 | L48: 25 | M48: 25 | O48: X | P48: NO | Q48: 81 | R48: No se cumplió con el presupuesto programado de ingresos del mes. | S48: NA | T48: AC 01/2026 | U48: NA | V48: Lolita Berrelleza | W48: Vence 19 Junio 2026. Replanteada al 13 de Enero 2027. | Z48: 87 | AA48: 75 | AB48: 87 | AC48: =AVERAGE(Z48:AB48) -> 83 | AD48: =J48 -> 25 | AE48: =(J48*AC48)/I48 -> 20.75 | AF48: 72 | AG48: 73 | AH48: 78 | AI48: =AVERAGE(AF48:AH48) -> 74.333333 | AJ48: =J48+K48 -> 50 | AK48: =(K48*AI48)/I48 -> 18.583333 | AL48: =AE48+AK48 -> 39.333333 | AM48: =Q48 -> 81 | AP48: =AVERAGE(AM48:AO48) -> 81 | AQ48: =J48+K48+L48 -> 75 | AR48: =(L48*AP48)/I48 -> 20.25 | AS48: =AE48+AK48+AR48 -> 59.583333 | AW48: =AVERAGE(AT48:AV48) -> #DIV/0! | AX48: =J48+K48+L48+M48 -> 100 | AY48: =(M48*AW48)/I48 -> #DIV/0! | AZ48: =AE48+AK48+AR48+AY48 -> #DIV/0!
E49: 42 | F49: Eficiencia comercial | G49: Mensual | H49: Porcentaje | I49: 60 | J49: 15 | K49: 15 | L49: 15 | M49: 15 | O49: X | P49: NO | Q49: 40.22 | R49: No se cumplió con la meta de la eficiencia comercial del mes. | S49: NA | T49: AC 01/2026 | U49: NA | V49: Ana Gloria Pérez | W49: Vence 19 Junio 2026. Replanteada al 13 de Enero 2027. | Z49: 43.01 | AA49: 36.41 | AB49: 41.53 | AC49: =AVERAGE(Z49:AB49) -> 40.316667 | AD49: =J49 -> 15 | AE49: =(J49*AC49)/I49 -> 10.079167 | AF49: 38.09 | AG49: 41.44 | AH49: 38.93 | AI49: =AVERAGE(AF49:AH49) -> 39.486667 | AJ49: =J49+K49 -> 30 | AK49: =(K49*AI49)/I49 -> 9.8716667 | AL49: =AE49+AK49 -> 19.950833 | AM49: =Q49 -> 40.22 | AP49: =AVERAGE(AM49:AO49) -> 40.22 | AQ49: =J49+K49+L49 -> 45 | AR49: =(L49*AP49)/I49 -> 10.055 | AS49: =AE49+AK49+AR49 -> 30.005833 | AW49: =AVERAGE(AT49:AV49) -> #DIV/0! | AX49: =J49+K49+L49+M49 -> 60 | AY49: =(M49*AW49)/I49 -> #DIV/0! | AZ49: =AE49+AK49+AR49+AY49 -> #DIV/0!
E50: 43 | F50: Eficiencia comercial de rezago | G50: Mensual | H50: Porcentaje | I50: 10 | J50: 2 | K50: 3 | L50: 2 | M50: 3 | O50: X | P50: NO | Q50: 0.53 | R50: No se cumplió con la meta de la eficiencia comercial de rezago del mes. | S50: NA | T50: AC 01/2026 | U50: NA | V50: Ana Gloria Pérez | W50: Vence 19 Junio 2026. Replanteada al 13 de Enero 2027. | Z50: 0.49 | AA50: 0.42 | AB50: 0.58 | AC50: =AVERAGE(Z50:AB50) -> 0.49666667 | AD50: =J50 -> 2 | AE50: =(J50*AC50)/I50 -> 0.099333333 | AF50: 0.48 | AG50: 0.48 | AH50: 0.51 | AI50: =AVERAGE(AF50:AH50) -> 0.49 | AJ50: =J50+K50 -> 5 | AK50: =(K50*AI50)/I50 -> 0.147 | AL50: =AE50+AK50 -> 0.24633333 | AM50: =Q50 -> 0.53 | AP50: =AVERAGE(AM50:AO50) -> 0.53 | AQ50: =J50+K50+L50 -> 7 | AR50: =(L50*AP50)/I50 -> 0.106 | AS50: =AE50+AK50+AR50 -> 0.35233333 | AW50: =AVERAGE(AT50:AV50) -> #DIV/0! | AX50: =J50+K50+L50+M50 -> 10 | AY50: =(M50*AW50)/I50 -> #DIV/0! | AZ50: =AE50+AK50+AR50+AY50 -> #DIV/0!
C51: Programas Sociales | D51: Trabajo Social | E51: 44 | F51: Atender las órdenes de trabajo en un lapso de 7 días hábiles | G51: Mensual | H51: Porcentaje | I51: 100 | J51: 25 | K51: 25 | L51: 25 | M51: 25 | O51: X | P51: SI | Q51: 100 | R51: Se cumplió al 100% en atender las órdenes de trabajo. | S51: NA | T51: NA | U51: NA | V51: Rosalva Ybarra | Z51: 100 | AA51: 100 | AB51: 100 | AC51: =AVERAGE(Z51:AB51) -> 100 | AD51: =J51 -> 25 | AE51: =(J51*AC51)/I51 -> 25 | AF51: 100 | AG51: 100 | AH51: 100 | AI51: =AVERAGE(AF51:AH51) -> 100 | AJ51: =J51+K51 -> 50 | AK51: =(K51*AI51)/I51 -> 25 | AL51: =AE51+AK51 -> 50 | AM51: =Q51 -> 100 | AP51: =AVERAGE(AM51:AO51) -> 100 | AQ51: =J51+K51+L51 -> 75 | AR51: =(L51*AP51)/I51 -> 25 | AS51: =AE51+AK51+AR51 -> 75 | AW51: =AVERAGE(AT51:AV51) -> #DIV/0! | AX51: =J51+K51+L51+M51 -> 100 | AY51: =(M51*AW51)/I51 -> #DIV/0! | AZ51: =AE51+AK51+AR51+AY51 -> #DIV/0!
A52: 5 | B52: Producción | C52: Técnica | D52: Control de Calidad | E52: 45 | F52: Cumplimiento a NOM-127-SSA1-2021 aplicable a control de calidad. | G52: Mensual | H52: Muestreos | I52: 10063 | J52: 2497 | K52: 2491 | L52: 2545 | M52: 2530 | O52: X | P52: SI | Q52: 875 | R52: Se da cumplimiento a la norma aplicable a control de calidad con 875 muestreos. | S52: NA | T52: NA | U52: SNC 111-128/2026 | V52: Lenia Luzanilla | Z52: 957 | AA52: 856 | AB52: 962 | AC52: =SUM(Z52:AB52) -> 2775 | AD52: =J52 -> 2497 | AE52: =AC52 -> 2775 | AF52: 883 | AG52: 839 | AH52: 857 | AI52: =SUM(AF52:AH52) -> 2579 | AJ52: =J52+K52 -> 4988 | AK52: =AI52 -> 2579 | AL52: =AE52+AK52 -> 5354 | AM52: =Q52 -> 875 | AP52: =SUM(AM52:AO52) -> 875 | AQ52: =J52+K52+L52 -> 7533 | AR52: =AP52 -> 875 | AS52: =AE52+AK52+AR52 -> 6229 | AW52: =SUM(AT52:AV52) -> 0 | AX52: =J52+K52+L52+M52 -> 10063 | AY52: =AW52 -> 0 | AZ52: =AE52+AK52+AR52+AY52 -> 6229
E53: 46 | F53: Índice de cumplimiento en muestreos y análisis de agua potable. | G53: Trimestral | H53: Informes | I53: 214 | J53: 62 | K53: 48 | L53: 56 | M53: 48 | O53: X | P53: SI | Q53: 0 | R53: Se cumple con el programa de análisis de agua potable. | S53: NA | T53: AC 10/2026 | U53: NA | V53: Lenia Luzanilla | W53: Vence 31 Diciembre 2026 | Z53: 0 | AA53: 0 | AB53: 50 | AC53: =SUM(Z53:AB53) -> 50 | AD53: =J53 -> 62 | AE53: =AC53 -> 50 | AF53: 0 | AG53: 0 | AH53: 49 | AI53: =SUM(AF53:AH53) -> 49 | AJ53: =J53+K53 -> 110 | AK53: =AI53 -> 49 | AL53: =AE53+AK53 -> 99 | AM53: =Q53 -> 0 | AP53: =SUM(AM53:AO53) -> 0 | AQ53: =J53+K53+L53 -> 166 | AR53: =AP53 -> 0 | AS53: =AE53+AK53+AR53 -> 99 | AW53: =SUM(AT53:AV53) -> 0 | AX53: =J53+K53+L53+M53 -> 214 | AY53: =AW53 -> 0 | AZ53: =AE53+AK53+AR53+AY53 -> 99
D54: Plantas Potabilizadoras | E54: 47 | F54: Producción de agua en plantas potabilizadoras y pozos de área urbana | G54: Mensual | H54: M3 | I54: 48439097 | J54: 12397143 | K54: 11618468 | L54: 12195511 | M54: 12227975 | O54: X | P54: SI | Q54: 3797664 | R54: Se cumplió con la producción de agua en plantas y pozos urbanos. | S54: NA | T54: NA | U54: NA | V54: Aracely Galvez | Z54: 3740059 | AA54: 3352981 | AB54: 3732973 | AC54: =SUM(Z54:AB54) -> 10826013 | AD54: =J54 -> 12397143 | AE54: =AC54 -> 10826013 | AF54: 3539531 | AG54: 3681315 | AH54: 3696993 | AI54: =SUM(AF54:AH54) -> 10917839 | AJ54: =J54+K54 -> 24015611 | AK54: =AI54 -> 10917839 | AL54: =AE54+AK54 -> 21743852 | AM54: =Q54 -> 3797664 | AP54: =SUM(AM54:AO54) -> 3797664 | AQ54: =J54+K54+L54 -> 36211122 | AR54: =AP54 -> 3797664 | AS54: =AE54+AK54+AR54 -> 25541516 | AW54: =SUM(AT54:AV54) -> 0 | AX54: =J54+K54+L54+M54 -> 48439097 | AY54: =AW54 -> 0 | AZ54: =AE54+AK54+AR54+AY54 -> 25541516
E55: 48 | F55: Índice de cobertura de macromedición | G55: Mensual | H55: Porcentaje | I55: 70 | J55: 20 | K55: 20 | L55: 20 | M55: 10 | O55: X | P55: NO | Q55: 57 | R55: No se cumplió con el índice de cobertura de macromedición. | S55: NA | T55: AC 17/2025 | U55: NA | V55: Aracely Galvez | W55: Vence 29 Mayo 2026. Replanteada el 28 diciembre 2026. | Z55: 57 | AA55: 57 | AB55: 57 | AC55: =AVERAGE(Z55:AB55) -> 57 | AD55: =J55 -> 20 | AE55: =(J55*AC55)/I55 -> 16.285714 | AF55: 57 | AG55: 57 | AH55: 57 | AI55: =AVERAGE(AF55:AH55) -> 57 | AJ55: =J55+K55 -> 40 | AK55: =(K55*AI55)/I55 -> 16.285714 | AL55: =AE55+AK55 -> 32.571429 | AM55: =Q55 -> 57 | AP55: =AVERAGE(AM55:AO55) -> 57 | AQ55: =J55+K55+L55 -> 60 | AR55: =(L55*AP55)/I55 -> 16.285714 | AS55: =AE55+AK55+AR55 -> 48.857143 | AW55: =AVERAGE(AT55:AV55) -> #DIV/0! | AX55: =J55+K55+L55+M55 -> 70 | AY55: =(M55*AW55)/I55 -> #DIV/0! | AZ55: =AE55+AK55+AR55+AY55 -> #DIV/0!
D56: Alcantarillado y Saneamiento | E56: 49 | F56: Índice de agua residual tratada. | G56: Mensual | H56: Porcentaje | I56: 100 | J56: 25 | K56: 25 | L56: 25 | M56: 25 | O56: X | P56: SI | Q56: 100 | R56: Se cumplió al 100% con el Índice de agua residual tratada. | S56: NA | T56: NA | U56: NA | V56: Jorge Fernández | Z56: 100 | AA56: 100 | AB56: 100 | AC56: =AVERAGE(Z56:AB56) -> 100 | AD56: =J56 -> 25 | AE56: =(J56*AC56)/I56 -> 25 | AF56: 100 | AG56: 100 | AH56: 100 | AI56: =AVERAGE(AF56:AH56) -> 100 | AJ56: =J56+K56 -> 50 | AK56: =(K56*AI56)/I56 -> 25 | AL56: =AE56+AK56 -> 50 | AM56: =Q56 -> 100 | AP56: =AVERAGE(AM56:AO56) -> 100 | AQ56: =J56+K56+L56 -> 75 | AR56: =(L56*AP56)/I56 -> 25 | AS56: =AE56+AK56+AR56 -> 75 | AW56: =AVERAGE(AT56:AV56) -> #DIV/0! | AX56: =J56+K56+L56+M56 -> 100 | AY56: =(M56*AW56)/I56 -> #DIV/0! | AZ56: =AE56+AK56+AR56+AY56 -> #DIV/0!
E57: 50 | F57: Programa de muestreo y análisis de aguas residuales | G57: Mensual | H57: Porcentaje | I57: 100 | J57: 25 | K57: 25 | L57: 25 | M57: 25 | O57: X | P57: SI | Q57: 100 | R57: Se cumplió al 100% con el programa de muestreo y análisis de aguas residuales. | S57: NA | T57: NA | U57: NA | V57: Jorge Fernández | Z57: 100 | AA57: 100 | AB57: 100 | AC57: =AVERAGE(Z57:AB57) -> 100 | AD57: =J57 -> 25 | AE57: =(J57*AC57)/I57 -> 25 | AF57: 100 | AG57: 100 | AH57: 100 | AI57: =AVERAGE(AF57:AH57) -> 100 | AJ57: =J57+K57 -> 50 | AK57: =(K57*AI57)/I57 -> 25 | AL57: =AE57+AK57 -> 50 | AM57: =Q57 -> 100 | AP57: =AVERAGE(AM57:AO57) -> 100 | AQ57: =J57+K57+L57 -> 75 | AR57: =(L57*AP57)/I57 -> 25 | AS57: =AE57+AK57+AR57 -> 75 | AW57: =AVERAGE(AT57:AV57) -> #DIV/0! | AX57: =J57+K57+L57+M57 -> 100 | AY57: =(M57*AW57)/I57 -> #DIV/0! | AZ57: =AE57+AK57+AR57+AY57 -> #DIV/0!
D58: Suburbano Técnico | E58: 51 | F58: Cumplir con el volumen de agua potabilizada. | G58: Mensual | H58: M3 | I58: 14583516 | J58: 3645879 | K58: 3645879 | L58: 3645879 | M58: 3645879 | O58: X | P58: SI | Q58: 1241188 | R58: Se cumplió con el volumen de agua programado. | S58: NA | T58: NA | U58: NA | V58: Mario Mendoza | Z58: 1227052 | AA58: 1580049 | AB58: 1238600 | AC58: =SUM(Z58:AB58) -> 4045701 | AD58: =J58 -> 3645879 | AE58: =AC58 -> 4045701 | AF58: 1216571 | AG58: 1239619 | AH58: 1222293 | AI58: =SUM(AF58:AH58) -> 3678483 | AJ58: =J58+K58 -> 7291758 | AK58: =AI58 -> 3678483 | AL58: =AE58+AK58 -> 7724184 | AM58: =Q58 -> 1241188 | AP58: =SUM(AM58:AO58) -> 1241188 | AQ58: =J58+K58+L58 -> 10937637 | AR58: =AP58 -> 1241188 | AS58: =AE58+AK58+AR58 -> 8965372 | AW58: =SUM(AT58:AV58) -> 0 | AX58: =J58+K58+L58+M58 -> 14583516 | AY58: =AW58 -> 0 | AZ58: =AE58+AK58+AR58+AY58 -> 8965372
A59: 6 | B59: Medición, Análisis y Mejora | C59: Órgano de Control de Interno | D59: Órgano de Control Interno | E59: 52 | F59: Realizar en el ejercicio fiscal una auditoría programada mensual. | G59: Mensual | H59: Informe | I59: 12 | J59: 3 | K59: 3 | L59: 3 | M59: 3 | N59: X | P59: SI | Q59: 1 | R59: Se realizó la auditoría programada mensual. | S59: RC 12/2025, RC03/2026 | T59: AC 11/2026 | U59: NA | V59: Evelyn Pelaez | W59: Vence 05 de Enero 2027. | Z59: 0 | AA59: 1 | AB59: 1 | AC59: =SUM(Z59:AB59) -> 2 | AD59: =J59 -> 3 | AE59: =AC59 -> 2 | AF59: 1 | AG59: 0 | AH59: 1 | AI59: =SUM(AF59:AH59) -> 2 | AJ59: =J59+K59 -> 6 | AK59: =AI59 -> 2 | AL59: =AE59+AK59 -> 4 | AM59: =Q59 -> 1 | AP59: =SUM(AM59:AO59) -> 1 | AQ59: =J59+K59+L59 -> 9 | AR59: =AP59 -> 1 | AS59: =AE59+AK59+AR59 -> 5 | AW59: =SUM(AT59:AV59) -> 0 | AX59: =J59+K59+L59+M59 -> 12 | AY59: =AW59 -> 0 | AZ59: =AE59+AK59+AR59+AY59 -> 5
E60: 53 | F60: Revisar el seguimiento y control del recurso federalizado en el ejercicio fiscal. | G60: Semestral | H60: Porcentaje | I60: 60 | J60: 0 | K60: 30 | L60: 0 | M60: 30 | N60: X | P60: NO | Q60: 13 | R60: Al mes de Junio se considera avance de la revisión del 13% con recurso federal. | S60: RC 07/2026 | T60: NA | U60: NA | V60: Evelyn Pelaez | Z60: 0 | AA60: 13 | AB60: 13 | AC60: =AB60 -> 13 | AD60: =J60 -> 0 | AE60: =AC60 -> 13 | AF60: 13 | AG60: 13 | AH60: 13 | AI60: =AH60 -> 13 | AJ60: =J60+K60 -> 30 | AK60: =AI60 -> 13 | AL60: =AK60 -> 13 | AM60: =Q60 -> 13 | AP60: =AO60 -> 0 | AQ60: =J60+K60+L60 -> 30 | AR60: =AP60 -> 0 | AS60: =AR60 -> 0 | AW60: =AV60 -> 0 | AX60: =J60+K60+L60+M60 -> 60 | AY60: =AW60 -> 0 | AZ60: =AY60 -> 0
E61: 54 | F61: Atender las solicitudes de intervención especiales y no programadas. | G61: Mensual | H61: Porcentaje | I61: 100 | J61: 25 | K61: 25 | L61: 25 | M61: 25 | N61: X | P61: SI | Q61: 100 | R61: Durante el mes se atendió al 100% las solicitudes de intervención especial y no programadas. | S61: NA | T61: NA | U61: NA | V61: Evelyn Pelaez | Z61: 100 | AA61: 100 | AB61: 100 | AC61: =AVERAGE(Z61:AB61) -> 100 | AD61: =J61 -> 25 | AE61: =(J61*AC61)/I61 -> 25 | AF61: 100 | AG61: 100 | AH61: 100 | AI61: =AVERAGE(AF61:AH61) -> 100 | AJ61: =J61+K61 -> 50 | AK61: =(K61*AI61)/I61 -> 25 | AL61: =AE61+AK61 -> 50 | AM61: =Q61 -> 100 | AP61: =AVERAGE(AM61:AO61) -> 100 | AQ61: =J61+K61+L61 -> 75 | AR61: =(L61*AP61)/I61 -> 25 | AS61: =AE61+AK61+AR61 -> 75 | AW61: =AVERAGE(AT61:AV61) -> #DIV/0! | AX61: =J61+K61+L61+M61 -> 100 | AY61: =(M61*AW61)/I61 -> #DIV/0! | AZ61: =AE61+AK61+AR61+AY61 -> #DIV/0!
E62: 55 | F62: Atender y dar seguimiento a las observaciones de los sujetos fiscalizadores. | G62: Mensual | H62: Porcentaje | I62: 100 | J62: 25 | K62: 25 | L62: 25 | M62: 25 | N62: X | P62: SI | Q62: 100 | R62: No se obtuvieron observaciones durante el por parte de sujetos fiscalizadores. | S62: NA | T62: NA | U62: NA | V62: Evelyn Pelaez | Z62: 100 | AA62: 100 | AB62: 100 | AC62: =AVERAGE(Z62:AB62) -> 100 | AD62: =J62 -> 25 | AE62: =(J62*AC62)/I62 -> 25 | AF62: 100 | AG62: 100 | AH62: 100 | AI62: =AVERAGE(AF62:AH62) -> 100 | AJ62: =J62+K62 -> 50 | AK62: =(K62*AI62)/I62 -> 25 | AL62: =AE62+AK62 -> 50 | AM62: =Q62 -> 100 | AP62: =AVERAGE(AM62:AO62) -> 100 | AQ62: =J62+K62+L62 -> 75 | AR62: =(L62*AP62)/I62 -> 25 | AS62: =AE62+AK62+AR62 -> 75 | AW62: =AVERAGE(AT62:AV62) -> #DIV/0! | AX62: =J62+K62+L62+M62 -> 100 | AY62: =(M62*AW62)/I62 -> #DIV/0! | AZ62: =AE62+AK62+AR62+AY62 -> #DIV/0!
E63: 56 | F63: Atender al personal que acuda al OCI a asesorías. | G63: Trimestral | H63: Porcentaje | I63: 100 | J63: 25 | K63: 25 | L63: 25 | M63: 25 | N63: X | P63: SI | Q63: 100 | R63: Se atendió al personal que acudió a asesorías. | S63: NA | T63: NA | U63: NA | V63: Evelyn Pelaez | Z63: 100 | AA63: 100 | AB63: 100 | AC63: =AVERAGE(Z63:AB63) -> 100 | AD63: =J63 -> 25 | AE63: =(J63*AC63)/I63 -> 25 | AF63: 100 | AG63: 100 | AH63: 100 | AI63: =AVERAGE(AF63:AH63) -> 100 | AJ63: =J63+K63 -> 50 | AK63: =(K63*AI63)/I63 -> 25 | AL63: =AE63+AK63 -> 50 | AM63: =Q63 -> 100 | AP63: =AVERAGE(AM63:AO63) -> 100 | AQ63: =J63+K63+L63 -> 75 | AR63: =(L63*AP63)/I63 -> 25 | AS63: =AE63+AK63+AR63 -> 75 | AW63: =AVERAGE(AT63:AV63) -> #DIV/0! | AX63: =J63+K63+L63+M63 -> 100 | AY63: =(M63*AW63)/I63 -> #DIV/0! | AZ63: =AE63+AK63+AR63+AY63 -> #DIV/0!
E64: 57 | F64: Atender a los usuarios que interpongan quejas y denuncias en contra del servicio o cualquier servidor público. | G64: Mensual | H64: Porcentaje | I64: 100 | J64: 25 | K64: 25 | L64: 25 | M64: 25 | O64: X | P64: SI | Q64: 100 | R64: Se atendieron al 100% los usuarios que interpusieron quejas y denuncias en contra del servicio o cualquier servidor público. | S64: NA | T64: NA | U64: NA | V64: Evelyn Pelaez | Z64: 100 | AA64: 100 | AB64: 100 | AC64: =AVERAGE(Z64:AB64) -> 100 | AD64: =J64 -> 25 | AE64: =(J64*AC64)/I64 -> 25 | AF64: 100 | AG64: 100 | AH64: 100 | AI64: =AVERAGE(AF64:AH64) -> 100 | AJ64: =J64+K64 -> 50 | AK64: =(K64*AI64)/I64 -> 25 | AL64: =AE64+AK64 -> 50 | AM64: =Q64 -> 100 | AP64: =AVERAGE(AM64:AO64) -> 100 | AQ64: =J64+K64+L64 -> 75 | AR64: =(L64*AP64)/I64 -> 25 | AS64: =AE64+AK64+AR64 -> 75 | AW64: =AVERAGE(AT64:AV64) -> #DIV/0! | AX64: =J64+K64+L64+M64 -> 100 | AY64: =(M64*AW64)/I64 -> #DIV/0! | AZ64: =AE64+AK64+AR64+AY64 -> #DIV/0!
C65: General | D65: Sistema de Gestión de Calidad | E65: 58 | F65: Cumplir en los cierres de planes de acción de Matriz de Riesgos | G65: Mensual | H65: Porcentaje | I65: 100 | J65: 25 | K65: 25 | L65: 25 | M65: 25 | N65: X | P65: NO | Q65: 99 | R65: No se cumplió en tiempo con los planes de acción de la Matriz de Riesgos. | S65: RC 08/2026 | T65: NA | U65: NA | V65: Miguel Encinas | Z65: 100 | AA65: 100 | AB65: 100 | AC65: =AVERAGE(Z65:AB65) -> 100 | AD65: =J65 -> 25 | AE65: =(J65*AC65)/I65 -> 25 | AF65: 99 | AG65: 100 | AH65: 100 | AI65: =AVERAGE(AF65:AH65) -> 99.666667 | AJ65: =J65+K65 -> 50 | AK65: =(K65*AI65)/I65 -> 24.916667 | AL65: =AE65+AK65 -> 49.916667 | AM65: =Q65 -> 99 | AP65: =AVERAGE(AM65:AO65) -> 99 | AQ65: =J65+K65+L65 -> 75 | AR65: =(L65*AP65)/I65 -> 24.75 | AS65: =AE65+AK65+AR65 -> 74.666667 | AW65: =AVERAGE(AT65:AV65) -> #DIV/0! | AX65: =J65+K65+L65+M65 -> 100 | AY65: =(M65*AW65)/I65 -> #DIV/0! | AZ65: =AE65+AK65+AR65+AY65 -> #DIV/0!
E66: 59 | F66: Estado de acciones y mejoras. | G66: Mensual | H66: Porcentaje | I66: 100 | J66: 25 | K66: 25 | L66: 25 | M66: 25 | N66: X | P66: SI | Q66: 100 | R66: Se cumplió en tiempo con el estado de acciones y mejoras. | S66: RC 08/2025 | T66: AC 15/2025 | U66: NA | V66: Héctor Paez | W66: Vence 23 de octubre 2025. Replanteada 26 Enero 2026.Replanteada 17 julio 2026. Replanteada 30 de Diciembre. | Z66: 99 | AA66: 95 | AB66: 99 | AC66: =AVERAGE(Z66:AB66) -> 97.666667 | AD66: =J66 -> 25 | AE66: =(J66*AC66)/I66 -> 24.416667 | AF66: 100 | AG66: 100 | AH66: 100 | AI66: =AVERAGE(AF66:AH66) -> 100 | AJ66: =J66+K66 -> 50 | AK66: =(K66*AI66)/I66 -> 25 | AL66: =AE66+AK66 -> 49.416667 | AM66: =Q66 -> 100 | AP66: =AVERAGE(AM66:AO66) -> 100 | AQ66: =J66+K66+L66 -> 75 | AR66: =(L66*AP66)/I66 -> 25 | AS66: =AE66+AK66+AR66 -> 74.416667 | AW66: =AVERAGE(AT66:AV66) -> #DIV/0! | AX66: =J66+K66+L66+M66 -> 100 | AY66: =(M66*AW66)/I66 -> #DIV/0! | AZ66: =AE66+AK66+AR66+AY66 -> #DIV/0!
E67: 60 | F67: Lograr el grado de eficacia derivado de las auditorías internas | G67: Bimestral | H67: Porcentaje | I67: 85 | J67: 20 | K67: 20 | L67: 20 | M67: 25 | O67: X | P67: SI | Q67: 92 | R67: Se cumplió al 92% con el grado de eficacia derivado de las auditorías internas. | S67: NA | T67: NA | U67: NA | V67: Vicente Ivich | Z67: 90 | AA67: 91 | AB67: 91 | AC67: =AVERAGE(Z67:AB67) -> 90.666667 | AD67: =J67 -> 20 | AE67: =(J67*AC67)/I67 -> 21.333333 | AF67: 91 | AG67: 92 | AH67: 92 | AI67: =AVERAGE(AF67:AH67) -> 91.666667 | AJ67: =J67+K67 -> 40 | AK67: =(K67*AI67)/I67 -> 21.568627 | AL67: =AE67+AK67 -> 42.901961 | AM67: =Q67 -> 92 | AP67: =AVERAGE(AM67:AO67) -> 92 | AQ67: =J67+K67+L67 -> 60 | AR67: =(L67*AP67)/I67 -> 21.647059 | AS67: =AE67+AK67+AR67 -> 64.54902 | AW67: =AVERAGE(AT67:AV67) -> #DIV/0! | AX67: =J67+K67+L67+M67 -> 85 | AY67: =(M67*AW67)/I67 -> #DIV/0! | AZ67: =AE67+AK67+AR67+AY67 -> #DIV/0!
D68: Línea OOMAPASC | E68: 61 | F68: Atender las llamadas o mensajes de solicitud de usuarios. | G68: Mensual | H68: Porcentaje | I68: 95 | J68: 24 | K68: 24 | L68: 24 | M68: 23 | O68: X | P68: SI | Q68: 100 | R68: Se cumplió al 100% con la atención de llamadas y mensajes de los usuarios. | S68: NA | T68: NA | U68: NA | V68: Alejandro Lara | Z68: 100 | AA68: 100 | AB68: 100 | AC68: =AVERAGE(Z68:AB68) -> 100 | AD68: =J68 -> 24 | AE68: =(J68*AC68)/I68 -> 25.263158 | AF68: 100 | AG68: 100 | AH68: 100 | AI68: =AVERAGE(AF68:AH68) -> 100 | AJ68: =J68+K68 -> 48 | AK68: =(K68*AI68)/I68 -> 25.263158 | AL68: =AE68+AK68 -> 50.526316 | AM68: =Q68 -> 100 | AP68: =AVERAGE(AM68:AO68) -> 100 | AQ68: =J68+K68+L68 -> 72 | AR68: =(L68*AP68)/I68 -> 25.263158 | AS68: =AE68+AK68+AR68 -> 75.789474 | AW68: =AVERAGE(AT68:AV68) -> #DIV/0! | AX68: =J68+K68+L68+M68 -> 95 | AY68: =(M68*AW68)/I68 -> #DIV/0! | AZ68: =AE68+AK68+AR68+AY68 -> #DIV/0!
E69: 62 | F69: Medir la satisfacción del cliente en atención recibida. | G69: Mensual | H69: Porcentaje | I69: 95 | J69: 24 | K69: 24 | L69: 24 | M69: 23 | O69: X | P69: SI | Q69: 98 | R69: Se cumplió al 98% con la satisfacción del ciente en la atención recibida. | S69: NA | T69: NA | U69: NA | V69: Alejandro Lara | Z69: 99 | AA69: 97 | AB69: 99 | AC69: =AVERAGE(Z69:AB69) -> 98.333333 | AD69: =J69 -> 24 | AE69: =(J69*AC69)/I69 -> 24.842105 | AF69: 99 | AG69: 97 | AH69: 99 | AI69: =AVERAGE(AF69:AH69) -> 98.333333 | AJ69: =J69+K69 -> 48 | AK69: =(K69*AI69)/I69 -> 24.842105 | AL69: =AE69+AK69 -> 49.684211 | AM69: =Q69 -> 98 | AP69: =AVERAGE(AM69:AO69) -> 98 | AQ69: =J69+K69+L69 -> 72 | AR69: =(L69*AP69)/I69 -> 24.757895 | AS69: =AE69+AK69+AR69 -> 74.442105 | AW69: =AVERAGE(AT69:AV69) -> #DIV/0! | AX69: =J69+K69+L69+M69 -> 95 | AY69: =(M69*AW69)/I69 -> #DIV/0! | AZ69: =AE69+AK69+AR69+AY69 -> #DIV/0!
C70: Comercial | D70: Contratos y Servicios | E70: 63 | F70: Cumplir con la satisfacción del cliente por la atención brindada. | G70: Mensual | H70: Porcentaje | I70: 96 | J70: 24 | K70: 24 | L70: 24 | M70: 24 | O70: X | P70: SI | Q70: 100 | R70: Se cumplió al 100% con la satisfacción del cliente por la atención brindada. | S70: NA | T70: NA | U70: NA | V70: Nadia López | Z70: 100 | AA70: 100 | AB70: 100 | AC70: =AVERAGE(Z70:AB70) -> 100 | AD70: =J70 -> 24 | AE70: =(J70*AC70)/I70 -> 25 | AF70: 100 | AG70: 100 | AH70: 100 | AI70: =AVERAGE(AF70:AH70) -> 100 | AJ70: =J70+K70 -> 48 | AK70: =(K70*AI70)/I70 -> 25 | AL70: =AE70+AK70 -> 50 | AM70: =Q70 -> 100 | AP70: =AVERAGE(AM70:AO70) -> 100 | AQ70: =J70+K70+L70 -> 72 | AR70: =(L70*AP70)/I70 -> 25 | AS70: =AE70+AK70+AR70 -> 75 | AW70: =AVERAGE(AT70:AV70) -> #DIV/0! | AX70: =J70+K70+L70+M70 -> 96 | AY70: =(M70*AW70)/I70 -> #DIV/0! | AZ70: =AE70+AK70+AR70+AY70 -> #DIV/0!
D71: Verificación y Lectura | E71: 64 | F71: Cumplir en las encuestas de satisfacción al usuario externo en los servicios proporcionados por el supervisor. | G71: Mensual | H71: Porcentaje | I71: 95 | J71: 23 | K71: 24 | L71: 24 | M71: 24 | O71: X | P71: SI | Q71: 100 | R71: Se cumplió al 100% en la satisfacción de los usuarios. | S71: NA | T71: NA | U71: NA | V71: Carlos Quintero | Z71: 100 | AA71: 100 | AB71: 100 | AC71: =AVERAGE(Z71:AB71) -> 100 | AD71: =J71 -> 23 | AE71: =(J71*AC71)/I71 -> 24.210526 | AF71: 100 | AG71: 100 | AH71: 100 | AI71: =AVERAGE(AF71:AH71) -> 100 | AJ71: =J71+K71 -> 47 | AK71: =(K71*AI71)/I71 -> 25.263158 | AL71: =AE71+AK71 -> 49.473684 | AM71: =Q71 -> 100 | AP71: =AVERAGE(AM71:AO71) -> 100 | AQ71: =J71+K71+L71 -> 71 | AR71: =(L71*AP71)/I71 -> 25.263158 | AS71: =AE71+AK71+AR71 -> 74.736842 | AW71: =AVERAGE(AT71:AV71) -> #DIV/0! | AX71: =J71+K71+L71+M71 -> 95 | AY71: =(M71*AW71)/I71 -> #DIV/0! | AZ71: =AE71+AK71+AR71+AY71 -> #DIV/0!
D72: Atención Ciudadana | E72: 65 | F72: Medir la eficiencia y el tiempo de respuesta establecido en 7 días hábiles a partir de la recepción del folio emitido por el H. Ayuntamiento de Cajeme. | G72: Mensual | H72: Porcentaje | I72: 100 | J72: 25 | K72: 25 | L72: 25 | M72: 25 | O72: X | P72: SI | Q72: 100 | R72: Se cumplió al 100% con el tiempo de respuesta de las solicitudes del H. Ayuntamiento de Cajeme. | S72: NA | T72: NA | U72: NA | V72: Ana Gloria Pérez | Z72: 100 | AA72: 100 | AB72: 100 | AC72: =AVERAGE(Z72:AB72) -> 100 | AD72: =J72 -> 25 | AE72: =(J72*AC72)/I72 -> 25 | AF72: 100 | AG72: 100 | AH72: 100 | AI72: =AVERAGE(AF72:AH72) -> 100 | AJ72: =J72+K72 -> 50 | AK72: =(K72*AI72)/I72 -> 25 | AL72: =AE72+AK72 -> 50 | AM72: =Q72 -> 100 | AP72: =AVERAGE(AM72:AO72) -> 100 | AQ72: =J72+K72+L72 -> 75 | AR72: =(L72*AP72)/I72 -> 25 | AS72: =AE72+AK72+AR72 -> 75 | AW72: =AVERAGE(AT72:AV72) -> #DIV/0! | AX72: =J72+K72+L72+M72 -> 100 | AY72: =(M72*AW72)/I72 -> #DIV/0! | AZ72: =AE72+AK72+AR72+AY72 -> #DIV/0!
D73: Agencia Providencia | E73: 66 | F73: Cumplir con la satisfacción del cliente por el servicio proporcionado | G73: Mensual | H73: Porcentaje | I73: 95 | J73: 24 | K73: 24 | L73: 24 | M73: 23 | O73: X | P73: SI | Q73: 100 | R73: Se cumplió al 100% en la satisfacción de los usuarios. | S73: NA | T73: NA | U73: NA | V73: Juan Compián | Z73: 100 | AA73: 100 | AB73: 100 | AC73: =AVERAGE(Z73:AB73) -> 100 | AD73: =J73 -> 24 | AE73: =(J73*AC73)/I73 -> 25.263158 | AF73: 100 | AG73: 100 | AH73: 100 | AI73: =AVERAGE(AF73:AH73) -> 100 | AJ73: =J73+K73 -> 48 | AK73: =(K73*AI73)/I73 -> 25.263158 | AL73: =AE73+AK73 -> 50.526316 | AM73: =Q73 -> 100 | AP73: =AVERAGE(AM73:AO73) -> 100 | AQ73: =J73+K73+L73 -> 72 | AR73: =(L73*AP73)/I73 -> 25.263158 | AS73: =AE73+AK73+AR73 -> 75.789474 | AW73: =AVERAGE(AT73:AV73) -> #DIV/0! | AX73: =J73+K73+L73+M73 -> 95 | AY73: =(M73*AW73)/I73 -> #DIV/0! | AZ73: =AE73+AK73+AR73+AY73 -> #DIV/0!
D74: Agencia Esperanza | E74: 67 | F74: Cumplir con la satisfacción del cliente por el servicio proporcionado | G74: Mensual | H74: Porcentaje | I74: 95 | J74: 24 | K74: 24 | L74: 24 | M74: 23 | O74: X | P74: SI | Q74: 100 | R74: Se cumplió al 100% en la satisfacción de los usuarios. | S74: NA | T74: NA | U74: NA | V74: Raúl Reichel | Z74: 100 | AA74: 100 | AB74: 100 | AC74: =AVERAGE(Z74:AB74) -> 100 | AD74: =J74 -> 24 | AE74: =(J74*AC74)/I74 -> 25.263158 | AF74: 100 | AG74: 100 | AH74: 100 | AI74: =AVERAGE(AF74:AH74) -> 100 | AJ74: =J74+K74 -> 48 | AK74: =(K74*AI74)/I74 -> 25.263158 | AL74: =AE74+AK74 -> 50.526316 | AM74: =Q74 -> 100 | AP74: =AVERAGE(AM74:AO74) -> 100 | AQ74: =J74+K74+L74 -> 72 | AR74: =(L74*AP74)/I74 -> 25.263158 | AS74: =AE74+AK74+AR74 -> 75.789474 | AW74: =AVERAGE(AT74:AV74) -> #DIV/0! | AX74: =J74+K74+L74+M74 -> 95 | AY74: =(M74*AW74)/I74 -> #DIV/0! | AZ74: =AE74+AK74+AR74+AY74 -> #DIV/0!
D75: Agencia Pueblo Yaqui | E75: 68 | F75: Cumplir con la satisfacción del cliente por el servicio proporcionado | G75: Mensual | H75: Porcentaje | I75: 95 | J75: 24 | K75: 24 | L75: 24 | M75: 23 | O75: X | P75: SI | Q75: 100 | R75: Se cumplió al 100% en la satisfacción de los usuarios. | S75: NA | T75: NA | U75: NA | V75: Raquel Estrada | Z75: 100 | AA75: 100 | AB75: 100 | AC75: =AVERAGE(Z75:AB75) -> 100 | AD75: =J75 -> 24 | AE75: =(J75*AC75)/I75 -> 25.263158 | AF75: 100 | AG75: 100 | AH75: 100 | AI75: =AVERAGE(AF75:AH75) -> 100 | AJ75: =J75+K75 -> 48 | AK75: =(K75*AI75)/I75 -> 25.263158 | AL75: =AE75+AK75 -> 50.526316 | AM75: =Q75 -> 100 | AP75: =AVERAGE(AM75:AO75) -> 100 | AQ75: =J75+K75+L75 -> 72 | AR75: =(L75*AP75)/I75 -> 25.263158 | AS75: =AE75+AK75+AR75 -> 75.789474 | AW75: =AVERAGE(AT75:AV75) -> #DIV/0! | AX75: =J75+K75+L75+M75 -> 95 | AY75: =(M75*AW75)/I75 -> #DIV/0! | AZ75: =AE75+AK75+AR75+AY75 -> #DIV/0!
D76: Agencia Marte R. Gómez | E76: 69 | F76: Cumplir con la satisfacción del cliente por el servicio proporcionado | G76: Mensual | H76: Porcentaje | I76: 95 | J76: 24 | K76: 24 | L76: 24 | M76: 23 | O76: X | P76: SI | Q76: 100 | R76: Se cumplió al 100% en la satisfacción de los usuarios. | S76: NA | T76: NA | U76: NA | V76: Guadalupe Alcaráz | Z76: 100 | AA76: 100 | AB76: 100 | AC76: =AVERAGE(Z76:AB76) -> 100 | AD76: =J76 -> 24 | AE76: =(J76*AC76)/I76 -> 25.263158 | AF76: 100 | AG76: 100 | AH76: 100 | AI76: =AVERAGE(AF76:AH76) -> 100 | AJ76: =J76+K76 -> 48 | AK76: =(K76*AI76)/I76 -> 25.263158 | AL76: =AE76+AK76 -> 50.526316 | AM76: =Q76 -> 100 | AP76: =AVERAGE(AM76:AO76) -> 100 | AQ76: =J76+K76+L76 -> 72 | AR76: =(L76*AP76)/I76 -> 25.263158 | AS76: =AE76+AK76+AR76 -> 75.789474 | AW76: =AVERAGE(AT76:AV76) -> #DIV/0! | AX76: =J76+K76+L76+M76 -> 95 | AY76: =(M76*AW76)/I76 -> #DIV/0! | AZ76: =AE76+AK76+AR76+AY76 -> #DIV/0!
D77: Control y Servicios | E77: 70 | F77: Cumplir con la satisfacción de los usuarios por reconexiones | G77: Mensual | H77: Porcentaje | I77: 90 | J77: 22 | K77: 23 | L77: 22 | M77: 23 | O77: X | P77: SI | Q77: 99 | R77: Se cumplió al 99% con la satisfacción de los usuarios. | S77: NA | T77: NA | U77: NA | V77: Irasema Moreno | Z77: 99 | AA77: 99 | AB77: 99 | AC77: =AVERAGE(Z77:AB77) -> 99 | AD77: =J77 -> 22 | AE77: =(J77*AC77)/I77 -> 24.2 | AF77: 99 | AG77: 99 | AH77: 99 | AI77: =AVERAGE(AF77:AH77) -> 99 | AJ77: =J77+K77 -> 45 | AK77: =(K77*AI77)/I77 -> 25.3 | AL77: =AE77+AK77 -> 49.5 | AM77: =Q77 -> 99 | AP77: =AVERAGE(AM77:AO77) -> 99 | AQ77: =J77+K77+L77 -> 67 | AR77: =(L77*AP77)/I77 -> 24.2 | AS77: =AE77+AK77+AR77 -> 73.7 | AW77: =AVERAGE(AT77:AV77) -> #DIV/0! | AX77: =J77+K77+L77+M77 -> 90 | AY77: =(M77*AW77)/I77 -> #DIV/0! | AZ77: =AE77+AK77+AR77+AY77 -> #DIV/0!
C78: Jurídico | D78: Transparencia | E78: 71 | F78: Atender en tiempo y forma las solicitudes de información aplicables al área. | G78: Mensual | H78: Porcentaje | I78: 100 | J78: 25 | K78: 25 | L78: 25 | M78: 25 | N78: X | P78: SI | Q78: 100 | R78: Se cumplió al 100% en tiempo y forma con las solicitudes de información presentadas en el mes. | S78: NA | T78: NA | U78: NA | V78: David Bazúa | Z78: 100 | AA78: 100 | AB78: 100 | AC78: =AVERAGE(Z78:AB78) -> 100 | AD78: =J78 -> 25 | AE78: =(J78*AC78)/I78 -> 25 | AF78: 100 | AG78: 100 | AH78: 100 | AI78: =AVERAGE(AF78:AH78) -> 100 | AJ78: =J78+K78 -> 50 | AK78: =(K78*AI78)/I78 -> 25 | AL78: =AE78+AK78 -> 50 | AM78: =Q78 -> 100 | AP78: =AVERAGE(AM78:AO78) -> 100 | AQ78: =J78+K78+L78 -> 75 | AR78: =(L78*AP78)/I78 -> 25 | AS78: =AE78+AK78+AR78 -> 75 | AW78: =AVERAGE(AT78:AV78) -> #DIV/0! | AX78: =J78+K78+L78+M78 -> 100 | AY78: =(M78*AW78)/I78 -> #DIV/0! | AZ78: =AE78+AK78+AR78+AY78 -> #DIV/0!
E79: 72 | F79: Indicador de cumplimiento página de transparencia. | G79: Trimestral | H79: Porcentaje | I79: 100 | J79: 25 | K79: 25 | L79: 25 | M79: 25 | N79: X | P79: SI | Q79: 0 | R79: Se cumplió al 100% con la entrrega de la información de transparencia. | S79: NA | T79: NA | U79: NA | V79: David Bazúa | Z79: 0 | AA79: 0 | AB79: 100 | AC79: =AB79 -> 100 | AD79: =J79 -> 25 | AE79: =(J79*AC79)/I79 -> 25 | AF79: 0 | AG79: 0 | AH79: 100 | AI79: =AH79 -> 100 | AJ79: =J79+K79 -> 50 | AK79: =(K79*AI79)/I79 -> 25 | AL79: =AE79+AK79 -> 50 | AM79: =Q79 -> 0 | AP79: =AVERAGE(AM79:AO79) -> 0 | AQ79: =J79+K79+L79 -> 75 | AR79: =(L79*AP79)/I79 -> 0 | AS79: =AE79+AK79+AR79 -> 50 | AW79: =AVERAGE(AT79:AV79) -> #DIV/0! | AX79: =J79+K79+L79+M79 -> 100 | AY79: =(M79*AW79)/I79 -> #DIV/0! | AZ79: =AE79+AK79+AR79+AY79 -> #DIV/0!
D80: Coord. Jurídico | E80: 73 | F80: Índice de atención por asesorías. | G80: Mensual | H80: Porcentaje | I80: 100 | J80: 25 | K80: 25 | L80: 25 | M80: 25 | N80: X | P80: SI | Q80: 100 | R80: Se cumplió al 100% con la atención por asesorías. | S80: NA | T80: NA | U80: NA | V80: Berenice Berrelleza | Z80: 100 | AA80: 100 | AB80: 100 | AC80: =AVERAGE(Z80:AB80) -> 100 | AD80: =J80 -> 25 | AE80: =(J80*AC80)/I80 -> 25 | AF80: 100 | AG80: 100 | AH80: 100 | AI80: =AVERAGE(AF80:AH80) -> 100 | AJ80: =J80+K80 -> 50 | AK80: =(K80*AI80)/I80 -> 25 | AL80: =AE80+AK80 -> 50 | AM80: =Q80 -> 100 | AP80: =AVERAGE(AM80:AO80) -> 100 | AQ80: =J80+K80+L80 -> 75 | AR80: =(L80*AP80)/I80 -> 25 | AS80: =AE80+AK80+AR80 -> 75 | AW80: =AVERAGE(AT80:AV80) -> #DIV/0! | AX80: =J80+K80+L80+M80 -> 100 | AY80: =(M80*AW80)/I80 -> #DIV/0! | AZ80: =AE80+AK80+AR80+AY80 -> #DIV/0!
E81: 74 | F81: Notificar a todas las áreas las actualizaciones que se presenten mensualmente en los documentos externos declarados. | G81: Mensual | H81: Porcentaje | I81: 100 | J81: 25 | K81: 25 | L81: 25 | M81: 25 | N81: X | P81: SI | Q81: 100 | R81: Se notificó al 100% a las áreas las actualizaciones en los documentos externos. | S81: NA | T81: NA | U81: NA | V81: Denisse López | Z81: 100 | AA81: 100 | AB81: 100 | AC81: =AVERAGE(Z81:AB81) -> 100 | AD81: =J81 -> 25 | AE81: =(J81*AC81)/I81 -> 25 | AF81: 100 | AG81: 100 | AH81: 100 | AI81: =AVERAGE(AF81:AH81) -> 100 | AJ81: =J81+K81 -> 50 | AK81: =(K81*AI81)/I81 -> 25 | AL81: =AE81+AK81 -> 50 | AM81: =Q81 -> 100 | AP81: =AVERAGE(AM81:AO81) -> 100 | AQ81: =J81+K81+L81 -> 75 | AR81: =(L81*AP81)/I81 -> 25 | AS81: =AE81+AK81+AR81 -> 75 | AW81: =AVERAGE(AT81:AV81) -> #DIV/0! | AX81: =J81+K81+L81+M81 -> 100 | AY81: =(M81*AW81)/I81 -> #DIV/0! | AZ81: =AE81+AK81+AR81+AY81 -> #DIV/0!
E82: 75 | F82: Cumplir con la elaboración de solicitudes de contrato solicitados por la gerencia de licitaciones de conformidad al procedimiento OOMPJU-07. | G82: Mensual | H82: Porcentaje | I82: 100 | J82: 25 | K82: 25 | L82: 25 | M82: 25 | N82: X | P82: SI | Q82: 100 | R82: Se cumplió al 100% con las solicitudes de contrato. | S82: NA | T82: NA | U82: NA | V82: Rodrigo Badilla | Z82: 100 | AA82: 100 | AB82: 100 | AC82: =AVERAGE(Z82:AB82) -> 100 | AD82: =J82 -> 25 | AE82: =(J82*AC82)/I82 -> 25 | AF82: 100 | AG82: 100 | AH82: 100 | AI82: =AVERAGE(AF82:AH82) -> 100 | AJ82: =J82+K82 -> 50 | AK82: =(K82*AI82)/I82 -> 25 | AL82: =AE82+AK82 -> 50 | AM82: =Q82 -> 100 | AP82: =AVERAGE(AM82:AO82) -> 100 | AQ82: =J82+K82+L82 -> 75 | AR82: =(L82*AP82)/I82 -> 25 | AS82: =AE82+AK82+AR82 -> 75 | AW82: =AVERAGE(AT82:AV82) -> #DIV/0! | AX82: =J82+K82+L82+M82 -> 100 | AY82: =(M82*AW82)/I82 -> #DIV/0! | AZ82: =AE82+AK82+AR82+AY82 -> #DIV/0!
E83: 76 | F83: Índice de juntas de gobierno. | G83: Mensual | H83: Porcentaje | I83: 100 | J83: 25 | K83: 25 | L83: 25 | M83: 25 | N83: X | P83: SI | Q83: 100 | R83: Se convocó a 1 junta de gobierno en el mes. | S83: NA | T83: NA | U83: NA | V83: Denisse López | Z83: 100 | AA83: 100 | AB83: 100 | AC83: =AVERAGE(Z83:AB83) -> 100 | AD83: =J83 -> 25 | AE83: =(J83*AC83)/I83 -> 25 | AF83: 100 | AG83: 100 | AH83: 100 | AI83: =AVERAGE(AF83:AH83) -> 100 | AJ83: =J83+K83 -> 50 | AK83: =(K83*AI83)/I83 -> 25 | AL83: =AE83+AK83 -> 50 | AM83: =Q83 -> 100 | AP83: =AVERAGE(AM83:AO83) -> 100 | AQ83: =J83+K83+L83 -> 75 | AR83: =(L83*AP83)/I83 -> 25 | AS83: =AE83+AK83+AR83 -> 75 | AW83: =AVERAGE(AT83:AV83) -> #DIV/0! | AX83: =J83+K83+L83+M83 -> 100 | AY83: =(M83*AW83)/I83 -> #DIV/0! | AZ83: =AE83+AK83+AR83+AY83 -> #DIV/0!
C84: Administrativa | D84: Direccion Administrativa | E84: 77 | F84: Índice de eficiencia administrativa. | G84: Trimestral | H84: Porcentaje | I84: 90 | J84: 22 | K84: 23 | L84: 22 | M84: 23 | N84: X | P84: SI | Q84: 0 | R84: En el 2do trimestre se cumplió al 93% con la eficiencia administrativa. | S84: NA | T84: NA | U84: NA | V84: Sonia Ochoa | Z84: 0 | AA84: 0 | AB84: 93 | AC84: =AB84 -> 93 | AD84: =J84 -> 22 | AE84: =(J84*AC84)/I84 -> 22.733333 | AF84: 0 | AG84: 0 | AH84: 93 | AI84: =AH84 -> 93 | AJ84: =J84+K84 -> 45 | AK84: =(K84*AI84)/I84 -> 23.766667 | AL84: =AE84+AK84 -> 46.5 | AM84: =Q84 -> 0 | AP84: =AO84 -> 0 | AQ84: =J84+K84+L84 -> 67 | AR84: =(L84*AP84)/I84 -> 0 | AS84: =AE84+AK84+AR84 -> 46.5 | AW84: =AV84 -> 0 | AX84: =J84+K84+L84+M84 -> 90 | AY84: =(M84*AW84)/I84 -> 0 | AZ84: =AE84+AK84+AR84+AY84 -> 46.5
E85: 78 | F85: Sistema de gestión por comparación cuestionario único de información básica. | G85: Anual | H85: Porcentaje | I85: 100 | J85: 100 | K85: 0 | L85: 0 | M85: 0 | N85: X | P85: SI | Q85: 0 | R85: Se cumplió con la entrega del cuestionario único de información básica. | S85: NA | T85: NA | U85: NA | V85: Sonia Ochoa | Z85: 0 | AA85: 0 | AB85: 100 | AC85: =AB85 -> 100 | AD85: =J85 -> 100 | AE85: =AC85 -> 100 | AF85: 0 | AG85: 0 | AH85: 0 | AI85: =AH85 -> 0 | AJ85: =J85+K85 -> 100 | AK85: =AI85 -> 0 | AL85: =AE85+AK85 -> 100 | AM85: =Q85 -> 0 | AP85: =AO85 -> 0 | AQ85: =J85+K85+L85 -> 100 | AR85: =AP85 -> 0 | AS85: =AE85+AK85+AR85 -> 100 | AW85: =AV85 -> 0 | AX85: =J85+K85+L85+M85 -> 100 | AY85: =AW85 -> 0 | AZ85: =AE85+AK85+AR85+AY85 -> 100
D86: Mtto. y servicios generales | E86: 79 | F86: Cumplimiento de la satisfacción del cliente. | G86: Mensual | H86: Porcentaje | I86: 94 | J86: 23 | K86: 24 | L86: 23 | M86: 24 | N86: X | P86: SI | Q86: 94 | R86: Se cumplió al 94% con la satisfacción del cliente. | S86: N/A | T86: N/A | U86: N/A | V86: Jazmín Sortillón | Z86: 95 | AA86: 94 | AB86: 94 | AC86: =AVERAGE(Z86:AB86) -> 94.333333 | AD86: =J86 -> 23 | AE86: =(J86*AC86)/I86 -> 23.08156 | AF86: 95 | AG86: 95 | AH86: 95 | AI86: =AVERAGE(AF86:AH86) -> 95 | AJ86: =J86+K86 -> 47 | AK86: =(K86*AI86)/I86 -> 24.255319 | AL86: =AE86+AK86 -> 47.336879 | AM86: =Q86 -> 94 | AP86: =AVERAGE(AM86:AO86) -> 94 | AQ86: =J86+K86+L86 -> 70 | AR86: =(L86*AP86)/I86 -> 23 | AS86: =AE86+AK86+AR86 -> 70.336879 | AW86: =AVERAGE(AT86:AV86) -> #DIV/0! | AX86: =J86+K86+L86+M86 -> 94 | AY86: =(M86*AW86)/I86 -> #DIV/0! | AZ86: =AE86+AK86+AR86+AY86 -> #DIV/0!
D87: Seguridad Industrial | E87: 80 | F87: Satisfacción del cliente | G87: Mensual | H87: Porcentaje | I87: 90 | J87: 23 | K87: 22 | L87: 23 | M87: 22 | N87: X | P87: SI | Q87: 100 | R87: Se cumplió al 100% con la satisfacción del cliente. | S87: NA | T87: NA | U87: NA | V87: Martín Ávila | Z87: 100 | AA87: 100 | AB87: 100 | AC87: =AVERAGE(Z87:AB87) -> 100 | AD87: =J87 -> 23 | AE87: =(J87*AC87)/I87 -> 25.555556 | AF87: 100 | AG87: 100 | AH87: 100 | AI87: =AVERAGE(AF87:AH87) -> 100 | AJ87: =J87+K87 -> 45 | AK87: =(K87*AI87)/I87 -> 24.444444 | AL87: =AE87+AK87 -> 50 | AM87: =Q87 -> 100 | AP87: =AVERAGE(AM87:AO87) -> 100 | AQ87: =J87+K87+L87 -> 68 | AR87: =(L87*AP87)/I87 -> 25.555556 | AS87: =AE87+AK87+AR87 -> 75.555556 | AW87: =AVERAGE(AT87:AV87) -> #DIV/0! | AX87: =J87+K87+L87+M87 -> 90 | AY87: =(M87*AW87)/I87 -> #DIV/0! | AZ87: =AE87+AK87+AR87+AY87 -> #DIV/0!
C88: Técnica | D88: Control de Calidad | E88: 81 | F88: Cumplir con las auditorías para la acreditación de la NMX-EC-17025-IMNC-2018 y/o ISO/IEC 17025:2017. | G88: Anual | H88: Informes | I88: 2 | J88: 0 | K88: 2 | L88: 0 | M88: 0 | O88: X | P88: SI | Q88: 1 | R88: Se llevó a cabo la auditoría durante el mes de julio. | S88: NA | T88: NA | U88: NA | V88: Lenia Luzanilla | Z88: 0 | AA88: 0 | AB88: 0 | AC88: =SUM(Z88:AB88) -> 0 | AD88: =J88 -> 0 | AE88: =AC88 -> 0 | AF88: 0 | AG88: 0 | AH88: 1 | AI88: =SUM(AF88:AH88) -> 1 | AJ88: =J88+K88 -> 2 | AK88: =AI88 -> 1 | AL88: =AE88+AK88 -> 1 | AM88: =Q88 -> 1 | AP88: =SUM(AM88:AO88) -> 1 | AQ88: =J88+K88+L88 -> 2 | AR88: =AP88 -> 1 | AS88: =AE88+AK88+AR88 -> 2 | AW88: =SUM(AT88:AV88) -> 0 | AX88: =J88+K88+L88+M88 -> 2 | AY88: =AW88 -> 0 | AZ88: =AE88+AK88+AR88+AY88 -> 2
D89: Alcantarillado y Saneamiento | E89: 82 | F89: Índice de cumplimiento de reportes atendidos | G89: Mensual | H89: Porcentaje | I89: 100 | J89: 25 | K89: 25 | L89: 25 | M89: 25 | O89: X | P89: SI | Q89: 142 | R89: Se cumplió al 142% con el índice de reportes atendidos. | S89: NA | T89: NA | U89: NA | V89: Jorge Fernández | Z89: 201.33 | AA89: 152.17 | AB89: 259.83 | AC89: =AVERAGE(Z89:AB89) -> 204.44333 | AD89: =J89 -> 25 | AE89: =(J89*AC89)/I89 -> 51.110833 | AF89: 273.33 | AG89: 197.67 | AH89: 198.33 | AI89: =AVERAGE(AF89:AH89) -> 223.11 | AJ89: =J89+K89 -> 50 | AK89: =(K89*AI89)/I89 -> 55.7775 | AL89: =AE89+AK89 -> 106.88833 | AM89: =Q89 -> 142 | AP89: =AVERAGE(AM89:AO89) -> 142 | AQ89: =J89+K89+L89 -> 75 | AR89: =(L89*AP89)/I89 -> 35.5 | AS89: =AE89+AK89+AR89 -> 142.38833 | AW89: =AVERAGE(AT89:AV89) -> #DIV/0! | AX89: =J89+K89+L89+M89 -> 100 | AY89: =(M89*AW89)/I89 -> #DIV/0! | AZ89: =AE89+AK89+AR89+AY89 -> #DIV/0!
E90: 83 | F90: Cumplimiento del programa de inspecciones | G90: Mensual | H90: Porcentaje | I90: 100 | J90: 25 | K90: 25 | L90: 25 | M90: 25 | O90: X | P90: SI | Q90: 100 | R90: Se cumplió al 100% con el programa de inspecciones. | S90: NA | T90: NA | U90: NA | V90: Jorge Fernández | Z90: 100 | AA90: 100 | AB90: 100 | AC90: =AVERAGE(Z90:AB90) -> 100 | AD90: =J90 -> 25 | AE90: =(J90*AC90)/I90 -> 25 | AF90: 100 | AG90: 100 | AH90: 100 | AI90: =AVERAGE(AF90:AH90) -> 100 | AJ90: =J90+K90 -> 50 | AK90: =(K90*AI90)/I90 -> 25 | AL90: =AE90+AK90 -> 50 | AM90: =Q90 -> 100 | AP90: =AVERAGE(AM90:AO90) -> 100 | AQ90: =J90+K90+L90 -> 75 | AR90: =(L90*AP90)/I90 -> 25 | AS90: =AE90+AK90+AR90 -> 75 | AW90: =AVERAGE(AT90:AV90) -> #DIV/0! | AX90: =J90+K90+L90+M90 -> 100 | AY90: =(M90*AW90)/I90 -> #DIV/0! | AZ90: =AE90+AK90+AR90+AY90 -> #DIV/0!
D91: Suburbano Técnico | E91: 84 | F91: Atención a reportes suburbanos | G91: Mensual | H91: Porcentaje | I91: 100 | J91: 25 | K91: 25 | L91: 25 | M91: 25 | O91: X | P91: SI | Q91: 103.22 | R91: Se cumplió en la atención de reportes suburbanos programados. | S91: NA | T91: NA | U91: NA | V91: Ana Karen Pérez | Z91: 177 | AA91: 175 | AB91: 172 | AC91: =AVERAGE(Z91:AB91) -> 174.66667 | AD91: =J91 -> 25 | AE91: =(J91*AC91)/I91 -> 43.666667 | AF91: 236 | AG91: 106.44 | AH91: 140.22 | AI91: =AVERAGE(AF91:AH91) -> 160.88667 | AJ91: =J91+K91 -> 50 | AK91: =(K91*AI91)/I91 -> 40.221667 | AL91: =AE91+AK91 -> 83.888333 | AM91: =Q91 -> 103.22 | AP91: =AVERAGE(AM91:AO91) -> 103.22 | AQ91: =J91+K91+L91 -> 75 | AR91: =(L91*AP91)/I91 -> 25.805 | AS91: =AE91+AK91+AR91 -> 109.69333 | AW91: =AVERAGE(AT91:AV91) -> #DIV/0! | AX91: =J91+K91+L91+M91 -> 100 | AY91: =(M91*AW91)/I91 -> #DIV/0! | AZ91: =AE91+AK91+AR91+AY91 -> #DIV/0!
D92: Subdirección de Operación y Mantenimiento | E92: 85 | F92: Índice de cumplimiento en los indicadores de las gerencias de la Subdirección de Operación y Mantenimiento. | G92: Trimestral | H92: Porcentaje | I92: 100 | J92: 25 | K92: 25 | L92: 25 | M92: 25 | N92: X | P92: NO | Q92: 94 | R92: No se cumplió en los indicadores de la gerencia de plantas potabilizadoras. | S92: NA | T92: AC 17/2025 AC 10/2026 | U92: NA | V92: Eduardo Rochín | W92: Vence 29 Mayo 2026. Replanteada el 28 de diciembre 2026. Vence 31 de Dic. 2026. | Z92: 92 | AA92: 92 | AB92: 77 | AC92: =AVERAGE(Z92:AB92) -> 87 | AD92: =J92 -> 25 | AE92: =(J92*AC92)/I92 -> 21.75 | AF92: 85 | AG92: 77 | AH92: 85 | AI92: =AVERAGE(AF92:AH92) -> 82.333333 | AJ92: =J92+K92 -> 50 | AK92: =(K92*AI92)/I92 -> 20.583333 | AL92: =AE92+AK92 -> 42.333333 | AM92: =Q92 -> 94 | AP92: =AVERAGE(AM92:AO92) -> 94 | AQ92: =J92+K92+L92 -> 75 | AR92: =(L92*AP92)/I92 -> 23.5 | AS92: =AE92+AK92+AR92 -> 65.833333 | AW92: =AVERAGE(AT92:AV92) -> #DIV/0! | AX92: =J92+K92+L92+M92 -> 100 | AY92: =(M92*AW92)/I92 -> #DIV/0! | AZ92: =AE92+AK92+AR92+AY92 -> #DIV/0!
D93: Subdirección de Proyectos e Infraestructura | E93: 86 | F93: Índice de cumplimiento en los indicadores de las gerencias de la Subdirección de Proyectos e Infraestructura. | G93: Trimestral | H93: Porcentaje | I93: 100 | J93: 25 | K93: 25 | L93: 25 | M93: 25 | N93: X | P93: SI | Q93: 100 | R93: Se cumplió al 100% en los indicadores de las gerencias de la Subdirección de Proyectos e Infraestructura. | S93: NA | T93: NA | U93: NA | V93: Manuel Enríquez | Z93: 100 | AA93: 100 | AB93: 100 | AC93: =AVERAGE(Z93:AB93) -> 100 | AD93: =J93 -> 25 | AE93: =(J93*AC93)/I93 -> 25 | AF93: 100 | AG93: 100 | AH93: 100 | AI93: =AVERAGE(AF93:AH93) -> 100 | AJ93: =J93+K93 -> 50 | AK93: =(K93*AI93)/I93 -> 25 | AL93: =AE93+AK93 -> 50 | AM93: =Q93 -> 100 | AP93: =AVERAGE(AM93:AO93) -> 100 | AQ93: =J93+K93+L93 -> 75 | AR93: =(L93*AP93)/I93 -> 25 | AS93: =AE93+AK93+AR93 -> 75 | AW93: =AVERAGE(AT93:AV93) -> #DIV/0! | AX93: =J93+K93+L93+M93 -> 100 | AY93: =(M93*AW93)/I93 -> #DIV/0! | AZ93: =AE93+AK93+AR93+AY93 -> #DIV/0!
A94: 7 | B94: Proyectos e Infraestructura | C94: Técnica | D94: Supervisión de Obras | E94: 87 | F94: Cumplir con tiempo, costo y calidad definidos en la supervisión de obras según proyecto autorizado | G94: Mensual | H94: Porcentaje | I94: 100 | J94: 25 | K94: 25 | L94: 25 | M94: 25 | N94: X | P94: SI | Q94: 100 | R94: Se cumplió al 100% con el tiempo, costo y calidad definidos en la supervisión de obras según proyecto autorizado. | S94: NA | T94: NA | U94: NA | V94: Joel Acuña | Z94: 100 | AA94: 100 | AB94: 100 | AC94: =AVERAGE(Z94:AB94) -> 100 | AD94: =J94 -> 25 | AE94: =(J94*AC94)/I94 -> 25 | AF94: 100 | AG94: 100 | AH94: 100 | AI94: =AVERAGE(AF94:AH94) -> 100 | AJ94: =J94+K94 -> 50 | AK94: =(K94*AI94)/I94 -> 25 | AL94: =AE94+AK94 -> 50 | AM94: =Q94 -> 100 | AP94: =AVERAGE(AM94:AO94) -> 100 | AQ94: =J94+K94+L94 -> 75 | AR94: =(L94*AP94)/I94 -> 25 | AS94: =AE94+AK94+AR94 -> 75 | AW94: =AVERAGE(AT94:AV94) -> #DIV/0! | AX94: =J94+K94+L94+M94 -> 100 | AY94: =(M94*AW94)/I94 -> #DIV/0! | AZ94: =AE94+AK94+AR94+AY94 -> #DIV/0!
D95: Proyectos e Infraestructura | E95: 88 | F95: Elaboración de prefactibilidades | G95: Mensual | H95: Porcentaje | I95: 100 | J95: 25 | K95: 25 | L95: 25 | M95: 25 | N95: X | P95: SI | Q95: 100 | R95: Se cumplió al 100% con la elaboración de prefactibilidades en el mes. | S95: NA | T95: NA | U95: NA | V95: Oswaldo Sauceda | Z95: 100 | AA95: 100 | AB95: 100 | AC95: =AVERAGE(Z95:AB95) -> 100 | AD95: =J95 -> 25 | AE95: =(J95*AC95)/I95 -> 25 | AF95: 100 | AG95: 100 | AH95: 100 | AI95: =AVERAGE(AF95:AH95) -> 100 | AJ95: =J95+K95 -> 50 | AK95: =(K95*AI95)/I95 -> 25 | AL95: =AE95+AK95 -> 50 | AM95: =Q95 -> 100 | AP95: =AVERAGE(AM95:AO95) -> 100 | AQ95: =J95+K95+L95 -> 75 | AR95: =(L95*AP95)/I95 -> 25 | AS95: =AE95+AK95+AR95 -> 75 | AW95: =AVERAGE(AT95:AV95) -> #DIV/0! | AX95: =J95+K95+L95+M95 -> 100 | AY95: =(M95*AW95)/I95 -> #DIV/0! | AZ95: =AE95+AK95+AR95+AY95 -> #DIV/0!
E96: 89 | F96: Aprobación de proyectos de agua potable y/o alcantarillado sanitario | G96: Mensual | H96: Porcentaje | I96: 100 | J96: 25 | K96: 25 | L96: 25 | M96: 25 | N96: X | P96: SI | Q96: 100 | R96: Se cumplió al 100% con las aprobaciones de proyectos de agua potable y/o alcantarillado sanitario. | S96: NA | T96: NA | U96: NA | V96: Oswaldo Sauceda | Z96: 100 | AA96: 100 | AB96: 100 | AC96: =AVERAGE(Z96:AB96) -> 100 | AD96: =J96 -> 25 | AE96: =(J96*AC96)/I96 -> 25 | AF96: 100 | AG96: 100 | AH96: 100 | AI96: =AVERAGE(AF96:AH96) -> 100 | AJ96: =J96+K96 -> 50 | AK96: =(K96*AI96)/I96 -> 25 | AL96: =AE96+AK96 -> 50 | AM96: =Q96 -> 100 | AP96: =AVERAGE(AM96:AO96) -> 100 | AQ96: =J96+K96+L96 -> 75 | AR96: =(L96*AP96)/I96 -> 25 | AS96: =AE96+AK96+AR96 -> 75 | AW96: =AVERAGE(AT96:AV96) -> #DIV/0! | AX96: =J96+K96+L96+M96 -> 100 | AY96: =(M96*AW96)/I96 -> #DIV/0! | AZ96: =AE96+AK96+AR96+AY96 -> #DIV/0!
E97: 90 | F97: Elaboración de proyectos de agua potable y/o alcantarillado sanitario | G97: Mensual | H97: Porcentaje | I97: 100 | J97: 25 | K97: 25 | L97: 25 | M97: 25 | N97: X | P97: SI | Q97: 100 | R97: Se cumplió al 100% con elaboración de proyectos de agua potable y/o alcantarillado sanitario. | S97: NA | T97: NA | U97: NA | V97: Oswaldo Sauceda | Z97: 100 | AA97: 100 | AB97: 100 | AC97: =AVERAGE(Z97:AB97) -> 100 | AD97: =J97 -> 25 | AE97: =(J97*AC97)/I97 -> 25 | AF97: 100 | AG97: 100 | AH97: 100 | AI97: =AVERAGE(AF97:AH97) -> 100 | AJ97: =J97+K97 -> 50 | AK97: =(K97*AI97)/I97 -> 25 | AL97: =AE97+AK97 -> 50 | AM97: =Q97 -> 100 | AP97: =AVERAGE(AM97:AO97) -> 100 | AQ97: =J97+K97+L97 -> 75 | AR97: =(L97*AP97)/I97 -> 25 | AS97: =AE97+AK97+AR97 -> 75 | AW97: =AVERAGE(AT97:AV97) -> #DIV/0! | AX97: =J97+K97+L97+M97 -> 100 | AY97: =(M97*AW97)/I97 -> #DIV/0! | AZ97: =AE97+AK97+AR97+AY97 -> #DIV/0!
E98: 91 | F98: Elaboración de viabilidad comercial e industrial | G98: Mensual | H98: Porcentaje | I98: 100 | J98: 25 | K98: 25 | L98: 25 | M98: 25 | N98: X | P98: SI | Q98: 100 | R98: Se cumplió al 100% con la elaboración de viabilidad comercial e industrial. | S98: NA | T98: NA | U98: NA | V98: Oswaldo Sauceda | Z98: 100 | AA98: 100 | AB98: 100 | AC98: =AVERAGE(Z98:AB98) -> 100 | AD98: =J98 -> 25 | AE98: =(J98*AC98)/I98 -> 25 | AF98: 100 | AG98: 100 | AH98: 100 | AI98: =AVERAGE(AF98:AH98) -> 100 | AJ98: =J98+K98 -> 50 | AK98: =(K98*AI98)/I98 -> 25 | AL98: =AE98+AK98 -> 50 | AM98: =Q98 -> 100 | AP98: =AVERAGE(AM98:AO98) -> 100 | AQ98: =J98+K98+L98 -> 75 | AR98: =(L98*AP98)/I98 -> 25 | AS98: =AE98+AK98+AR98 -> 75 | AW98: =AVERAGE(AT98:AV98) -> #DIV/0! | AX98: =J98+K98+L98+M98 -> 100 | AY98: =(M98*AW98)/I98 -> #DIV/0! | AZ98: =AE98+AK98+AR98+AY98 -> #DIV/0!
D99: Sectorización Hidrométrica e Innovación | E99: 92 | F99: Elaboración de proyectos para mejoramiento de la eficiencia | G99: Mensual | H99: Porcentaje | I99: 100 | J99: 25 | K99: 25 | L99: 25 | M99: 25 | N99: X | P99: SI | Q99: 100 | R99: Se cumplió al 100% con la elaboración de proyectos. | S99: NA | T99: NA | U99: NA | V99: Ana Cristina Solis | Z99: 100 | AA99: 100 | AB99: 100 | AC99: =AVERAGE(Z99:AB99) -> 100 | AD99: =J99 -> 25 | AE99: =(J99*AC99)/I99 -> 25 | AF99: 100 | AG99: 100 | AH99: 100 | AI99: =AVERAGE(AF99:AH99) -> 100 | AJ99: =J99+K99 -> 50 | AK99: =(K99*AI99)/I99 -> 25 | AL99: =AE99+AK99 -> 50 | AM99: =Q99 -> 100 | AP99: =AVERAGE(AM99:AO99) -> 100 | AQ99: =J99+K99+L99 -> 75 | AR99: =(L99*AP99)/I99 -> 25 | AS99: =AE99+AK99+AR99 -> 75 | AW99: =AVERAGE(AT99:AV99) -> #DIV/0! | AX99: =J99+K99+L99+M99 -> 100 | AY99: =(M99*AW99)/I99 -> #DIV/0! | AZ99: =AE99+AK99+AR99+AY99 -> #DIV/0!
E100: 93 | F100: Detecciones de infraestructura subterránea. | G100: Mensual | H100: Porcentaje | I100: 100 | J100: 25 | K100: 25 | L100: 25 | M100: 25 | N100: X | P100: SI | Q100: 100 | R100: Se cumplió al 100% con las detecciones de infraestructura subterránea solicitadas. | S100: NA | T100: NA | U100: NA | V100: Ana Cristina Solis | Z100: 100 | AA100: 100 | AB100: 100 | AC100: =AVERAGE(Z100:AB100) -> 100 | AD100: =J100 -> 25 | AE100: =(J100*AC100)/I100 -> 25 | AF100: 100 | AG100: 100 | AH100: 100 | AI100: =AVERAGE(AF100:AH100) -> 100 | AJ100: =J100+K100 -> 50 | AK100: =(K100*AI100)/I100 -> 25 | AL100: =AE100+AK100 -> 50 | AM100: =Q100 -> 100 | AP100: =AVERAGE(AM100:AO100) -> 100 | AQ100: =J100+K100+L100 -> 75 | AR100: =(L100*AP100)/I100 -> 25 | AS100: =AE100+AK100+AR100 -> 75 | AW100: =AVERAGE(AT100:AV100) -> #DIV/0! | AX100: =J100+K100+L100+M100 -> 100 | AY100: =(M100*AW100)/I100 -> #DIV/0! | AZ100: =AE100+AK100+AR100+AY100 -> #DIV/0!
...

Sheet REPORTES DE CORRECCIÓN
B3: 2023 | C3: RC 4/2023 | D3: OCI | E3: CERRADA
C4: RC 8, 9/2023 | D4: SGC | E4: CERRADA
B5: 2024 | C5: RC 01 | D5: MIGUEL | E5: CERRADA
C6: RC 02 | D6: HECTOR | E6: CERRADA
C7: RC 03 | D7: MIGUEL | E7: CERRADA
C8: RC 04 | D8: HECTOR | E8: CERRADA
C9: RC 05 | D9: HECTOR | E9: CERRADA
C10: RC 06 | D10: PADRÓN | E10: CERRADA
C11: RC 07 | D11: HECTOR | E11: CERRADA
C12: RC 08 | D12: HECTOR | E12: CERRADA
C13: RC 09 | D13: EVELYN | E13: CERRADA
B14: 2025 | C14: RC 01 | D14: EVELYN | E14: CERRADA
C15: RC 02 | D15: PADRÓN | E15: CERRADA
C16: RC 03 | D16: PADRÓN | E16: CERRADA
C17: RC 04 | D17: MIGUEL | E17: CERRADA
C18: RC 05 | D18: ALFREDO | E18: CERRADA
C19: RC 06 | D19: MIGUEL | E19: CERRADA
C20: RC 07 | D20: EVELYN | E20: CERRADA
C21: RC 08 | D21: HECTOR | E21: ABIERTA
C22: RC 09 | D22: EVELYN | E22: CERRADA
C23: RC 10 | D23: MIGUEL | E23: CERRADA
C24: RC 11 | D24: Ana Cecilia | E24: CERRADA
C25: RC 12 | D25: EVELYN | E25: ABIERTA
B26: 2026 | C26: RC 01 | D26: MIGUEL | E26: CERRADA
C27: RC 02 | D27: EVELYN | E27: CERRADA
C28: RC 03 | D28: EVELYN | E28: ABIERTA
C29: RC 04 | D29: ANA CECILIA | E29: ABIERTA
C30: RC 05 | D30: MIGUEL | E30: CERRADA
C31: RC 06 | D31: Jazmín Sortillón | E31: CERRADA
C32: RC 07 | D32: EVELYN | E32: ABIERTA
C33: RC 08 | D33: MIGUEL | E33: ABIERTA
C34: RC 09 | D34: JAZMÍN | E34: ABIERTA

Sheet Hoja1
C5: Técnica | D5: Trámites Técnicos | E5: Índice de programas federales gestionados | F5: ='OOMRSC-05'!P21 -> SI | G5: ='OOMRSC-05'!Q21 -> 0
C6: Técnica | D6: Supervisión de Obras | E6: Cumplir con tiempo, costo y calidad definidos en la supervisión de obras. | F6: ='OOMRSC-05'!P94 -> SI | G6: ='OOMRSC-05'!Q94 -> 100
D7: Proyectos e Infraestructura | E7: Elaboración de prefactibilidades | F7: ='OOMRSC-05'!P95 -> SI | G7: ='OOMRSC-05'!Q95 -> 100
E8: Aprobación de proyectos de agua potable y/o alcantarillado sanitario | F8: ='OOMRSC-05'!P96 -> SI | G8: ='OOMRSC-05'!Q96 -> 100
E9: Elaboración de proyectos de agua potable y/o alcantarillado sanitario | F9: ='OOMRSC-05'!P97 -> SI | G9: ='OOMRSC-05'!Q97 -> 100
E10: Elaboración de viabilidad comercial e industrial | F10: ='OOMRSC-05'!P98 -> SI | G10: ='OOMRSC-05'!Q98 -> 100
D11: Sectorización Hidrométrica e Innovación | E11: Elaboración de proyectos para el mejoramiento de la eficiencia física y/o energética | F11: ='OOMRSC-05'!P99 -> SI | G11: ='OOMRSC-05'!Q99 -> 100
E12: Detecciones de infraestructura subterránea. | F12: ='OOMRSC-05'!P100 -> SI | G12: ='OOMRSC-05'!Q100 -> 100
D13: Trámites Técnicos | E13: Índice de cumplimiento de tiempo para cálculo de Derechos de Conexión. | F13: ='OOMRSC-05'!P101 -> SI | G13: ='OOMRSC-05'!Q101 -> 100
F14: =COUNTIF(F5:F13,"si") -> 9 | G14: =F14/9 -> 1
C16: Técnica | D16: Mantenimiento de Redes | E16: Atender los reportes de los usuarios de la ciudad. | F16: ='OOMRSC-05'!P31 -> SI | G16: ='OOMRSC-05'!Q31 -> 103
D17: Control de Calidad | E17: Cumplir con programa de calibración y verificación de equipos de medición. | F17: ='OOMRSC-05'!P32 -> SI | G17: ='OOMRSC-05'!Q32 -> 0
D18: Plantas Potabilizadoras | E18: Índice de cumplimiento de los programas de mantenimiento a instalaciones y mantenimiento electromecánico preventivo y correctivo | F18: ='OOMRSC-05'!P33 -> SI | G18: ='OOMRSC-05'!Q33 -> 100
D19: Alcantarillado y Saneamiento | E19: Programa de mantenimiento de redes sanitaria | F19: ='OOMRSC-05'!P34 -> SI | G19: ='OOMRSC-05'!Q34 -> 107
D20: Suburbano Técnico | E20: Cumplir con el programa anual de mantenimiento preventivo a equipos de cloración y dosificación | F20: ='OOMRSC-05'!P35 -> SI | G20: ='OOMRSC-05'!Q35 -> 0
E21: Cumplir con el programa anual de mantenimiento preventivo y toma de parámetros eléctrico y mecánicos | F21: ='OOMRSC-05'!P36 -> SI | G21: ='OOMRSC-05'!Q36 -> 100
C22: Técnica | D22: Control de Calidad | E22: Cumplimiento a NOM-127-SSA1-2021 aplicable a control de calidad. | F22: ='OOMRSC-05'!P52 -> SI | G22: ='OOMRSC-05'!Q52 -> 875
E23: Índice de cumplimiento en muestreos y análisis de agua potable. | F23: ='OOMRSC-05'!P53 -> SI | G23: ='OOMRSC-05'!Q53 -> 0
D24: Plantas Potabilizadoras | E24: Producción de agua en plantas potabilizadoras y pozos de área urbana | F24: ='OOMRSC-05'!P54 -> SI | G24: ='OOMRSC-05'!Q54 -> 3797664
E25: Índice de cobertura de macromedición | F25: ='OOMRSC-05'!P55 -> NO | G25: ='OOMRSC-05'!Q55 -> 57
D26: Alcantarillado y Saneamiento | E26: Índice de agua residual tratada. | F26: ='OOMRSC-05'!P56 -> SI | G26: ='OOMRSC-05'!Q56 -> 100
E27: Programa de muestreo y análisis de aguas residuales | F27: ='OOMRSC-05'!P57 -> SI | G27: ='OOMRSC-05'!Q57 -> 100
D28: Suburbano Técnico | E28: Cumplir con el volumen de agua potabilizada. | F28: ='OOMRSC-05'!P58 -> SI | G28: ='OOMRSC-05'!Q58 -> 1241188
C29: Técnica | D29: Control de Calidad | E29: Cumplir con las auditorías para la acreditación de la NMX-EC-17025-IMNC-2018 y/o ISO/IEC 17025:2017. | F29: ='OOMRSC-05'!P88 -> SI | G29: ='OOMRSC-05'!Q88 -> 1
D30: Alcantarillado y Saneamiento | E30: Índice de cumplimiento de reportes atendidos | F30: ='OOMRSC-05'!P89 -> SI | G30: ='OOMRSC-05'!Q89 -> 142
E31: Cumplimiento del programa de inspecciones | F31: ='OOMRSC-05'!P90 -> SI | G31: ='OOMRSC-05'!Q90 -> 100
D32: Suburbano Técnico | E32: Índice de atención a reportes suburbanos. | F32: ='OOMRSC-05'!P91 -> SI | G32: ='OOMRSC-05'!Q91 -> 103.22
F33: =COUNTIF(F16:F32,"si") -> 16 | G33: =F33/17 -> 0.94117647

Sheet Hoja2
B3: Meta MIR 2026
B4: Meta Anual | C4: 1er Trim. | D4: 2do Trim. | E4: 3er Trim. | F4: 4to Trim. | H4: LLENAR LO QUE ESTÁ EN AMARILLO
B5: 95 | C5: 24 | D5: 24 | E5: 24 | F5: 23
B7: Resultado Indicador Mensual
B8: Enero | C8: Febrero | D8: Marzo | E8: Abril | F8: Mayo | G8: Junio | H8: Julio | I8: Agosto | J8: Septiembre | K8: Octubre | L8: Noviembre | M8: Diciembre
B9: 100 | C9: 100 | D9: 100 | E9: 100 | F9: 100 | G9: 100
K10: LLENAR LO QUE ESTA EN AMARILLO
B11: Resultado de Indicadores (OP 12)
B12: 1er Trim. | D12: 2do Trim. | F12: 3er Trim. | H12: 4to Trim.
B13: Programada | C13: Real | D13: Programada | E13: Real | F13: Programada | G13: Real | H13: Programada | I13: Real
B14: =C5 -> 24 | C14: =(AVERAGE(B9:D9)*(C5))/B5 -> 25.263158 | D14: =C5+D5 -> 48 | E14: =((AVERAGE(E9:G9)*(D5))/B5)+C14 -> 50.526316 | F14: =C5+D5+E5 -> 72 | G14: =((AVERAGE(H9:J9)*(E5))/B5)+E14 -> #DIV/0! | H14: =C5+D5+E5+F5 -> 95 | I14: =((AVERAGE(K9:M9)*(F5))/B5)+G14 -> #DIV/0!

Sheet Hoja3
B3: Meta MIR 2026
B4: Meta Anual | C4: 1er Trim. | D4: 2do Trim. | E4: 3er Trim. | F4: 4to Trim. | H4: LLENAR LO QUE ESTÁ EN AMARILLO
B5: 90 | C5: 22 | D5: 23 | E5: 22 | F5: 23
B7: Resultado Indicador Mensual
B8: Enero | C8: Febrero | D8: Marzo | E8: Abril | F8: Mayo | G8: Junio | H8: Julio | I8: Agosto | J8: Septiembre | K8: Octubre | L8: Noviembre | M8: Diciembre
B9: na | C9: na | D9: 93 | E9: na | F9: na | G9: 93 | H9: na | I9: na | J9: 100 | K9: na | L9: na | M9: 100
K10: LLENAR LO QUE ESTA EN AMARILLO
B11: Resultado de Indicadores (OP 12)
B12: 1er Trim. | D12: 2do Trim. | F12: 3er Trim. | H12: 4to Trim.
B13: Programada | C13: Real | D13: Programada | E13: Real | F13: Programada | G13: Real | H13: Programada | I13: Real
B14: =C5 -> 22 | C14: =D9*C5/B5 -> 22.733333 | D14: =C5+D5 -> 45 | E14: =(G9*D5/B5)+C14 -> 46.5 | F14: =C5+D5+E5 -> 67 | G14: =(J9*E5/B5)+E14 -> 70.944444 | H14: =C5+D5+E5+F5 -> 90 | I14: =(M9*F5/B5)+G14 -> 96.5
