Workbook
Name ÁREAS_responsabilidad: 'ÁREAS QUE INTEGRAN PROCESOS'!$B$4:$B$8
Name Comercialización_e: 'ENTRADAS-SALIDAS DIAGRAMA'!$C$7
Name Comercialización_L: Comercialización[ÁREAS QUE INTEGRAN EL PROCESO:]
Name Comunicación_L: Comunicación[ÁREAS QUE INTEGRAN EL PROCESO:]
Name ESCUDO: INDEX('ENTRADAS-SALIDAS DIAGRAMA'!$J$59:$J$61,MATCH('ENTRADAS-SALIDAS DIAGRAMA'!$J$3,'ENTRADAS-SALIDAS DIAGRAMA'!$I$59:$I$61,0))
Name Gestión_de_recursos_L: Gestión_de_recursos[ÁREAS QUE INTEGRAN EL PROCESO:]
Name Mantenimiento_y_calibración_L: Mantenimiento_y_calibración[ÁREAS QUE INTEGRAN EL PROCESO:]
Name Medición_análisis_y_mejora_L: Medición_análisis_y_mejora[ÁREAS QUE INTEGRAN EL PROCESO:]
Name PROCESOS: 'MATRIZ REQUISITOS ISO'!$B$7:$B$14
Name Producción_L: Producción[ÁREAS QUE INTEGRAN EL PROCESO:]
Name Proyectos_e_infraestructura_L: Proyector_e_infraestructura[ÁREAS QUE INTEGRAN EL PROCESO:]
Name Responsabilidad_de_la_dirección_L: Responsabilidad_de_la_dirección[ÁREAS QUE INTEGRAN EL PROCESO:]

Sheet Matriz
E2: REQUISITOS NORMA ISO 9001/2015
B3: ENTRADAS | D3: PROCESO | E3: 4.1 | F3: 4.2 | G3: 4.3 | H3: 4.4 | I3: 5.1 | J3: 5.2 | K3: 5.3 | L3: 6.1 | M3: 6.2 | N3: 6.3 | O3: 7.1 | P3: 7.2 | Q3: 7.3 | R3: 7.4 | S3: 7.5 | T3: 8.1 | U3: 8.2 | V3: 8.3 | W3: 8.4 | X3: 8.5 | Y3: 8.6 | Z3: 8.7 | AA3: 9.1 | AB3: 9.2 | AC3: 9.3 | AD3: 10.1 | AE3: 10.2 | AF3: 10.3 | AH3: SALIDAS
B4: {=IFERROR(_xlfn._xlws.FILTER(ENTRADAS[ENTRADAS],ENTRADAS[PROCESO]=Matriz!D4),"")} | E4: {=IFERROR(IF(_xlfn.XLOOKUP($D$4,PROCESOS,'MATRIZ REQUISITOS ISO'!D7:AE14)=0,"",_xlfn.XLOOKUP($D$4,PROCESOS,'MATRIZ REQUISITOS ISO'!D7:AE14)),"")} | AH4: {=IFERROR(_xlfn._xlws.FILTER(SALIDAS[SALIDAS],SALIDAS[PROCESO]=Matriz!D4),"")} | DB4: =_xlfn.CONCAT(D4,"_L") -> _L
D5: ÁREA: | E5: PROPÓSITO DEL PROCESO:
E6: =IFERROR(IF(_xlfn.XLOOKUP($D$4,PROCESOS,'MATRIZ REQUISITOS ISO'!AG7:AG14)=0,"",_xlfn.XLOOKUP($D$4,PROCESOS,'MATRIZ REQUISITOS ISO'!AG7:AG14)),"")
D7: DOCUMENTOS QUE INTERACTUAN CON EL ÁREA(ACTUAR): | U7: VERIFICAR:
D8: =IF($D$4="","",IFERROR(IF($D$4="Responsabilidad_de_la_dirección",VLOOKUP($D$6,Responsabilidad_de_la_dirección[],3,0),IF($D$4="Mantenimiento_y_Calibración",VLOOKUP($D$6,Mantenimiento_y_calibración[],3,0),IF($D$4="Gestión_de_Recursos",VLOOKUP($D$6,Gestión_de_recursos[],3,0),IF($D$4="comercialización",VLOOKUP($D$6,Comercialización[],3,0),IF($D$4="Producción",VLOOKUP($D$6,Producción[],3,0),IF($D$4="Medición_Análisis_y_Mejora",VLOOKUP($D$6,Medición_análisis_y_mejora[],3,0),IF($D$4="Proyectos_e_Infraestructura",VLOOKUP($D$6,Proyector_e_infraestructura[],3,0),IF($D$4="Comunicación",VLOOKUP($D$6,Comunicación[],3,0))))))))),"Verificar área a buscar del proceso")) | U8: =+IF($D$4="","","NOTA: Los registros a “Verificar” se encuentran documentados en cada uno de los procedimientos de las áreas que participan en el “Actuar” de este anexo.")
D27: PROCESOS EN LOS QUE PARTICIPA EL ÁREA:
D28: {=IF($D$6="","",_xlfn._xlws.FILTER('ÁREAS QUE INTEGRAN PROCESOS'!AH:AH,'ÁREAS QUE INTEGRAN PROCESOS'!B:B=Matriz!$D$6))} | E28: =SUBSTITUTE(IF($D$6="","",_xlfn.CONCAT(D28,CHAR(10),D29,CHAR(10),D30,CHAR(10),D31,CHAR(10),D32,CHAR(10),D33,CHAR(10),D34,CHAR(10),D35)),"_"," ")
B47: Interacciones con el SGC | T47: =IF(D6="","",D6)
C49: Indicadores: | X49: TOTAL: | Z49: =COUNTIF(KPI[Área:],$T$47) -> 0
D50: {=IFERROR(_xlfn._xlws.FILTER(KPI[Indicador o Índice:],KPI[Área:]=Matriz!$T$47),"")}
C58: Matriz de comunicación: | X58: TOTAL: | Z58: =COUNTIF(COM[área:],$T$47) -> 0
D59: {=IFERROR(_xlfn._xlws.FILTER(COM[Aspecto a comunicar],COM[área:]=Matriz!$T$47),"")}
B71: Partes Interesadas:
D73: ID | E73: Requisito: | T73: Plan de acción:
D74: {=IFERROR(_xlfn._xlws.FILTER(PI[ID],PI[Área]=$T$47),"")} | L74: {=IFERROR(_xlfn._xlws.FILTER(PI[Requisito:],PI[Área]=$T$47),"")} | S74: {=IFERROR(_xlfn._xlws.FILTER(PI[Plan de acción],PI[Área]=$T$47),"")}
B96: Interacciones con el SGC | T96: =IF($D$6="","",$D$6)
C98: Organigrama: | X98: TOTAL:
K100: =IFERROR(_xlfn.XLOOKUP($T$96,ORG[área],ORG[imagen],,0),"")

Sheet Hoja2
A2: área | B2: imagen
A3: Alcantarillado y Saneamiento | B3: #VALUE!
A4: Atención Ciudadana
A5: Comunicación e Imagen Institucional | B5: #VALUE!
A6: Contabilidad | B6: #VALUE!
A7: Contratos y Servicios | B7: #VALUE!
A8: Control de Calidad | B8: #VALUE!
A9: Control y Servicios | B9: #VALUE!
A10: Informática | B10: #VALUE!
A11: Jurídico | B11: #VALUE!
A12: Licitaciones | B12: #VALUE!
A13: Línea OOMAPASC | B13: #VALUE!
A14: Mantenimiento de Redes | B14: #VALUE!
A15: Mantenimiento y Servicios Generales | B15: #VALUE!
A16: Órgano de Control Interno | B16: #VALUE!
... A30: Verificación y Lectura | B30: #VALUE!

Sheet Consulta Matriz Comunicación
B3: Área: | C3: Supervisión y Control de Obras
B6: Aspecto a comunicar | C6: Responsable de comunicar | D6: ¿A quién le comunica? | E6: ¿Cuándo comunica? | F6: Documentos | G6: Estrategias de comunicación
B7: {=IFERROR(_xlfn._xlws.FILTER(COM[[Aspecto a comunicar]:[Estrategias de comunicación]],COM[área:]=$C$3),"")} -> Cuando se inicie una obra. | C7: Gerencia de Supervisión y Control de Obras | D7: Subdirección de Mantenimiento de redes, Comunicación Social. | E7: Al momento de iniciar con la ejecución del contrato. | F7: Mediante oficio | G7: Medios electrónicos.
B8: Resultados de la revisión por la dirección. | C8: Gerente de Supervisión y Control de Obras | D8: Personal del área. | E8: Mensual | F8: OOMRSC-04 | G8: Correo Electrónico
B9: Cobro de Estimaciones | C9: Gerencia de Supervisión y Control de Obras | D9: Departamento de Tramites técnicos | E9: Al momento de autorizar una estimación. | F9: OOMXSO-01 OOMXSO-03 | G9: EXPEDIENTES
B10: Realización de convenios de monto, tiempo y conceptos | C10: Gerencia de Supervisión y Control de Obras | D10: Departamento de Licitaciones | E10: Al momento de que se requiera modificación | F10: OOMRCL- 16 OOMRCL-17 | G10: Físicamente y Medios electrónicos.
B11: Entrega de documentación | C11: Gerencia de Supervisión y Control de Obras | D11: Subdirección de Mantenimiento de Redes, Proyectos e Infraestructura | E11: Cuando se realice alguna actualización | F11: Plano de obra terminada, Oficio al área requirente | G11: Medios electrónicos.
B12: Cuando se termine una obra. | C12: Gerencia de Supervisión y Control de Obras | D12: Subdirección de Mantenimiento de redes, Comunicación Social. | E12: Al momento de terminación del contrato. | F12: Mediante oficio | G12: Medios electrónicos, correo electrónico.
B13: Realizar una conexión | C13: Gerencia de Supervisión y Control de Obras | D13: Subdirección de Mantenimiento de redes, Comunicación Social, CATEL. | E13: Al momento de requerir programar alguna conexión | F13: OOMRSO-17 OOMXSO-08 OOMXSO-09 | G13: Entrega de documentación físicamente
B14: Activación del patrimonio | C14: Gerencia de Supervisión y Control de Obras | D14: Contabilidad | E14: Al momento de recibir un fraccionamiento | F14: Mediante oficio y copia de Acta Entrega-Recepción | G14: Entrega de documentacion fisicamente y Correo electronico

Sheet Matriz Comunicación
A1: Dirección: | B1: área: | C1: Aspecto a comunicar | D1: Responsable de comunicar | E1: ¿A quién le comunica? | F1: ¿Cuándo comunica? | G1: Documentos | H1: Estrategias de comunicación
A2: Técnica | B2: Plantas Potabilizadoras | C2: Informe de resultados de los Indicadores de Calidad | D2: Gerente de Plantas Potabilizadoras | E2: A todo el personal de la Gerencia de las Plantas Potabilizadoras, al Sistema de Gestión de Calidad | F2: Mensual | G2: OOMPPP-29 OOMPPP-32 OOMPPP-34 OOMRPP-15 OOMRPP-16 OOMRPP-18 OOMRPP-19 OOMRPP-20 OOMRPP-21 OOMRPP-27 OOMRPP-28 OOMRPP-122 OOMRPP-131 | H2: Medios electrónicos, correo electrónico, WhatsApp, ZOOM, impresos en reuniones mensuales
A3: Técnica | B3: Plantas Potabilizadoras | C3: Informe de resultados de la auditoría interna. | D3: Gerente de Plantas Potabilizadoras | E3: A todo el personal de la Gerencia de las Plantas Potabilizadoras | F3: Cuando Auditan el área | G3: OOMRSC-16 | H3: Medios electrónicos, correo electrónico, WhatsApp, ZOOM, impresos en reuniones mensuales
A4: Técnica | B4: Plantas Potabilizadoras | C4: Avances y cumplimiento en FODA y MATRIZ DE RIESGOS | D4: Gerente de Plantas Potabilizadoras | E4: Auxiliar en control de documentos del SGC | F4: Mensual | G4: OOMRSC-36 OOMRSC-37 | H4: Revisión física.
A5: Técnica | B5: Plantas Potabilizadoras | C5: Resultados de la revisión por la dirección. | D5: Gerente de Plantas Potabilizadoras | E5: A todo el personal de la Gerencia de las Plantas Potabilizadoras | F5: Mensual | G5: OOMRSC-04 | H5: Medios electrónicos, correo electrónico, WhatsApp, ZOOM, impresos en reuniones mensuales
A6: Técnica | B6: Plantas Potabilizadoras | C6: Resultados de el ambiente de trabajo | D6: Gerente de Plantas Potabilizadoras | E6: A todo el personal de la Gerencia de las Plantas Potabilizadoras | F6: Anual | G6: Indicador de Recursos Humanos | H6: Medios electrónicos, correo electrónico, WhatsApp, ZOOM, impresos en reuniones mensuales
A7: Técnica | B7: Alcantarillado y Saneamiento | C7: Indicadores de Calidad | D7: Alcantarillado y Saneamiento | E7: SGC Y PERSONAL | F7: Mensual | G7: OOMRSC-03 Y OOMRSC-05 | H7: Medios electrónico y Formato Impreso
A8: Técnica | B8: Alcantarillado y Saneamiento | C8: Resultados de la revisión por la dirección. | D8: Gerente de Alcantarillado y Saneamiento. | E8: Personal del área. | F8: Mensual | G8: OOMRSC-04 | H8: Correo Electrónico
A9: Técnica | B9: Alcantarillado y Saneamiento | C9: Transparencia | D9: Alcantarillado y Saneamiento | E9: Transparencia y responsable de área de transparencia | F9: trimestral | G9: Ley general de transparencia y acceso a la información pública. | H9: Correo Electrónico
A10: Técnica | B10: Alcantarillado y Saneamiento | C10: PEMS | D10: Alcantarillado y Saneamiento | E10: Transparencia y responsable de área de transparencia | F10: TRIMESTRAL | G10: PEMS | H10: Correo Electrónico
A11: Técnica | B11: Alcantarillado y Saneamiento | C11: CONAGUA | D11: Alcantarillado y Saneamiento | E11: DECLARAGUA | F11: TRIMESTRAL | G11: OOMXGS-03 OOMXGS-04 | H11: SISTEMA DECLARAGUA Y SUBDIRECCION
A12: Técnica | B12: Alcantarillado y Saneamiento | C12: OP 12 | D12: Alcantarillado y Saneamiento | E12: CONTABILIDAD | F12: trimestral | G12: OP 12 | H12: Correo Electrónico
... A200: Programas Sociales | B200: Trabajo Social | C200: Se da de alta a los usuarios con apoyos de Insten y Discapacidad | D200: Auxiliar de Trabajo Social | E200: A los Auxiliares de Atención a usuarios, cajeros, auxiliares adtvos y a quienes ocupan el apoyo | F200: diario | G200: OOMRSS-11 | H200: la persona que realice el trámite lo entrega al departamento para su ingreso a Sistema Comercial

Sheet Partes interesadas
A1: ID | B1: Parte Interesada: | C1: Área | D1: Requisito: | E1: Plan de acción | F1: Periodicidad | G1: Norma o Ley que aplica:
A2: Producto | B2: USUARIO DEL AGUA | C2: Plantas Potabilizadoras | D2: TURBIEDAD | E2: OOMPPP-05 Control de Turbiedad plantas 1 y 2 | F2: Lo mencionado en procedimiento | G2: OOMEOR-03 NOM-127-SSA1-2021
A3: Producto | B3: USUARIO DEL AGUA | C3: Plantas Potabilizadoras | D3: TURBIEDAD | E3: OOMPPP-06 Control de Turbiedad plantas 3 y 4 | F3: Lo mencionado en procedimiento | G3: OOMEOR-03 NOM-127-SSA1-2021
A4: Producto | B4: USUARIO DEL AGUA | C4: Plantas Potabilizadoras | D4: TURBIEDAD | E4: OOMPPP-07 Control de Turbiedad planta V.B. | F4: Lo mencionado en procedimiento | G4: OOMEOR-03 NOM-127-SSA1-2021
A5: Producto | B5: USUARIO DEL AGUA | C5: Control de Calidad | D5: TURBIEDAD | E5: OOMPCC-01 Determinación de Turbiedad NOM-201-SSA1-2015 | F5: Lo mencionado en procedimiento | G5: OOMEOR-03 NOM-127-SSA1-2021
A6: Producto | B6: USUARIO DEL AGUA | C6: Suburbano Técnico | D6: TURBIEDAD | E6: OOMPTS-09 Control de Turbiedad en Sistemas Suburbanos | F6: Lo mencionado en procedimiento | G6: OOMEOR-03 NOM-127-SSA1-2021
A7: Producto | B7: USUARIO DEL AGUA | C7: Control de Calidad | D7: COLOR | E7: OOMPCC-04 Determinación de Color | F7: Lo mencionado en procedimiento | G7: OOMEOR-03 NOM-127-SSA1-2021
A8: Producto | B8: USUARIO DEL AGUA | C8: Suburbano Técnico | D8: COLOR | E8: OOMPTS-14 Control de Manganeso y Fierro en Sistemas Suburbanos | F8: Lo mencionado en procedimiento | G8: OOMEOR-03 NOM-127-SSA1-2021
A9: Producto | B9: USUARIO DEL AGUA | C9: Control de Calidad | D9: OLOR Y SABOR | E9: OOMPCC-09 Determinación de Olor y Sabor | F9: Lo mencionado en procedimiento | G9: NOM-127-SSA1-1994 (NOTA: Sirve como guía para cumplir con los parámetros de olor y sabor)
A10: Producto | B10: USUARIO DEL AGUA | C10: Plantas Potabilizadoras | D10: OLOR Y SABOR | E10: OOMPPP-26 Paro de Plantas por Olor fuera de Norma | F10: Lo mencionado en procedimiento | G10: NOM-127-SSA1-1994 (NOTA: Sirve como guía para cumplir con los parámetros de olor y sabor)
A11: Producto | B11: USUARIO DEL AGUA | C11: Plantas Potabilizadoras | D11: OLOR Y SABOR | E11: OOMPPP-28 Determinación de Olor y Sabor | F11: Lo mencionado en procedimiento | G11: NOM-127-SSA1-1994 (NOTA: Sirve como guía para cumplir con los parámetros de olor y sabor)
A12: Producto | B12: USUARIO DEL AGUA | C12: Suburbano Técnico | D12: OLOR Y SABOR | E12: OOMPTS-17 Determinación de Olor y Sabor en Sistemas Suburbanos | F12: Lo mencionado en procedimiento | G12: NOM-127-SSA1-1994 (NOTA: Sirve como guía para cumplir con los parámetros de olor y sabor)
... A37: Servicio | B37: USUARIO DEL AGUA | C37: ALCANTARILLADO Y SANEAMIENTO | D37: CONTROL DE DESCARGAS DE AGUAS RESIDUALES | E37: OOMPGS-01 Visitas de Inspección | F37: Lo mencionado en procedimiento | G37: OOMEOR-33 NOM - 002- SEMARNAT-1996; OOMEOR-21 Ley de Aguas del Estado de Sonora; OOMEOR-17 Ley de ingresos y presupuestos de egresos del ayuntamiento del municipio de Cajeme Sonora para el ejercicio fiscal vigente.
A38: Servicio | B38: USUARIO DEL AGUA | C38: ALCANTARILLADO Y SANEAMIENTO | D38: CONTROL DE DESCARGAS DE AGUAS RESIDUALES | E38: OOMPGS-02 Dictamen Técnico | F38: Lo mencionado en procedimiento
A39: Servicio | B39: USUARIO DEL AGUA | C39: ALCANTARILLADO Y SANEAMIENTO | D39: ATENCIÓN A USUARIOS | E39: OOMPGS-06 Atención a Reportes de Alcantarillado Sanitario | F39: Lo mencionado en procedimiento | G39: OOMEOR-22 Ley de Obras Públicas y Servicios relacionados con las mismas para el Estado de Sonora, OOMEOR-26 Reglamento de la Ley de Obras Públicas y Servicios Relacionados con las Mismas para el Estado de Sonora; OOMEOR-21 Ley de Aguas del Estado de Sonora
A40: Servicio | B40: USUARIO DEL AGUA | C40: Suburbano Técnico | D40: ATENCIÓN A USUARIOS DEL SISTEMA DE ALCANTARILLADO | E40: OOMPTS-07 Atención a Reportes de Drenaje Tapados Suburbano | F40: Lo mencionado en procedimiento | G40: OOMEOR-22 Ley de Obras Públicas y Servicios relacionados con las mismas para el Estado de Sonora, OOMEOR-26 Reglamento de la Ley de Obras Públicas y Servicios Relacionados con las Mismas para el Estado de Sonora; OOMEOR-21 Ley de Aguas del Estado de Sonor
A41: Servicio | B41: USUARIO DEL AGUA | C41: Jurídico | D41: INCUMPLIMIENTO A LA LEGISLACIÓN | E41: OOMPJU-05 Sanción | F41: Lo mencionado en procedimiento | G41: OOMEOR-21 Ley de Agua del Estado de Sonora, OOMEOR-33 Nom-002-Semarnat-1996
A42: Servicio | B42: USUARIO DEL AGUA | C42: Jurídico | D42: QUEJAS PROFECO | E42: OOMPJU-11 Contestación de quejas profeco | F42: Lo mencionado en procedimiento | G42: OOMEOR-122 Ley Federal de Protección al Consumidor
A43: Servicio | B43: USUARIO DEL AGUA | C43: TRÁMITES TÉCNICOS | D43: ALTA DE FRACCIONAMIENTOS | E43: OOMPTT-01 Alta de Fraccionamiento | F43: Lo mencionado en procedimiento | G43: OOMEOR-85 Ley de ordenamiento territorial y desarrollo urbano del Estado de Sonora
A44: Servicio | B44: USUARIO DEL AGUA | C44: CONTRATOS Y SERVICIOS | D44: ATENCIÓN A USUARIOS MODULO | F44: Lo mencionado en procedimiento | G44: OOMEOR-21 Ley de Aguas del Estado Sonora, OOMEOR-17 Ley de ingresos y presupuestos de egresos del ayuntamiento del municipio de Cajeme Sonora para el ejercicio fiscal vigente.
A45: Servicio | B45: USUARIO DEL AGUA | C45: CONTRATOS Y SERVICIOS | D45: CONTRATACIÓN DE TOMA DE AGUA Y DESCARGA | E45: OOMPGC-01 Contratación de Instalación de Cuadro, Toma de Agua, Registro Descarga Sanitaria | F45: Lo mencionado en procedimiento | G45: OOMEOR-21 Ley de Aguas del Estado Sonora, OOMEOR-17 Ley de ingresos y presupuestos de egresos del ayuntamiento del municipio de Cajeme Sonora para el ejercicio fiscal vigente.
A46: Servicio | B46: USUARIO DEL AGUA | C46: CONTRATOS Y SERVICIOS | D46: CONTRATACIÓN DE TOMA DE AGUA Y DESCARGA | F46: Lo mencionado en procedimiento | G46: OOMEOR-21 Ley de Aguas del Estado Sonora, OOMEOR-17 Ley de ingresos y presupuestos de egresos del ayuntamiento del municipio de Cajeme Sonora para el ejercicio fiscal vigente.
A47: Servicio | B47: USUARIO DEL AGUA | C47: CONTRATOS Y SERVICIOS | D47: FACTURACIÓN | E47: OOMPGC- 03 Cambio de nombre en facuración | F47: Lo mencionado en procedimiento | G47: OOMEOR-21 Ley de Aguas del Estado Sonora, OOMEOR-17 Ley de ingresos y presupuestos de egresos del ayuntamiento del municipio de Cajeme Sonora para el ejercicio fiscal vigente.
A48: Servicio | B48: USUARIO DEL AGUA | C48: CONTRATOS Y SERVICIOS | D48: CONVENIOS | E48: OOMPGC- 04 Convenio | F48: Lo mencionado en procedimiento | G48: OOMEOR-21 Ley de Aguas del Estado Sonora, OOMEOR-17 Ley de ingresos y presupuestos de egresos del ayuntamiento del municipio de Cajeme Sonora para el ejercicio fiscal vigente.
A49: Servicio | B49: USUARIO DEL AGUA | C49: CONTRATOS Y SERVICIOS | D49: CERTIFICADOS | E49: OOMPGC-05 Certificado de no adeudo | F49: Lo mencionado en procedimiento | G49: OOMEOR-21 Ley de Aguas del Estado Sonora, OOMEOR-17 Ley de ingresos y presupuestos de egresos del ayuntamiento del municipio de Cajeme Sonora para el ejercicio fiscal vigente.
A50: Servicio | B50: USUARIO DEL AGUA | C50: CONTRATOS Y SERVICIOS | D50: ALTA DE SERVICIOS | E50: OOMPGC-06 Alta de Servicio | F50: Lo mencionado en procedimiento | G50: OOMEOR-21 Ley de Aguas del Estado Sonora, OOMEOR-17 Ley de ingresos y presupuestos de egresos del ayuntamiento del municipio de Cajeme Sonora para el ejercicio fiscal vigente.
A51: Servicio | B51: USUARIO DEL AGUA | C51: CONTRATOS Y SERVICIOS | D51: CONTRATACIÓN DE MEDIDORES | E51: OOMPGC-08 Contratación de Medidores | F51: Lo mencionado en procedimiento | G51: OOMEOR-21 Ley de Aguas del Estado Sonora, OOMEOR-17 Ley de ingresos y presupuestos de egresos del ayuntamiento del municipio de Cajeme Sonora para el ejercicio fiscal vigente.
A52: Servicio | B52: USUARIO DEL AGUA | C52: CONTRATOS Y SERVICIOS | D52: CAMBIOS DE TOMA | E52: OOMPGC-11 Cambio de Toma Activa a Toma Muerta | F52: Lo mencionado en procedimiento | G52: OOMEOR-21 Ley de Aguas del Estado Sonora, OOMEOR-17 Ley de ingresos y presupuestos de egresos del ayuntamiento del municipio de Cajeme Sonora para el ejercicio fiscal vigente.
A53: Servicio | B53: USUARIO DEL AGUA | C53: CONTRATOS Y SERVICIOS | D53: CAMBIOS DE TOMA | E53: OOMPGC-12 Cambio de Toma Muerta a Toma Activa | F53: Lo mencionado en procedimiento | G53: OOMEOR-21 Ley de Aguas del Estado Sonora, OOMEOR-17 Ley de ingresos y presupuestos de egresos del ayuntamiento del municipio de Cajeme Sonora para el ejercicio fiscal vigente.
A54: Servicio | B54: USUARIO DEL AGUA | C54: CONTRATOS Y SERVICIOS | D54: ESTADOS DE CUENTA | E54: OOMIGC-02 Expedir Estados de Cuenta | F54: Lo mencionado en procedimiento | G54: OOMEOR-21 Ley de Aguas del Estado Sonora, OOMEOR-17 Ley de ingresos y presupuestos de egresos del ayuntamiento del municipio de Cajeme Sonora para el ejercicio fiscal vigente.
A55: Servicio | B55: USUARIO DEL AGUA | C55: CONTRATOS Y SERVICIOS | D55: DERECHOS DE CONEXIÓN | E55: OOMIGC-03 Cargos de Derecho de Conexión para Constructoras | F55: Lo mencionado en procedimiento | G55: OOMEOR-21 Ley de Aguas del Estado Sonora, OOMEOR-17 Ley de ingresos y presupuestos de egresos del ayuntamiento del municipio de Cajeme Sonora para el ejercicio fiscal vigente.
A56: Servicio | B56: USUARIO DEL AGUA | C56: CONTRATOS Y SERVICIOS | D56: COBROS | E56: OOMPGC-16 Cobros en Caja | F56: Lo mencionado en procedimiento | G56: OOMEOR-21 Ley de Aguas del Estado Sonora, OOMEOR-17 Ley de ingresos y presupuestos de egresos del ayuntamiento del municipio de Cajeme Sonora para el ejercicio fiscal vigente.
A57: Servicio | B57: USUARIO DEL AGUA | C57: Atención Ciudadana | D57: DOMICILIACIÓN | E57: OOMPAC-02 Domiciliación de Pagos | F57: Lo mencionado en procedimiento | G57: OOMEOR-21 Ley de Aguas del Estado Sonora, OOMEOR-17 Ley de ingresos y presupuestos de egresos del ayuntamiento del municipio de Cajeme Sonora para el ejercicio fiscal vigente.
A58: Servicio | B58: USUARIO DEL AGUA | C58: VERIFICACIÓN Y LECTURA | D58: MICROMEDICIÓN | E58: OOMPVL-02 Procedimiento de Micromedición | F58: Lo mencionado en procedimiento | G58: OOMEOR-21 Ley de Aguas del Estado Sonora, OOMEOR-17 Ley de ingresos y presupuestos de egresos del ayuntamiento del municipio de Cajeme Sonora para el ejercicio fiscal vigente.
... A65: Servicio | B65: USUARIO DEL AGUA | C65: CONTROL Y SERVICIOS | D65: CAMBIOS DE TOMA | E65: OOMICS-02 Cambio de Toma Activa a Toma Muerta | F65: Lo mencionado en procedimiento | G65: OOMEOR-21 Ley de Aguas del Estado Sonora, OOMEOR-17 Ley de ingresos y presupuestos de egresos del ayuntamiento del municipio de Cajeme Sonora para el ejercicio fiscal vigente.
A66: Servicio | B66: USUARIO DEL AGUA | C66: CONTROL Y SERVICIOS | D66: CAMBIOS DE TOMA | F66: Lo mencionado en procedimiento | G66: OOMEOR-21 Ley de Aguas del Estado Sonora, OOMEOR-17 Ley de ingresos y presupuestos de egresos del ayuntamiento del municipio de Cajeme Sonora para el ejercicio fiscal vigente.
A67: Servicio | B67: USUARIO DEL AGUA | C67: Línea OOMAPASC | D67: ATENCIÓN A USUARIOS LÍNEA OOMAPASC | E67: OOMPAT-08 Generacion de reportes | F67: Lo mencionado en procedimiento | G67: OOMEOR-21 Ley de Aguas del Estado Sonora, OOMEOR-17 Ley de ingresos y presupuestos de egresos del ayuntamiento del municipio de Cajeme Sonora para el ejercicio fiscal vigente.
A68: Servicio | B68: USUARIO DEL AGUA | C68: Línea OOMAPASC | D68: ATENCIÓN A USUARIOS LÍNEA OOMAPASC | E68: OOMPAT-13 Atención de auxiliar telefonico a usuarios | F68: Lo mencionado en procedimiento | G68: OOMEOR-21 Ley de Aguas del Estado Sonora, OOMEOR-17 Ley de ingresos y presupuestos de egresos del ayuntamiento del municipio de Cajeme Sonora para el ejercicio fiscal vigente.
A69: Servicio | B69: USUARIO DEL AGUA | C69: TRABAJO SOCIAL | D69: Estudios Socioeconomicos | E69: OOMPSS-01 Apoyos o Subsidios en adeudos de consumo o contratación de servicios. | F69: Lo mencionado en procedimiento | G69: OOMEOR-17 Ley de Ingresos y presupuestos de egresos del Ayuntamiento del Municipio de Cajeme Sonora OOMEOR-21 Ley de Aguas del Estado Sonora
A70: Servicio | B70: USUARIO DEL AGUA | C70: MANTENIMIENTO DE REDES | D70: REHABILITACIÓN DE INFRAESTRUCTURA | E70: OOMPMR-01 Procedimiento General de Supervisión de Redes de Agua Potable y Obras de Reparación Asignadas a Contratistas. | F70: Lo mencionado en procedimiento | G70: OOMEOR-22 Ley de Obras Públicas y Servicios relacionados con las mismas para el Estado de Sonora, OOMEOR-26 Reglamento de la Ley de Obras Públicas y Servicios Relacionados con las Mismas para el Estado de Sonora; OOMEOR-21 Ley de Aguas del Estado de Sonora. OOMEOR-14 Ley de Adquisiciones Arrendamientos y Servicios del Sector Público, OOMEOR-15 Reglamento de la Ley de Adquisiciones Arrendamientos y Servicios del Sector Público
A71: Servicio | B71: USUARIO DEL AGUA | C71: SUBURBANOS TÉCNICO | D71: ATENCIÓN A REPORTES A MANTENIMIENTO DE REDES | E71: OOMPTS-06 Atención a reportes a mantenimiento de redes. | F71: Lo mencionado en procedimiento | G71: OOMEOR-22 Ley de Obras Públicas y Servicios relacionados con las mismas para el Estado de Sonora, OOMEOR-26 Reglamento de la Ley de Obras Públicas y Servicios Relacionados con las Mismas para el Estado de Sonora; OOMEOR-21 Ley de Aguas del Estado de Sonora
A72: Servicio | B72: USUARIO DEL AGUA | C72: Suburbano Comercial | D72: CONTRATACIÓN DE TOMA DE AGUA Y DESCARGA | E72: OOMPAS-01 Contratación de Instalación de Toma de Agua o Descarga | F72: Lo mencionado en procedimiento | G72: OOMEOR-21 Ley de Aguas del Estado Sonora, OOMEOR-17 Ley de ingresos y presupuestos de egresos del ayuntamiento del municipio de Cajeme Sonora para el ejercicio fiscal vigente.
A73: Servicio | B73: USUARIO DEL AGUA | C73: Suburbano Comercial | D73: FACTURACIÓN | E73: OOMPAS- 03 Cambio de nombre en la facuturación | F73: Lo mencionado en procedimiento | G73: OOMEOR-21 Ley de Aguas del Estado Sonora, OOMEOR-17 Ley de ingresos y presupuestos de egresos del ayuntamiento del municipio de Cajeme Sonora para el ejercicio fiscal vigente.
A74: Servicio | B74: USUARIO DEL AGUA | C74: Suburbano Comercial | D74: CONVENIOS | E74: OOMPAS- 14 Procedimiento de Convenio | F74: Lo mencionado en procedimiento | G74: No aplica ninguna ley o norma
A75: Servicio | B75: USUARIO DEL AGUA | C75: Suburbano Comercial | D75: CERTIFICADOS | E75: OOMPAS-04 Procedimiento de Certificado de no adeudo | F75: Lo mencionado en procedimiento | G75: OOMEOR-21 Ley de Aguas del Estado Sonora, OOMEOR-17 Ley de ingresos y presupuestos de egresos del ayuntamiento del municipio de Cajeme Sonora para el ejercicio fiscal vigente.
A76: Servicio | B76: USUARIO DEL AGUA | C76: Suburbano Comercial | D76: INSTALACION DE MEDIDORES | E76: OOMPAS-07 Contratación cuadro y/o medidor | F76: Lo mencionado en procedimiento | G76: OOMEOR-21 Ley de Aguas del Estado Sonora, OOMEOR-17 Ley de ingresos y presupuestos de egresos del ayuntamiento del municipio de Cajeme Sonora para el ejercicio fiscal vigente.
A77: Servicio | B77: USUARIO DEL AGUA | C77: Suburbano Comercial | D77: CAMBIOS DE TOMA | E77: OOMPAS-08 Cambio de Toma Activa a Toma Muerta | F77: Lo mencionado en procedimiento | G77: OOMEOR-21 Ley de Aguas del Estado Sonora, OOMEOR-17 Ley de ingresos y presupuestos de egresos del ayuntamiento del municipio de Cajeme Sonora para el ejercicio fiscal vigente.
A78: Servicio | B78: USUARIO DEL AGUA | C78: Suburbano Comercial | D78: CAMBIOS DE TOMA | E78: OOMPAS-09 Cambio de Toma Muerta a Toma Activa | F78: Lo mencionado en procedimiento | G78: OOMEOR-21 Ley de Aguas del Estado Sonora, OOMEOR-17 Ley de ingresos y presupuestos de egresos del ayuntamiento del municipio de Cajeme Sonora para el ejercicio fiscal vigente.
... A81: Servicio | B81: USUARIO DEL AGUA | C81: PROYECTOS E INFRAESTRUCTURA | D81: APROBACIÓN DE PROYECTO DE AGUA POTABLE Y/O ALCANTARILLADO SANITARIO | E81: OOMPPI-04 Revisión y aprobación de proyecto de Agua Potable y/o Alcantarillado Sanitario | F81: Lo mencionado en procedimiento | G81: OOMEOR-34 Manual de Agua Potable y Alcantarillado CNA
A82: Servicio | B82: USUARIO DEL AGUA | C82: PROYECTOS E INFRAESTRUCTURA | D82: APROBACIÓN DE PROYECTO DE AGUA POTABLE Y/O ALCANTARILLADO SANITARIO | F82: Lo mencionado en procedimiento | G82: Manual técnico para diseño de proyectos de agua potable y alcantarillado del OOMAPAS de Cajeme
A83: Servicio | B83: USUARIO DEL AGUA | C83: PROYECTOS E INFRAESTRUCTURA | D83: APROBACIÓN DE PROYECTO DE AGUA POTABLE Y/O ALCANTARILLADO SANITARIO | F83: Lo mencionado en procedimiento | G83: OOMEOR-17 Ley de Ingresos y presupuestos de egresos del Ayuntamiento del Municipio de Cajeme Sonora
A84: Servicio | B84: USUARIO DEL AGUA | C84: PROYECTOS E INFRAESTRUCTURA | D84: PREFACTIBILIDAD | E84: OOMPPI-01 Otorgamiento de puntos de conexión provisionales o definitivos de los servicios de agua potable y/o alcantarillado sanitario para nuevos fraccionamientos. | F84: Lo mencionado en procedimiento | G84: OOMEOR-17 Ley de Ingresos y presupuestos de egresos del Ayuntamiento del Municipio de Cajeme Sonora
A85: Servicio | B85: USUARIO DEL AGUA | C85: Sectorización hidrométrica e innovación | D85: DETECCIÓN CON EQUIPO GEORRADAR. | E85: OOMPSH-05 Detección con equipo georradar en búsqueda o localización de infraestructura existente en el subsuelo. | F85: Lo mencionado en procedimiento | G85: No aplica ninguna ley o norma
A86: Servicio | B86: USUARIO DEL AGUA | C86: CONTROL Y SERVICIOS | D86: SUSPENSIÓN DE SERVICIO DE AGUA POTABLE | E86: OOMPCS-01 Restricción de Servicio de Agua Potable | F86: Lo mencionado en procedimiento | G86: OOMEOR-21 Ley de Aguas del Estado Sonora
A87: Servicio | B87: USUARIO DEL AGUA | C87: CONTROL Y SERVICIOS | D87: COBRANZA ESPECIAL | E87: OOMPCS-05 Cobranza Especial | F87: Lo mencionado en procedimiento | G87: No aplica ninguna ley o norma
A88: Servicio | B88: USUARIO DEL AGUA | C88: CONTROL Y SERVICIOS | D88: ATENCION A QUEJAS DE CONTROL Y SERVICIOS | E88: OOMPCS-09 Quejas, infracciones y sanciones | F88: Lo mencionado en procedimiento | G88: OOMEOR-21 Ley de Aguas del Estado Sonora
A89: Servicio | B89: USUARIO DEL AGUA | C89: Órgano de Control Interno | D89: QUEJAS Y DENUNCIAS | E89: OOMPOC-01 Procedimiento de Quejas y Denuncias | F89: Lo mencionado en procedimiento | G89: OOMEOR-21 Ley de Aguas del Estado Sonora
A90: Servicio | B90: SOLICITANTE | C90: Jurídico | D90: SOLICITUD DE INFORMACIÓN | E90: OOMPJU-03 SOLICITUD DE INFORMACION | F90: Lo mencionado en procedimiento | G90: OOMEOR-133 Ley de Acceso a la Informacion y Proteccion de Datos Personales Publica del Estado de Sonora.
A91: Servicio | B91: SOLICITANTE | C91: Jurídico | D91: SOLICITUD DE INFORMACIÓN | F91: Lo mencionado en procedimiento | G91: OOMEOR-17 Ley de Ingresos y presupuestos de egresos del Ayuntamiento del Municipio de Cajeme Sonora
A92: Servicio | B92: SOLICITANTE | C92: Supervisión y Control de Obras | D92: SUPERVISION DE OBRAS | E92: OOMPSO-01 Procedimiento de Supervisión de obras | F92: Lo mencionado en procedimiento | G92: OOMEOR-19 Ley de obras públicas y servicios relacionados con las mismas OOMEOR-20 Reglamento ley de obras públicas y servicios relacionados con las mismas OOMEOR-22 Ley de obras públicas y servicios relacionados con las mismas para el estado de sonora OOMEOR-26 Reglamento de la ley de obras públicas y servicios relacionados con las mismas para el estado de sonora OOMEOR-21 Ley de aguas del estado de sonora OOMEOR-14 Ley de adquisiciones arrendamientos y servicios del sector público OOMEOR-15 Reglamento de la ley de adquisiciones arrendamientos y servicios del sector público , NORMA OFICIAL MEXICANA NOM-001-CONAGUA-2011, Sistemas de agua potable, tomas domiciliarias y alcantarillado sanitario-hermeticidad-especificaciones y metodos de prueba. OOMEOR-18 Salud ambiental. Agua para uso y consumo humano, requisitos sanitarios que se deben cumplir en los sistemas de abastecimiento públicos y privados durante el manejo del agua. Procedimientos sanitarios para el muestreo. NOM-230-SSA1-2002.
A93: Servicio | B93: SOLICITANTE | C93: Supervisión y Control de Obras | D93: ESTIMACIONES | E93: OOMPSO-02 Revisión de estimaciones | F93: Lo mencionado en procedimiento | G93: OOMEOR-19 Ley de obras públicas y servicios relacionados con las mismas OOMEOR-20 Reglamento ley de obras públicas y servicios relacionados con las mismas OOMEOR-22 Ley de obras públicas y servicios relacionados con las mismas para el estado de sonora OOMEOR-26 Reglamento de la ley de obras públicas y servicios relacionados con las mismas para el estado de sonora OOMEOR-14 Ley de adquisiciones arrendamientos y servicios del sector público OOMEOR-15 Reglamento de la ley de adquisiciones arrendamientos y servicios del sector público OOMEOR-17 Ley de Ingresos y Presupuesto de Ingresos del H. Ayuntamiento de Cajeme 2024. (ART. 128)
A94: Servicio | B94: SOLICITANTE | C94: Supervisión y Control de Obras | D94: SUPERVISION DE FRACCIONAMIENTOS | E94: OOMPSO-03 Procedimiento de Supervisión de Obra en Fraccionamientos | F94: Lo mencionado en procedimiento | G94: NORMA OFICIAL MEXICANA NOM-001-CONAGUA-2011, Sistemas de agua potable, tomas domiciliarias y alcantarillado sanitario-hermeticidad-especificaciones y metodos de prueba. OOMEOR-21 Ley de aguas del estado de sonora. OOMEOR-18 Salud ambiental. Agua para uso y consumo humano, requisitos sanitarios que se deben cumplir en los sistemas de abastecimiento públicos y privados durante el manejo del agua. Procedimientos sanitarios para el muestreo. NOM-230-SSA1-2002.
A95: Servicio | B95: SOLICITANTE | C95: Supervisión y Control de Obras | D95: SUPERVISIÓN DE OBRAS DE ASIGNACIÓN EXTERNA | E95: OOMPSO-04 Procedimiento de Supervisión de Obras de Asignación Externa | F95: Lo mencionado en procedimiento | G95: NORMA OFICIAL MEXICANA NOM-001-CONAGUA-2011, Sistemas de agua potable, tomas domiciliarias y alcantarillado sanitario-hermeticidad-especificaciones y metodos de prueba. OOMEOR-21 Ley de aguas del estado de sonora. OOMEOR-18 Salud ambiental. Agua para uso y consumo humano, requisitos sanitarios que se deben cumplir en los sistemas de abastecimiento públicos y privados durante el manejo del agua. Procedimientos sanitarios para el muestreo. NOM-230-SSA1-2002.
A96: Gobierno | B96: CONAGUA | C96: Director Técnico/Director Administrativo | D96: Pago de derechos de agua | E96: Hacer el calculo de consumo de agua cruda para el pago de derechos | F96: Trimestral | G96: OOMEOR-21 Ley de agua del estado de sonora.
A97: Gobierno | B97: CONAGUA | C97: Director Técnico/Director Administrativo | D97: Pago de derecchos de agua residual | E97: Hacer declaracion en base al volumen y calidad para el pago | F97: Trimestral | G97: OOMEOR-21 Ley de agua del estado de sonora.
A98: Gobierno | B98: CEA | C98: Director Técnico/Director Administrativo | D98: Pago de derechos de agua | E98: Hacer el calculo de consumo de agua cruda para el pago de derechos | F98: Mensual | G98: OOMEOR-21 Ley de agua del estado de sonora.
A99: Gobierno | B99: Distrito de Riego | C99: Director Técnico/Director Administrativo | D99: Pago de derechos de agua | E99: Hacer el calculo de consumo de agua cruda para el pago de derechos | F99: Mensual | G99: OOMEOR-21 Ley de agua del estado de sonora.
A100: Gobierno | B100: Ayuntamiento de Cajeme | C100: Director Administrativo | D100: Cuenta públlica | E100: Presentación trimestral de cuenta publica | F100: Trimestral | G100: Ley de fiscalización superior para el estado de sonora.
A101: Gobierno | B101: SAT | C101: Contabilidad | D101: Pago de Impuestos | E101: Elaboración de declaración y pago correspondiente de impuestos | F101: Mensual | G101: OOMEOR-36 Ley del impuesto sobre la renta.
A102: Gobierno | B102: CFE | C102: Contabilidad | D102: Pago de energía electrica | E102: Realizar pago del mes correspondiente en tiempo y forma | F102: Mensual | G102: Ley de servicio público de energía eléctrica.
A103: Gobierno | B103: Secretaría del Trabajo y Previsión Social | C103: Director Jurídico/Coordinador de Nóminas | D103: Cumplir con requerimientos de la Secretaría | E103: Cumplimiento de la normativa | F103: Mensual | G103: OOMEOR-24 Ley federal del trabajo
... A132: Cliente/Sociedad | B132: Usuarios domesticos-comerciales | C132: Suburbano Comercial | D132: Cobranza, contratación de toma, atención a usuario en modulo, convenios, certificados, cambio de toma, derechos de conexión. | E132: Cumplimiento de Normas Oficiales aplicables y procedimientos establecidos. | F132: Mensual | G132: OOMEOR-21 Ley de agua del estado de sonora. OOMEOR-17 Ley de ingresos y presupuesto de ingresos del ayuntamiento de cajeme.

Sheet KPI-2025
A1: Proceso: | B1: Dirección: | C1: Área: | D1: # | E1: Indicador o Índice: | F1: Periodicidad | G1: Unidad de Medida
A2: Responsabilidad de la Dirección | B2: General | C2: Sistema de Gestión de Calidad | D2: 0 | E2: Lograr el grado de eficacia del SGC determinado por auditorías e indicadores. | F2: Mensual | G2: Porcentaje
A3: Responsabilidad de la Dirección | B3: General | C3: Dirección General | D3: 1 | E3: Cumplir con las metas establecidas por las direcciones adscritas a la Dirección General | F3: Trimestral | G3: Porcentaje | L3: {=_xlfn.UNIQUE(KPI[Área:])} -> Sistema de Gestión de Calidad | M3: =COUNTIF(KPI[Área:],L3) -> 5
A4: Responsabilidad de la Dirección | B4: General | C4: Dirección General | D4: 2 | E4: Mantener una relación de comunicación con el Consejo Consultivo. | F4: Trimestral | G4: Actas | L4: Dirección General | M4: =COUNTIF(KPI[Área:],L4) -> 2
A5: Gestión de Recursos | B5: Administrativa | C5: Recursos Humanos | D5: 3 | E5: Remuneración del personal. | F5: Trimestral | G5: Cantidad | L5: Recursos Humanos | M5: =COUNTIF(KPI[Área:],L5) -> 4
A6: Gestión de Recursos | B6: Administrativa | C6: Recursos Humanos | D6: 4 | E6: Remuneración a jubilados y pensionados | F6: Trimestral | G6: Cantidad | L6: Recursos Materiales | M6: =COUNTIF(KPI[Área:],L6) -> 2
A7: Gestión de Recursos | B7: Administrativa | C7: Recursos Humanos | D7: 5 | E7: Cumplir con el programa trimestral de capacitación. | F7: Trimestral | G7: Porcentaje | L7: Contabilidad | M7: =COUNTIF(KPI[Área:],L7) -> 1
A8: Gestión de Recursos | B8: Administrativa | C8: Recursos Humanos | D8: 6 | E8: Evaluación del ambiente de trabajo. | F8: Mensual | G8: Porcentaje | L8: Seguridad Industrial | M8: =COUNTIF(KPI[Área:],L8) -> 3
A9: Gestión de Recursos | B9: Administrativa | C9: Recursos Materiales | D9: 7 | E9: Evaluar el desempeño de proveedores de productos químicos críticos | F9: Mensual | G9: Porcentaje | L9: Licitaciones | M9: =COUNTIF(KPI[Área:],L9) -> 2
A10: Gestión de Recursos | B10: Administrativa | C10: Recursos Materiales | D10: 8 | E10: Atender las solicitudes de compra en el tiempo establecido. | F10: Mensual | G10: Porcentaje | L10: Trámites Técnicos | M10: =COUNTIF(KPI[Área:],L10) -> 3
A11: Gestión de Recursos | B11: Administrativa | C11: Contabilidad | D11: 9 | E11: Cumplir con el calendario contable y presupuestal. | F11: Mensual | G11: Documentos | L11: Informática | M11: =COUNTIF(KPI[Área:],L11) -> 3
A12: Gestión de Recursos | B12: Administrativa | C12: Seguridad Industrial | D12: 10 | E12: Accidentes de trabajo | F12: Mensual | G12: Cantidad | L12: Mantenimiento y Servicios Generales | M12: =COUNTIF(KPI[Área:],L12) -> 6
A13: Gestión de Recursos | B13: Administrativa | C13: Licitaciones | D13: 11 | E13: Cumplir con el proceso de licitación pública o simplificada | F13: Mensual | G13: Porcentaje | L13: Mantenimiento de Redes | M13: =COUNTIF(KPI[Área:],L13) -> 1
A14: Gestión de Recursos | B14: Administrativa | C14: Licitaciones | D14: 12 | E14: Cumplir con el proceso de adjudicación directa. | F14: Mensual | G14: Porcentaje | L14: Control de Calidad | M14: =COUNTIF(KPI[Área:],L14) -> 4
A15: Gestión de Recursos | B15: Técnica | C15: Trámites Técnicos | D15: 13 | E15: Índice de programas federales gestionados | F15: Semestral | G15: Programa | L15: Plantas Potabilizadoras | M15: =COUNTIF(KPI[Área:],L15) -> 3
... A36: Comercialización | B36: Comercial | C36: Verificación y Lectura | D36: 34 | E36: Porcentaje de error en toma de lectura. | F36: Mensual | G36: Porcentaje | L36: Comunicación e imagen institucional | M36: =COUNTIF(KPI[Área:],L36) -> 3
A37: Comercialización | B37: Comercial | C37: Verificación y Lectura | D37: 35 | E37: Cobertura de Micromedición en área urbana | F37: Mensual | G37: Porcentaje | M37: =COUNTIF(KPI[Área:],L37) -> 0
A38: Comercialización | B38: Comercial | C38: Suburbano Comercial | D38: 36 | E38: Cumplir con el presupuesto de ingresos en la gerencia Providencia. | F38: Mensual | G38: Porcentaje | M38: =COUNTIF(KPI[Área:],L38) -> 0
A39: Comercialización | B39: Comercial | C39: Suburbano Comercial | D39: 37 | E39: Cumplir con el presupuesto de ingresos en la gerencia Esperanza | F39: Mensual | G39: Porcentaje | M39: =COUNTIF(KPI[Área:],L39) -> 0
A40: Comercialización | B40: Comercial | C40: Suburbano Comercial | D40: 38 | E40: Cumplir con el presupuesto de ingresos en la gerencia Pueblo Yaqui. | F40: Mensual | G40: Porcentaje | M40: =COUNTIF(KPI[Área:],L40) -> 0
A41: Comercialización | B41: Comercial | C41: Suburbano Comercial | D41: 39 | E41: Cumplir con el presupuesto de ingresos en la gerencia Marte R. Gómez. | F41: Mensual | G41: Porcentaje
A42: Comercialización | B42: Comercial | C42: Dirección Comercial | D42: 40 | E42: Cumplir con el presupuesto programado de ingresos. | F42: Mensual | G42: Porcentaje
A43: Comercialización | B43: Comercial | C43: Dirección Comercial | D43: 41 | E43: Eficiencia comercial | F43: Mensual | G43: Porcentaje
A44: Comercialización | B44: Comercial | C44: Dirección Comercial | D44: 42 | E44: Eficiencia comercial de rezago | F44: Mensual | G44: Porcentaje
A45: Comercialización | B45: Programas Sociales | C45: Trabajo Social | D45: 43 | E45: Atender las órdenes de trabajo en un lapso de 7 días hábiles | F45: Mensual | G45: Porcentaje
A46: Producción | B46: Técnica | C46: Control de Calidad | D46: 44 | E46: Cumplimiento a NOM-127-SSA1-2021 aplicable a control de calidad. | F46: Mensual | G46: Muestreos
A47: Producción | B47: Técnica | C47: Control de Calidad | D47: 45 | E47: Índice de cumplimiento en muestreos y análisis de agua potable. | F47: Trimestral | G47: Informes
A48: Producción | B48: Técnica | C48: Plantas Potabilizadoras | D48: 46 | E48: Producción de agua en plantas potabilizadoras y pozos de área urbana | F48: Mensual | G48: M3
A49: Producción | B49: Técnica | C49: Plantas Potabilizadoras | D49: 47 | E49: Índice de cobertura de macromedición | F49: Mensual | G49: Porcentaje
A50: Producción | B50: Técnica | C50: Alcantarillado y Saneamiento | D50: 48 | E50: Índice de agua residual tratada. | F50: Mensual | G50: Porcentaje
A51: Producción | B51: Técnica | C51: Alcantarillado y Saneamiento | D51: 49 | E51: Programa de muestreo y análisis de aguas residuales | F51: Mensual | G51: Porcentaje
A52: Producción | B52: Técnica | C52: Suburbano Técnico | D52: 50 | E52: Cumplir con el volumen de agua potabilizada. | F52: Mensual | G52: M3
... A103: Comunicación | B103: Programas Sociales | C103: Trabajo Social | D103: 101 | E103: Cumplir con el programa anual de pláticas de cultura del agua. | F103: Mensual | G103: Porcentaje

Sheet Hoja4
A1: Alcantarillado y Saneamiento
A2: Atención Ciudadana
A3: Comunicación e Imagen Institucional
A4: Contabilidad
A5: Contratos y Servicios
A6: Control de Calidad
A7: Control y Servicios
A8: Informática
A9: Jurídico
A10: Licitaciones
A11: Línea OOMAPASC
A12: Mantenimiento de Redes
... A30: Verificación y Lectura

Sheet Interacción entre procesos
B2: OOMAPASC | D2: MATRIZ DE PROCESOS | L2: Fecha actualización: | O2: 46235
L3: Clave: | O3: OOMLSC-A21
L4: Revisión: | O4: 15

Sheet MATRIZ REQUISITOS ISO
B6: PROCESOS | C6: LISTA BUSQUEDA | D6: 4.1 | E6: 4.2 | F6: 4.3 | G6: 4.4 | H6: 5.1 | I6: 5.2 | J6: 5.3 | K6: 6.1 | L6: 6.2 | M6: 6.3 | N6: 7.1 | O6: 7.2 | P6: 7.3 | Q6: 7.4 | R6: 7.5 | S6: 8.1 | T6: 8.2 | U6: 8.3 | V6: 8.4 | W6: 8.5 | X6: 8.6 | Y6: 8.7 | Z6: 9.1 | AA6: 9.2 | AB6: 9.3 | AC6: 10.1 | AD6: 10.2 | AE6: 10.3 | AF6: TOTAL REQUISITOS | AG6: PROPÓSITO DE LOS PROCESOS
A7: 1 | B7: Comercialización | C7: =_xlfn.CONCAT(B7&"_L") -> Comercialización_L | E7: 4 | G7: 4 | K7: 4 | L7: 4 | N7: 4 | O7: 4 | P7: 4 | Q7: 4 | R7: 4 | S7: 4 | T7: 4 | W7: 4 | X7: 4 | Y7: 4 | Z7: 4 | AB7: 4 | AC7: 4 | AD7: 4 | AE7: 4 | AF7: =COUNT(D7:AE7) -> 19 | AG7: El OOMAPAS de Cajeme lleva a cabo actividades de comercialización con sus clientes, donde determina las actividades para el servicio que se ofrece y mide la eficiencia de sus resultados. En este proceso es donde se define las actividades para la recaudación y sus estrategias de cobranza tanto en zona urbana como suburbana.
A8: 2 | B8: Comunicación | C8: =_xlfn.CONCAT(B8&"_L") -> Comunicación_L | D8: 8 | E8: 8 | G8: 8 | K8: 8 | L8: 8 | N8: 8 | P8: 8 | Q8: 8 | R8: 8 | Z8: 8 | AA8: 8 | AB8: 8 | AC8: 8 | AD8: 8 | AE8: 8 | AF8: =COUNT(D8:AE8) -> 15 | AG8: En este proceso se lleva a cabo la comunicación con el cliente interno, externo y las partes interesadas, por medio de correos, tableros, intranet, en conjunto con la información de los reportes para dar servicio a los usuarios que envía el H. Ayuntamiento de Cajeme.
A9: 3 | B9: Gestión_de_Recursos | C9: =_xlfn.CONCAT(B9&"_L") -> Gestión_de_Recursos_L | G9: 2 | K9: 2 | L9: 2 | N9: 2 | O9: 2 | P9: 2 | Q9: 2 | R9: 2 | V9: 2 | Y9: 2 | Z9: 2 | AB9: 2 | AC9: 2 | AD9: 2 | AE9: 2 | AF9: =COUNT(D9:AE9) -> 15 | AG9: En este proceso se Gestiona tanto los recursos materiales, recursos financieros, recurso humano y recursos federales; necesarios para la producción de agua potable, saneamiento y alcantarillado y los servicios comerciales.
A10: 4 | B10: Mantenimiento_y_Calibración | C10: =_xlfn.CONCAT(B10&"_L") -> Mantenimiento_y_Calibración_L | G10: 3 | K10: 3 | L10: 3 | N10: 3 | O10: 3 | P10: 3 | Q10: 3 | R10: 3 | W10: 3 | Y10: 3 | Z10: 3 | AB10: 3 | AC10: 3 | AD10: 3 | AE10: 3 | AF10: =COUNT(D10:AE10) -> 15 | AG10: El OOMAPAS de Cajeme establece procesos para asegurarse de que el seguimiento y medición pueden realizarse de una manera coherente con los requisitos de seguimiento y medición. Cuando es necesario asegurarse de la validez de los resultados, el equipo de medición se calibra o verifica, o ambos, a intervalos especificados o antes de su utilización, comparado con patrones de medición trazables a patrones de mediciones nacionales o internacionales; cuando no existen tales patrones se registran la base utilizada para la calibración y verificación. En este proceso se llevan a cabo programas de mantenimientos preventivos para los equipos y la infraestructura del organismo.
A11: 5 | B11: Medición_Análisis_y_Mejora | C11: =_xlfn.CONCAT(B11&"_L") -> Medición_Análisis_y_Mejora_L | D11: 6 | E11: 6 | G11: 6 | K11: 6 | L11: 6 | O11: 6 | P11: 6 | Q11: 6 | R11: 6 | Y11: 6 | Z11: 6 | AA11: 6 | AB11: 6 | AC11: 6 | AD11: 6 | AE11: 6 | AF11: =COUNT(D11:AE11) -> 16 | AG11: El OOMAPAS de Cajeme Planifica e implementa los procesos de seguimiento, medición, análisis y mejora necesarios para demostrar la conformidad con los requisitos del producto, asegurarse de la conformidad del Sistema de Gestión de la Calidad por medio de la Revisión por la Dirección y la realización de auditorías, y mejorar continuamente la eficacia del Sistema de Gestión de la Calidad. En este proceso se revisan los resultados de todas las actividades documentadas del Organismo, además de proporcionar el resultado de indicadores y de auditorias internas.
A12: 6 | B12: Producción | C12: =_xlfn.CONCAT(B12&"_L") -> Producción_L | E12: 5 | G12: 5 | K12: 5 | L12: 5 | N12: 5 | O12: 5 | P12: 5 | Q12: 5 | R12: 5 | S12: 5 | T12: 5 | W12: 5 | X12: 5 | Y12: 5 | Z12: 5 | AB12: 5 | AC12: 5 | AD12: 5 | AE12: 5 | AF12: =COUNT(D12:AE12) -> 19 | AG12: El OOMAPAS de Cajeme planifica y lleva a cabo la producción y la prestación del servicio bajo condiciones controladas. Las condiciones controladas incluyen cuando sea aplicable la disponibilidad de información que describe las características del producto, la disponibilidad de instrucciones de trabajo cuando es necesario, el uso del equipo apropiado y la implementación de actividades de liberación, entrega y posteriores a la entrega del producto. En este proceso se definen las actividades para el desarrollo del producto (agua potable, alcantarillado y saneamiento) principalmente.
A13: 7 | B13: Proyectos_e_Infraestructura | C13: =_xlfn.CONCAT(B13&"_L") -> Proyectos_e_Infraestructura_L | E13: 7 | G13: 7 | K13: 7 | L13: 7 | N13: 7 | O13: 7 | P13: 7 | Q13: 7 | R13: 7 | Y13: 7 | Z13: 7 | AB13: 7 | AC13: 7 | AD13: 7 | AE13: 7 | AF13: =COUNT(D13:AE13) -> 15 | AG13: En este proceso se desarrollan las propuestas de las obras de infraestructura hidráulica necesarias para las redes de agua potable, alcantarillado y saneamiento, con el apoyo de los programas federales, así como la infraestructura para los fraccionamientos y obras que van de la mano con el H. Ayuntamiento de Cajeme.
A14: 8 | B14: Responsabilidad_de_la_Dirección | C14: =_xlfn.CONCAT(B14&"_L") -> Responsabilidad_de_la_Dirección_L | D14: 1 | E14: 1 | F14: 1 | G14: 1 | H14: 1 | I14: 1 | J14: 1 | K14: 1 | L14: 1 | M14: 1 | N14: 1 | O14: 1 | P14: 1 | Q14: 1 | R14: 1 | S14: 1 | T14: 1 | Y14: 1 | Z14: 1 | AB14: 1 | AF14: =COUNT(D14:AE14) -> 20 | AG14: La alta dirección del OOMAPAS de Cajeme proporciona evidencia de su compromiso con el desarrollo e implementación del Sistema de Gestión de la Calidad, así como con la mejora continua de su eficacia. Comunica a la organización la importancia de satisfacer tanto los requisitos de las partes interesadas como los legales y reglamentarios, establece la política de la calidad, asegura que se establecen los objetivos de la calidad, lleva a cabo Revisiones por la Dirección y asegura la disponibilidad de los recursos.

Sheet ENTRADAS-SALIDAS DIAGRAMA
B3: PROCESO | C3: ENTRADAS | E3: PROCESO | F3: SALIDAS
B4: Responsabilidad_de_la_Dirección | C4: El estado de las acciones de las revisiones por la dirección previas. | E4: Responsabilidad_de_la_Dirección | F4: Las oportunidades de mejora.
B5: Responsabilidad_de_la_Dirección | C5: Los cambios en las cuestiones externas e internas que sean pertinentes al sistema de gestión de calidad. | E5: Responsabilidad_de_la_Dirección | F5: Cualquier necesidad de cambio en el sistema de gestión de calidad.
B6: Responsabilidad_de_la_Dirección | C6: La información sobre el desempeño y la eficacia del sistema de gestión de la calidad. | E6: Responsabilidad_de_la_Dirección | F6: Las necesidades de Recursos. | P6: =INDEX($J$59:$J$61,MATCH($J$3,$I$59:$I$61,0)) -> #N/A
B7: Responsabilidad_de_la_Dirección | C7: La adecuación de los recursos. | E7: Responsabilidad_de_la_Dirección | F7: Planificación de Cambios. | R7: =#REF! -> #REF!
B8: Responsabilidad_de_la_Dirección | C8: La eficacia de las acciones tomadas para abordar los riesgos y las oportunidades. | E8: Responsabilidad_de_la_Dirección | F8: Información solicitada por las partes interesadas Internas y Externas -CEA CONAGUA-
B9: Responsabilidad_de_la_Dirección | C9: Las oportunidades de mejora e Información de los Resultados. | E9: Responsabilidad_de_la_Dirección
B10: Gestión_de_Recursos | C10: Necesidad de Mejora a Proceso/Producto. Solicitud de Materiales y Servicios. Retroalimentación del Cliente. | E10: Gestión_de_Recursos | F10: Producto o Servicio Entregado. Recursos Externos Gestionados.
B11: Gestión_de_Recursos | C11: Retroalimentación del Cliente. Información de Proveedores. Política de Calidad. | E11: Gestión_de_Recursos | F11: Avance Presupuestal. Cheque o transferencia bancaria.
B12: Gestión_de_Recursos | C12: Objetivos de Calidad. Mejoras al Proceso. Solicitud de capacitación. | E12: Gestión_de_Recursos | F12: Bienes resguardados. Proveedores Contratados.
B13: Gestión_de_Recursos | C13: Presupuesto de egresos. Presupuesto de Ingresos. Necesidad de Recursos. | E13: Gestión_de_Recursos | F13: Proveedores Evaluados. Presupuesto Ejercido.
B14: Gestión_de_Recursos | C14: Apoyos/Subsidios Externos. Información interna de Evaluación a Proveedores. | E14: Gestión_de_Recursos | F14: Ampliaciones al Presupuesto.
B15: Gestión_de_Recursos | C15: Programa de inversión. Resultados de análisis de Productos Químicos/ Críticos. Normatividad Mexicana. | E15: Gestión_de_Recursos | F15: Producto Aceptado o Rechazado.
B16: Mantenimiento_y_Calibración | C16: Política de calidad. Objetivos de calidad. | E16: Mantenimiento_y_Calibración | F16: Mantenimiento preventivo y correctivo efectuado.
B17: Mantenimiento_y_Calibración | C17: Bitácora de mantenimiento. Programa de mantenimiento preventivo. | E17: Mantenimiento_y_Calibración | F17: Información para evaluación.
B18: Mantenimiento_y_Calibración | C18: Programa de mantenimiento de infraestructura de plantas y oficinas. | E18: Mantenimiento_y_Calibración | F18: Servicios proporcionados.
B19: Mantenimiento_y_Calibración | C19: Mantenimiento correctivo. | E19: Mantenimiento_y_Calibración | F19: Equipos disponibles.
B20: Mantenimiento_y_Calibración | C20: Recursos proporcionados. Mejoras al proceso. | E20: Mantenimiento_y_Calibración | F20: Desempeño del proceso.
B21: Mantenimiento_y_Calibración | C21: Análisis FODA. Matriz de Riesgos y oportunidades. | E21: Mantenimiento_y_Calibración | F21: Necesidad de recursos.
... B32: Producción | C32: Análisis FODA. Matriz de Riesgos y Oportunidades. | E32: Producción | F32: Mejora al producto. Mejora al proceso.
B33: Producción | E33: Producción | F33: Cumplimiento a Normas Oficiales.
B34: Medición_Análisis_y_Mejora | C34: Política de Calidad Objetivos de Calidad | E34: Medición_Análisis_y_Mejora | F34: Resultados de auditorias Desempeño de procesos
B35: Medición_Análisis_y_Mejora | C35: Resultados de auditoria Interna Resultados de Auditorías Externas | E35: Medición_Análisis_y_Mejora | F35: Conformidad del producto Estado de las acciones correctivas y mejoras
B36: Medición_Análisis_y_Mejora | C36: Información de los procesos y productos Retroalimentación con el cliente | E36: Medición_Análisis_y_Mejora | F36: Recomendación Para la mejora Necesidad de recurso
B37: Medición_Análisis_y_Mejora | C37: Mejoras al proceso Recurso proporcionado | E37: Medición_Análisis_y_Mejora | F37: Eficacia Información al cliente
B38: Medición_Análisis_y_Mejora | C38: Requisitos legales y reglamentarios Tendencia de los procesos | E38: Medición_Análisis_y_Mejora | F38: Toma de decisiones
B39: Medición_Análisis_y_Mejora | C39: Revisión por la Dirección Análisis FODA Matriz de Riesgos y Oportunidades | E39: Medición_Análisis_y_Mejora | F39: Conformidad del servicio Eficiencia
B40: Proyectos_e_Infraestructura | C40: Montos de Inversión del Organismo. Programa de Acciones de Recursos Federales. | E40: Proyectos_e_Infraestructura | F40: Liberación de Derechos de Conexión. Acta de entrega recepción.
B41: Proyectos_e_Infraestructura | C41: Solicitud de Factibilidad. Solicitud de Viabilidad comercial e industrial. Solicitud de Pre- factibilidad. | E41: Proyectos_e_Infraestructura | F41: Pago de estimaciones. Indicadores. Proyectos.
B42: Proyectos_e_Infraestructura | C42: Solicitud de Aprobación de Proyectos. Solicitud de Elaboración de Proyectos. | E42: Proyectos_e_Infraestructura | F42: Infraestructura. Información.
B43: Proyectos_e_Infraestructura | C43: Solicitud de Supervisión de Obras. Solicitud de Pruebas de Calidad. | E43: Proyectos_e_Infraestructura | F43: Viabilidad Comercial e Industrial. Prefactibilidades.
B44: Proyectos_e_Infraestructura | C44: Solicitud de Conexiones de Redes. Solicitud de Revisión de Estimaciones. | E44: Proyectos_e_Infraestructura | F44: Aprobación de Proyectos.
B45: Proyectos_e_Infraestructura | C45: Solicitud de Entrega-Recepción de Obras. Solicitud de Pagos de Derechos de Conexión. | E45: Proyectos_e_Infraestructura | F45: Factibilidades.
... B49: Comunicación | C49: Gestión de Riesgos. Acciones de seguimiento de las revisiones por la dirección previas. | E49: Comunicación | F49: Información Suficiente Y Oportuna para todos Los Colaboradores del Organismo.
B50: Comunicación | C50: Los cambios en las cuestiones externas e internas que sean pertinentes al sistema de gestión de calidad. | E50: Comunicación
B51: Comunicación | C51: Política de la Calidad Objetivos de la Calidad. Recursos proporcionados. Situaciones Externas. | E51: Comunicación
I59: Responsabilidad_de_la_Dirección | J59: DIAGRAMAS DE FLUJO
I60: Responsabilidad_de_la_Dirección
I61: Gestión_de_Recursos
I62: Mantenimiento_y_Calibración
I63: Comercialización
I64: Producción
I65: Medición_Análisis_y_Mejora
I66: Proyectos_e_Infraestructura
I67: Comunicación

Sheet ÁREAS QUE INTEGRAN PROCESOS
B2: Responsabilidad_de_la_Dirección | E2: REQUISITOS NORMA ISO 9001/2015
B3: ÁREAS QUE INTEGRAN EL PROCESO: | C3: Dirección: | D3: Procedimientos involucrados: | E3: participación DIRECTA (D) INDIRECTA (I) | F3: 4.1 | G3: 4.2 | H3: 4.3 | I3: 4.4 | J3: 5.1 | K3: 5.2 | L3: 5.3 | M3: 6.1 | N3: 6.2 | O3: 6.3 | P3: 7.1 | Q3: 7.2 | R3: 7.3 | S3: 7.4 | T3: 7.5 | U3: 8.1 | V3: 8.2 | W3: 8.3 | X3: 8.4 | Y3: 8.5 | Z3: 8.6 | AA3: 8.7 | AB3: 9.1 | AC3: 9.2 | AD3: 9.3 | AE3: 10.1 | AF3: 10.2 | AG3: 10.3 | AH3: CÓDIGO 1
B4: Alta Dirección | C4: General | F4: =IF($B4="","",_xlfn.XLOOKUP($B$2,PROCESOS,'MATRIZ REQUISITOS ISO'!D$7:D$14,"")) -> 1 | G4: =IF($B4="","",_xlfn.XLOOKUP($B$2,PROCESOS,'MATRIZ REQUISITOS ISO'!E$7:E$14,"")) -> 1 | H4: =IF($B4="","",_xlfn.XLOOKUP($B$2,PROCESOS,'MATRIZ REQUISITOS ISO'!F$7:F$14,"")) -> 1 | I4: =IF($B4="","",_xlfn.XLOOKUP($B$2,PROCESOS,'MATRIZ REQUISITOS ISO'!G$7:G$14,"")) -> 1 | J4: =IF($B4="","",_xlfn.XLOOKUP($B$2,PROCESOS,'MATRIZ REQUISITOS ISO'!H$7:H$14,"")) -> 1 | K4: =IF($B4="","",_xlfn.XLOOKUP($B$2,PROCESOS,'MATRIZ REQUISITOS ISO'!I$7:I$14,"")) -> 1 | L4: =IF($B4="","",_xlfn.XLOOKUP($B$2,PROCESOS,'MATRIZ REQUISITOS ISO'!J$7:J$14,"")) -> 1 | M4: =IF($B4="","",_xlfn.XLOOKUP($B$2,PROCESOS,'MATRIZ REQUISITOS ISO'!K$7:K$14,"")) -> 1 | ... AG4: =IF($B4="","",_xlfn.XLOOKUP($B$2,PROCESOS,'MATRIZ REQUISITOS ISO'!AE$7:AE$14,"")) -> 0 | AH4: =$B$2 -> Responsabilidad_de_la_Dirección
B5: Sistema de Gestión de Calidad | C5: General | D5: OOMPSC-01 OOMPSC-02 OOMPSC-03 OOMPSC-05 OOMPSC-09 OOMPSC-11 OOMPSC-14 OOMPSC-16 | F5: =IF($B5="","",_xlfn.XLOOKUP($B$2,PROCESOS,'MATRIZ REQUISITOS ISO'!D$7:D$14,"")) -> 1 | G5: =IF($B5="","",_xlfn.XLOOKUP($B$2,PROCESOS,'MATRIZ REQUISITOS ISO'!E$7:E$14,"")) -> 1 | H5: =IF($B5="","",_xlfn.XLOOKUP($B$2,PROCESOS,'MATRIZ REQUISITOS ISO'!F$7:F$14,"")) -> 1 | I5: =IF($B5="","",_xlfn.XLOOKUP($B$2,PROCESOS,'MATRIZ REQUISITOS ISO'!G$7:G$14,"")) -> 1 | J5: =IF($B5="","",_xlfn.XLOOKUP($B$2,PROCESOS,'MATRIZ REQUISITOS ISO'!H$7:H$14,"")) -> 1 | K5: =IF($B5="","",_xlfn.XLOOKUP($B$2,PROCESOS,'MATRIZ REQUISITOS ISO'!I$7:I$14,"")) -> 1 | L5: =IF($B5="","",_xlfn.XLOOKUP($B$2,PROCESOS,'MATRIZ REQUISITOS ISO'!J$7:J$14,"")) -> 1 | M5: =IF($B5="","",_xlfn.XLOOKUP($B$2,PROCESOS,'MATRIZ REQUISITOS ISO'!K$7:K$14,"")) -> 1 | ... AG5: =IF($B5="","",_xlfn.XLOOKUP($B$2,PROCESOS,'MATRIZ REQUISITOS ISO'!AE$7:AE$14,"")) -> 0 | AH5: =$B$2 -> Responsabilidad_de_la_Dirección
F6: =IF($B6="","",_xlfn.XLOOKUP($B$2,PROCESOS,'MATRIZ REQUISITOS ISO'!D$7:D$14,"")) | G6: =IF($B6="","",_xlfn.XLOOKUP($B$2,PROCESOS,'MATRIZ REQUISITOS ISO'!E$7:E$14,"")) | H6: =IF($B6="","",_xlfn.XLOOKUP($B$2,PROCESOS,'MATRIZ REQUISITOS ISO'!F$7:F$14,"")) | I6: =IF($B6="","",_xlfn.XLOOKUP($B$2,PROCESOS,'MATRIZ REQUISITOS ISO'!G$7:G$14,"")) | J6: =IF($B6="","",_xlfn.XLOOKUP($B$2,PROCESOS,'MATRIZ REQUISITOS ISO'!H$7:H$14,"")) | K6: =IF($B6="","",_xlfn.XLOOKUP($B$2,PROCESOS,'MATRIZ REQUISITOS ISO'!I$7:I$14,"")) | L6: =IF($B6="","",_xlfn.XLOOKUP($B$2,PROCESOS,'MATRIZ REQUISITOS ISO'!J$7:J$14,"")) | M6: =IF($B6="","",_xlfn.XLOOKUP($B$2,PROCESOS,'MATRIZ REQUISITOS ISO'!K$7:K$14,"")) | ... AG6: =IF($B6="","",_xlfn.XLOOKUP($B$2,PROCESOS,'MATRIZ REQUISITOS ISO'!AE$7:AE$14,"")) | AH6: =$B$2 -> Responsabilidad_de_la_Dirección
F7: =IF($B7="","",_xlfn.XLOOKUP($B$2,PROCESOS,'MATRIZ REQUISITOS ISO'!D$7:D$14,"")) | G7: =IF($B7="","",_xlfn.XLOOKUP($B$2,PROCESOS,'MATRIZ REQUISITOS ISO'!E$7:E$14,"")) | H7: =IF($B7="","",_xlfn.XLOOKUP($B$2,PROCESOS,'MATRIZ REQUISITOS ISO'!F$7:F$14,"")) | I7: =IF($B7="","",_xlfn.XLOOKUP($B$2,PROCESOS,'MATRIZ REQUISITOS ISO'!G$7:G$14,"")) | J7: =IF($B7="","",_xlfn.XLOOKUP($B$2,PROCESOS,'MATRIZ REQUISITOS ISO'!H$7:H$14,"")) | K7: =IF($B7="","",_xlfn.XLOOKUP($B$2,PROCESOS,'MATRIZ REQUISITOS ISO'!I$7:I$14,"")) | L7: =IF($B7="","",_xlfn.XLOOKUP($B$2,PROCESOS,'MATRIZ REQUISITOS ISO'!J$7:J$14,"")) | M7: =IF($B7="","",_xlfn.XLOOKUP($B$2,PROCESOS,'MATRIZ REQUISITOS ISO'!K$7:K$14,"")) | ... AG7: =IF($B7="","",_xlfn.XLOOKUP($B$2,PROCESOS,'MATRIZ REQUISITOS ISO'!AE$7:AE$14,"")) | AH7: =$B$2 -> Responsabilidad_de_la_Dirección
F8: =IF($B8="","",_xlfn.XLOOKUP($B$2,PROCESOS,'MATRIZ REQUISITOS ISO'!D$7:D$14,"")) | G8: =IF($B8="","",_xlfn.XLOOKUP($B$2,PROCESOS,'MATRIZ REQUISITOS ISO'!E$7:E$14,"")) | H8: =IF($B8="","",_xlfn.XLOOKUP($B$2,PROCESOS,'MATRIZ REQUISITOS ISO'!F$7:F$14,"")) | I8: =IF($B8="","",_xlfn.XLOOKUP($B$2,PROCESOS,'MATRIZ REQUISITOS ISO'!G$7:G$14,"")) | J8: =IF($B8="","",_xlfn.XLOOKUP($B$2,PROCESOS,'MATRIZ REQUISITOS ISO'!H$7:H$14,"")) | K8: =IF($B8="","",_xlfn.XLOOKUP($B$2,PROCESOS,'MATRIZ REQUISITOS ISO'!I$7:I$14,"")) | L8: =IF($B8="","",_xlfn.XLOOKUP($B$2,PROCESOS,'MATRIZ REQUISITOS ISO'!J$7:J$14,"")) | M8: =IF($B8="","",_xlfn.XLOOKUP($B$2,PROCESOS,'MATRIZ REQUISITOS ISO'!K$7:K$14,"")) | ... AG8: =IF($B8="","",_xlfn.XLOOKUP($B$2,PROCESOS,'MATRIZ REQUISITOS ISO'!AE$7:AE$14,"")) | AH8: =$B$2 -> Responsabilidad_de_la_Dirección
B9: Gestión_de_Recursos | E9: REQUISITOS NORMA ISO 9001/2015
B10: ÁREAS QUE INTEGRAN EL PROCESO: | C10: Dirección: | D10: Procedimientos involucrados: | E10: participación DIRECTA (D) INDIRECTA (I) | F10: 4.1 | G10: 4.2 | H10: 4.3 | I10: 4.4 | J10: 5.1 | K10: 5.2 | L10: 5.3 | M10: 6.1 | N10: 6.2 | O10: 6.3 | P10: 7.1 | Q10: 7.2 | R10: 7.3 | S10: 7.4 | T10: 7.5 | U10: 8.1 | V10: 8.2 | W10: 8.3 | X10: 8.4 | Y10: 8.5 | Z10: 8.6 | AA10: 8.7 | AB10: 9.1 | AC10: 9.2 | AD10: 9.3 | AE10: 10.1 | AF10: 10.2 | AG10: 10.3 | AH10: CÓDIGO 1
B11: Alcantarillado y Saneamiento | C11: Administrativa | D11: OOMPGS-02 OOMPGS-08 OOMPGS-10 | F11: =IF($B11="","",_xlfn.XLOOKUP($B$9,PROCESOS,'MATRIZ REQUISITOS ISO'!D$7:D$14,"")) -> 0 | G11: =IF($B11="","",_xlfn.XLOOKUP($B$9,PROCESOS,'MATRIZ REQUISITOS ISO'!E$7:E$14,"")) -> 0 | H11: =IF($B11="","",_xlfn.XLOOKUP($B$9,PROCESOS,'MATRIZ REQUISITOS ISO'!F$7:F$14,"")) -> 0 | I11: =IF($B11="","",_xlfn.XLOOKUP($B$9,PROCESOS,'MATRIZ REQUISITOS ISO'!G$7:G$14,"")) -> 2 | J11: =IF($B11="","",_xlfn.XLOOKUP($B$9,PROCESOS,'MATRIZ REQUISITOS ISO'!H$7:H$14,"")) -> 0 | K11: =IF($B11="","",_xlfn.XLOOKUP($B$9,PROCESOS,'MATRIZ REQUISITOS ISO'!I$7:I$14,"")) -> 0 | L11: =IF($B11="","",_xlfn.XLOOKUP($B$9,PROCESOS,'MATRIZ REQUISITOS ISO'!J$7:J$14,"")) -> 0 | M11: =IF($B11="","",_xlfn.XLOOKUP($B$9,PROCESOS,'MATRIZ REQUISITOS ISO'!K$7:K$14,"")) -> 2 | ... AG11: =IF($B11="","",_xlfn.XLOOKUP($B$9,PROCESOS,'MATRIZ REQUISITOS ISO'!AE$7:AE$14,"")) -> 2 | AH11: =$B$9 -> Gestión_de_Recursos
B12: Contabilidad | C12: Administrativa | D12: OOMPCO-01 OOMPCO-02 OOMPCO-03 OOMPCO-04 OOMPCO-05 OOMPCO-06 OOMPCO-09 | F12: =IF($B12="","",_xlfn.XLOOKUP($B$9,PROCESOS,'MATRIZ REQUISITOS ISO'!D$7:D$14,"")) -> 0 | G12: =IF($B12="","",_xlfn.XLOOKUP($B$9,PROCESOS,'MATRIZ REQUISITOS ISO'!E$7:E$14,"")) -> 0 | H12: =IF($B12="","",_xlfn.XLOOKUP($B$9,PROCESOS,'MATRIZ REQUISITOS ISO'!F$7:F$14,"")) -> 0 | I12: =IF($B12="","",_xlfn.XLOOKUP($B$9,PROCESOS,'MATRIZ REQUISITOS ISO'!G$7:G$14,"")) -> 2 | J12: =IF($B12="","",_xlfn.XLOOKUP($B$9,PROCESOS,'MATRIZ REQUISITOS ISO'!H$7:H$14,"")) -> 0 | K12: =IF($B12="","",_xlfn.XLOOKUP($B$9,PROCESOS,'MATRIZ REQUISITOS ISO'!I$7:I$14,"")) -> 0 | L12: =IF($B12="","",_xlfn.XLOOKUP($B$9,PROCESOS,'MATRIZ REQUISITOS ISO'!J$7:J$14,"")) -> 0 | M12: =IF($B12="","",_xlfn.XLOOKUP($B$9,PROCESOS,'MATRIZ REQUISITOS ISO'!K$7:K$14,"")) -> 2 | ... AG12: =IF($B12="","",_xlfn.XLOOKUP($B$9,PROCESOS,'MATRIZ REQUISITOS ISO'!AE$7:AE$14,"")) -> 2 | AH12: =$B$9 -> Gestión_de_Recursos
B13: Licitaciones | C13: Administrativa | D13: OOMPCL-01 OOMPCL-02 | F13: =IF($B13="","",_xlfn.XLOOKUP($B$9,PROCESOS,'MATRIZ REQUISITOS ISO'!D$7:D$14,"")) -> 0 | G13: =IF($B13="","",_xlfn.XLOOKUP($B$9,PROCESOS,'MATRIZ REQUISITOS ISO'!E$7:E$14,"")) -> 0 | H13: =IF($B13="","",_xlfn.XLOOKUP($B$9,PROCESOS,'MATRIZ REQUISITOS ISO'!F$7:F$14,"")) -> 0 | I13: =IF($B13="","",_xlfn.XLOOKUP($B$9,PROCESOS,'MATRIZ REQUISITOS ISO'!G$7:G$14,"")) -> 2 | J13: =IF($B13="","",_xlfn.XLOOKUP($B$9,PROCESOS,'MATRIZ REQUISITOS ISO'!H$7:H$14,"")) -> 0 | K13: =IF($B13="","",_xlfn.XLOOKUP($B$9,PROCESOS,'MATRIZ REQUISITOS ISO'!I$7:I$14,"")) -> 0 | L13: =IF($B13="","",_xlfn.XLOOKUP($B$9,PROCESOS,'MATRIZ REQUISITOS ISO'!J$7:J$14,"")) -> 0 | M13: =IF($B13="","",_xlfn.XLOOKUP($B$9,PROCESOS,'MATRIZ REQUISITOS ISO'!K$7:K$14,"")) -> 2 | ... AG13: =IF($B13="","",_xlfn.XLOOKUP($B$9,PROCESOS,'MATRIZ REQUISITOS ISO'!AE$7:AE$14,"")) -> 2 | AH13: =$B$9 -> Gestión_de_Recursos
B14: Recursos Humanos | C14: Administrativa | D14: OOMPRH-01 OOMPRH-04 OOMPRH-08 OOMPRH-09 OOMPRH-10 OOMPRH-11 OOMPRH-12 OOMPRH-16 | F14: =IF($B14="","",_xlfn.XLOOKUP($B$9,PROCESOS,'MATRIZ REQUISITOS ISO'!D$7:D$14,"")) -> 0 | G14: =IF($B14="","",_xlfn.XLOOKUP($B$9,PROCESOS,'MATRIZ REQUISITOS ISO'!E$7:E$14,"")) -> 0 | H14: =IF($B14="","",_xlfn.XLOOKUP($B$9,PROCESOS,'MATRIZ REQUISITOS ISO'!F$7:F$14,"")) -> 0 | I14: =IF($B14="","",_xlfn.XLOOKUP($B$9,PROCESOS,'MATRIZ REQUISITOS ISO'!G$7:G$14,"")) -> 2 | J14: =IF($B14="","",_xlfn.XLOOKUP($B$9,PROCESOS,'MATRIZ REQUISITOS ISO'!H$7:H$14,"")) -> 0 | K14: =IF($B14="","",_xlfn.XLOOKUP($B$9,PROCESOS,'MATRIZ REQUISITOS ISO'!I$7:I$14,"")) -> 0 | L14: =IF($B14="","",_xlfn.XLOOKUP($B$9,PROCESOS,'MATRIZ REQUISITOS ISO'!J$7:J$14,"")) -> 0 | M14: =IF($B14="","",_xlfn.XLOOKUP($B$9,PROCESOS,'MATRIZ REQUISITOS ISO'!K$7:K$14,"")) -> 2 | ... AG14: =IF($B14="","",_xlfn.XLOOKUP($B$9,PROCESOS,'MATRIZ REQUISITOS ISO'!AE$7:AE$14,"")) -> 2 | AH14: =$B$9 -> Gestión_de_Recursos
B15: Recursos Materiales | C15: Administrativa | D15: OOMPRM-01 OOMPRM-03 OOMPRM-07 OOMPRM-08 OOMIRM-01 | F15: =IF($B15="","",_xlfn.XLOOKUP($B$9,PROCESOS,'MATRIZ REQUISITOS ISO'!D$7:D$14,"")) -> 0 | G15: =IF($B15="","",_xlfn.XLOOKUP($B$9,PROCESOS,'MATRIZ REQUISITOS ISO'!E$7:E$14,"")) -> 0 | H15: =IF($B15="","",_xlfn.XLOOKUP($B$9,PROCESOS,'MATRIZ REQUISITOS ISO'!F$7:F$14,"")) -> 0 | I15: =IF($B15="","",_xlfn.XLOOKUP($B$9,PROCESOS,'MATRIZ REQUISITOS ISO'!G$7:G$14,"")) -> 2 | J15: =IF($B15="","",_xlfn.XLOOKUP($B$9,PROCESOS,'MATRIZ REQUISITOS ISO'!H$7:H$14,"")) -> 0 | K15: =IF($B15="","",_xlfn.XLOOKUP($B$9,PROCESOS,'MATRIZ REQUISITOS ISO'!I$7:I$14,"")) -> 0 | L15: =IF($B15="","",_xlfn.XLOOKUP($B$9,PROCESOS,'MATRIZ REQUISITOS ISO'!J$7:J$14,"")) -> 0 | M15: =IF($B15="","",_xlfn.XLOOKUP($B$9,PROCESOS,'MATRIZ REQUISITOS ISO'!K$7:K$14,"")) -> 2 | ... AG15: =IF($B15="","",_xlfn.XLOOKUP($B$9,PROCESOS,'MATRIZ REQUISITOS ISO'!AE$7:AE$14,"")) -> 2 | AH15: =$B$9 -> Gestión_de_Recursos
B16: Seguridad Industrial | C16: Administrativa | D16: OOMPIS-01 OOMPIS-02 OOMPIS-03 OOMPIS-05 | F16: =IF($B16="","",_xlfn.XLOOKUP($B$9,PROCESOS,'MATRIZ REQUISITOS ISO'!D$7:D$14,"")) -> 0 | G16: =IF($B16="","",_xlfn.XLOOKUP($B$9,PROCESOS,'MATRIZ REQUISITOS ISO'!E$7:E$14,"")) -> 0 | H16: =IF($B16="","",_xlfn.XLOOKUP($B$9,PROCESOS,'MATRIZ REQUISITOS ISO'!F$7:F$14,"")) -> 0 | I16: =IF($B16="","",_xlfn.XLOOKUP($B$9,PROCESOS,'MATRIZ REQUISITOS ISO'!G$7:G$14,"")) -> 2 | J16: =IF($B16="","",_xlfn.XLOOKUP($B$9,PROCESOS,'MATRIZ REQUISITOS ISO'!H$7:H$14,"")) -> 0 | K16: =IF($B16="","",_xlfn.XLOOKUP($B$9,PROCESOS,'MATRIZ REQUISITOS ISO'!I$7:I$14,"")) -> 0 | L16: =IF($B16="","",_xlfn.XLOOKUP($B$9,PROCESOS,'MATRIZ REQUISITOS ISO'!J$7:J$14,"")) -> 0 | M16: =IF($B16="","",_xlfn.XLOOKUP($B$9,PROCESOS,'MATRIZ REQUISITOS ISO'!K$7:K$14,"")) -> 2 | ... AG16: =IF($B16="","",_xlfn.XLOOKUP($B$9,PROCESOS,'MATRIZ REQUISITOS ISO'!AE$7:AE$14,"")) -> 2 | AH16: =$B$9 -> Gestión_de_Recursos
B17: Trámites Técnicos | C17: Técnica | D17: OOMPTT-05 OOMPTT-07 OOMPTT-08 | F17: =IF($B17="","",_xlfn.XLOOKUP($B$9,PROCESOS,'MATRIZ REQUISITOS ISO'!D$7:D$14,"")) -> 0 | G17: =IF($B17="","",_xlfn.XLOOKUP($B$9,PROCESOS,'MATRIZ REQUISITOS ISO'!E$7:E$14,"")) -> 0 | H17: =IF($B17="","",_xlfn.XLOOKUP($B$9,PROCESOS,'MATRIZ REQUISITOS ISO'!F$7:F$14,"")) -> 0 | I17: =IF($B17="","",_xlfn.XLOOKUP($B$9,PROCESOS,'MATRIZ REQUISITOS ISO'!G$7:G$14,"")) -> 2 | J17: =IF($B17="","",_xlfn.XLOOKUP($B$9,PROCESOS,'MATRIZ REQUISITOS ISO'!H$7:H$14,"")) -> 0 | K17: =IF($B17="","",_xlfn.XLOOKUP($B$9,PROCESOS,'MATRIZ REQUISITOS ISO'!I$7:I$14,"")) -> 0 | L17: =IF($B17="","",_xlfn.XLOOKUP($B$9,PROCESOS,'MATRIZ REQUISITOS ISO'!J$7:J$14,"")) -> 0 | M17: =IF($B17="","",_xlfn.XLOOKUP($B$9,PROCESOS,'MATRIZ REQUISITOS ISO'!K$7:K$14,"")) -> 2 | ... AG17: =IF($B17="","",_xlfn.XLOOKUP($B$9,PROCESOS,'MATRIZ REQUISITOS ISO'!AE$7:AE$14,"")) -> 2 | AH17: =$B$9 -> Gestión_de_Recursos
F18: =IF($B18="","",_xlfn.XLOOKUP($B$9,PROCESOS,'MATRIZ REQUISITOS ISO'!D$7:D$14,"")) | G18: =IF($B18="","",_xlfn.XLOOKUP($B$9,PROCESOS,'MATRIZ REQUISITOS ISO'!E$7:E$14,"")) | H18: =IF($B18="","",_xlfn.XLOOKUP($B$9,PROCESOS,'MATRIZ REQUISITOS ISO'!F$7:F$14,"")) | I18: =IF($B18="","",_xlfn.XLOOKUP($B$9,PROCESOS,'MATRIZ REQUISITOS ISO'!G$7:G$14,"")) | J18: =IF($B18="","",_xlfn.XLOOKUP($B$9,PROCESOS,'MATRIZ REQUISITOS ISO'!H$7:H$14,"")) | K18: =IF($B18="","",_xlfn.XLOOKUP($B$9,PROCESOS,'MATRIZ REQUISITOS ISO'!I$7:I$14,"")) | L18: =IF($B18="","",_xlfn.XLOOKUP($B$9,PROCESOS,'MATRIZ REQUISITOS ISO'!J$7:J$14,"")) | M18: =IF($B18="","",_xlfn.XLOOKUP($B$9,PROCESOS,'MATRIZ REQUISITOS ISO'!K$7:K$14,"")) | ... AG18: =IF($B18="","",_xlfn.XLOOKUP($B$9,PROCESOS,'MATRIZ REQUISITOS ISO'!AE$7:AE$14,"")) | AH18: =$B$9 -> Gestión_de_Recursos
B19: Mantenimiento_y_Calibración | E19: REQUISITOS NORMA ISO 9001/2015
B20: ÁREAS QUE INTEGRAN EL PROCESO: | C20: Dirección: | D20: Procedimientos involucrados: | E20: participación DIRECTA (D) INDIRECTA (I) | F20: 4.1 | G20: 4.2 | H20: 4.3 | I20: 4.4 | J20: 5.1 | K20: 5.2 | L20: 5.3 | M20: 6.1 | N20: 6.2 | O20: 6.3 | P20: 7.1 | Q20: 7.2 | R20: 7.3 | S20: 7.4 | T20: 7.5 | U20: 8.1 | V20: 8.2 | W20: 8.3 | X20: 8.4 | Y20: 8.5 | Z20: 8.6 | AA20: 8.7 | AB20: 9.1 | AC20: 9.2 | AD20: 9.3 | AE20: 10.1 | AF20: 10.2 | AG20: 10.3 | AH20: CÓDIGO 1
B21: Alcantarillado y Saneamiento | C21: Técnica | D21: OOMPGS-01 OOMPGS-02 OOMPGS-04 OOMPGS-06 OOMPGS-09 OOMPGS-10 OOMPGS-11 | F21: =IF($B21="","",_xlfn.XLOOKUP($B$19,PROCESOS,'MATRIZ REQUISITOS ISO'!D$7:D$14,"")) -> 0 | G21: =IF($B21="","",_xlfn.XLOOKUP($B$19,PROCESOS,'MATRIZ REQUISITOS ISO'!E$7:E$14,"")) -> 0 | H21: =IF($B21="","",_xlfn.XLOOKUP($B$19,PROCESOS,'MATRIZ REQUISITOS ISO'!F$7:F$14,"")) -> 0 | I21: =IF($B21="","",_xlfn.XLOOKUP($B$19,PROCESOS,'MATRIZ REQUISITOS ISO'!G$7:G$14,"")) -> 3 | J21: =IF($B21="","",_xlfn.XLOOKUP($B$19,PROCESOS,'MATRIZ REQUISITOS ISO'!H$7:H$14,"")) -> 0 | K21: =IF($B21="","",_xlfn.XLOOKUP($B$19,PROCESOS,'MATRIZ REQUISITOS ISO'!I$7:I$14,"")) -> 0 | L21: =IF($B21="","",_xlfn.XLOOKUP($B$19,PROCESOS,'MATRIZ REQUISITOS ISO'!J$7:J$14,"")) -> 0 | M21: =IF($B21="","",_xlfn.XLOOKUP($B$19,PROCESOS,'MATRIZ REQUISITOS ISO'!K$7:K$14,"")) -> 3 | ... AG21: =IF($B21="","",_xlfn.XLOOKUP($B$19,PROCESOS,'MATRIZ REQUISITOS ISO'!AE$7:AE$14,"")) -> 3 | AH21: =$B$19 -> Mantenimiento_y_Calibración
B22: Control de Calidad | C22: Técnica | D22: OOMPCC-27 OOMPCC-28 OOMPCC-29 OOMPCC-30 OOMPCC-31 OOMPCC-32 OOMPCC-33 OOMPCC-34 OOMPCC-43 OOMPCC-44 OOMPCC-48 OOMPCC-50 OOMPCC-51 OOMPCC-52 OOMPCC-58 OOMPCC-60 OOMPCC-61 OOMPCC-78 OOMPCC-79 | F22: =IF($B22="","",_xlfn.XLOOKUP($B$19,PROCESOS,'MATRIZ REQUISITOS ISO'!D$7:D$14,"")) -> 0 | G22: =IF($B22="","",_xlfn.XLOOKUP($B$19,PROCESOS,'MATRIZ REQUISITOS ISO'!E$7:E$14,"")) -> 0 | H22: =IF($B22="","",_xlfn.XLOOKUP($B$19,PROCESOS,'MATRIZ REQUISITOS ISO'!F$7:F$14,"")) -> 0 | I22: =IF($B22="","",_xlfn.XLOOKUP($B$19,PROCESOS,'MATRIZ REQUISITOS ISO'!G$7:G$14,"")) -> 3 | J22: =IF($B22="","",_xlfn.XLOOKUP($B$19,PROCESOS,'MATRIZ REQUISITOS ISO'!H$7:H$14,"")) -> 0 | K22: =IF($B22="","",_xlfn.XLOOKUP($B$19,PROCESOS,'MATRIZ REQUISITOS ISO'!I$7:I$14,"")) -> 0 | L22: =IF($B22="","",_xlfn.XLOOKUP($B$19,PROCESOS,'MATRIZ REQUISITOS ISO'!J$7:J$14,"")) -> 0 | M22: =IF($B22="","",_xlfn.XLOOKUP($B$19,PROCESOS,'MATRIZ REQUISITOS ISO'!K$7:K$14,"")) -> 3 | ... AG22: =IF($B22="","",_xlfn.XLOOKUP($B$19,PROCESOS,'MATRIZ REQUISITOS ISO'!AE$7:AE$14,"")) -> 3 | AH22: =$B$19 -> Mantenimiento_y_Calibración
B23: Informática | C23: Administrativa | D23: OOMPGI-01 OOMPGI-02 OOMPGI-03 OOMPGI-04 OOMPGI-05 OOMPGI-06 OOMPGI-07 | F23: =IF($B23="","",_xlfn.XLOOKUP($B$19,PROCESOS,'MATRIZ REQUISITOS ISO'!D$7:D$14,"")) -> 0 | G23: =IF($B23="","",_xlfn.XLOOKUP($B$19,PROCESOS,'MATRIZ REQUISITOS ISO'!E$7:E$14,"")) -> 0 | H23: =IF($B23="","",_xlfn.XLOOKUP($B$19,PROCESOS,'MATRIZ REQUISITOS ISO'!F$7:F$14,"")) -> 0 | I23: =IF($B23="","",_xlfn.XLOOKUP($B$19,PROCESOS,'MATRIZ REQUISITOS ISO'!G$7:G$14,"")) -> 3 | J23: =IF($B23="","",_xlfn.XLOOKUP($B$19,PROCESOS,'MATRIZ REQUISITOS ISO'!H$7:H$14,"")) -> 0 | K23: =IF($B23="","",_xlfn.XLOOKUP($B$19,PROCESOS,'MATRIZ REQUISITOS ISO'!I$7:I$14,"")) -> 0 | L23: =IF($B23="","",_xlfn.XLOOKUP($B$19,PROCESOS,'MATRIZ REQUISITOS ISO'!J$7:J$14,"")) -> 0 | M23: =IF($B23="","",_xlfn.XLOOKUP($B$19,PROCESOS,'MATRIZ REQUISITOS ISO'!K$7:K$14,"")) -> 3 | ... AG23: =IF($B23="","",_xlfn.XLOOKUP($B$19,PROCESOS,'MATRIZ REQUISITOS ISO'!AE$7:AE$14,"")) -> 3 | AH23: =$B$19 -> Mantenimiento_y_Calibración
B24: Mantenimiento de Redes | C24: Técnica | D24: OOMPMR-01 OOMPMR-06 OOMPMR-07 | F24: =IF($B24="","",_xlfn.XLOOKUP($B$19,PROCESOS,'MATRIZ REQUISITOS ISO'!D$7:D$14,"")) -> 0 | G24: =IF($B24="","",_xlfn.XLOOKUP($B$19,PROCESOS,'MATRIZ REQUISITOS ISO'!E$7:E$14,"")) -> 0 | H24: =IF($B24="","",_xlfn.XLOOKUP($B$19,PROCESOS,'MATRIZ REQUISITOS ISO'!F$7:F$14,"")) -> 0 | I24: =IF($B24="","",_xlfn.XLOOKUP($B$19,PROCESOS,'MATRIZ REQUISITOS ISO'!G$7:G$14,"")) -> 3 | J24: =IF($B24="","",_xlfn.XLOOKUP($B$19,PROCESOS,'MATRIZ REQUISITOS ISO'!H$7:H$14,"")) -> 0 | K24: =IF($B24="","",_xlfn.XLOOKUP($B$19,PROCESOS,'MATRIZ REQUISITOS ISO'!I$7:I$14,"")) -> 0 | L24: =IF($B24="","",_xlfn.XLOOKUP($B$19,PROCESOS,'MATRIZ REQUISITOS ISO'!J$7:J$14,"")) -> 0 | M24: =IF($B24="","",_xlfn.XLOOKUP($B$19,PROCESOS,'MATRIZ REQUISITOS ISO'!K$7:K$14,"")) -> 3 | ... AG24: =IF($B24="","",_xlfn.XLOOKUP($B$19,PROCESOS,'MATRIZ REQUISITOS ISO'!AE$7:AE$14,"")) -> 3 | AH24: =$B$19 -> Mantenimiento_y_Calibración
B25: Mantenimiento y Servicios Generales | C25: Administrativa | D25: OOMPMS-01 OOMPMS-02 OOMPMS-03 OOMPMS-04 | F25: =IF($B25="","",_xlfn.XLOOKUP($B$19,PROCESOS,'MATRIZ REQUISITOS ISO'!D$7:D$14,"")) -> 0 | G25: =IF($B25="","",_xlfn.XLOOKUP($B$19,PROCESOS,'MATRIZ REQUISITOS ISO'!E$7:E$14,"")) -> 0 | H25: =IF($B25="","",_xlfn.XLOOKUP($B$19,PROCESOS,'MATRIZ REQUISITOS ISO'!F$7:F$14,"")) -> 0 | I25: =IF($B25="","",_xlfn.XLOOKUP($B$19,PROCESOS,'MATRIZ REQUISITOS ISO'!G$7:G$14,"")) -> 3 | J25: =IF($B25="","",_xlfn.XLOOKUP($B$19,PROCESOS,'MATRIZ REQUISITOS ISO'!H$7:H$14,"")) -> 0 | K25: =IF($B25="","",_xlfn.XLOOKUP($B$19,PROCESOS,'MATRIZ REQUISITOS ISO'!I$7:I$14,"")) -> 0 | L25: =IF($B25="","",_xlfn.XLOOKUP($B$19,PROCESOS,'MATRIZ REQUISITOS ISO'!J$7:J$14,"")) -> 0 | M25: =IF($B25="","",_xlfn.XLOOKUP($B$19,PROCESOS,'MATRIZ REQUISITOS ISO'!K$7:K$14,"")) -> 3 | ... AG25: =IF($B25="","",_xlfn.XLOOKUP($B$19,PROCESOS,'MATRIZ REQUISITOS ISO'!AE$7:AE$14,"")) -> 3 | AH25: =$B$19 -> Mantenimiento_y_Calibración
B26: Plantas Potabilizadoras | C26: Técnica | D26: OOMPPP-01 OOMPPP-02 OOMPPP-03 OOMPPP-04 OOMPPP-21 OOMPPP-22 OOMPPP-23 OOMPPP-24 OOMPPP-25 OOMPPP-29 OOMPPP-30 OOMPPP-31 OOMPPP-32 OOMPPP-34 | F26: =IF($B26="","",_xlfn.XLOOKUP($B$19,PROCESOS,'MATRIZ REQUISITOS ISO'!D$7:D$14,"")) -> 0 | G26: =IF($B26="","",_xlfn.XLOOKUP($B$19,PROCESOS,'MATRIZ REQUISITOS ISO'!E$7:E$14,"")) -> 0 | H26: =IF($B26="","",_xlfn.XLOOKUP($B$19,PROCESOS,'MATRIZ REQUISITOS ISO'!F$7:F$14,"")) -> 0 | I26: =IF($B26="","",_xlfn.XLOOKUP($B$19,PROCESOS,'MATRIZ REQUISITOS ISO'!G$7:G$14,"")) -> 3 | J26: =IF($B26="","",_xlfn.XLOOKUP($B$19,PROCESOS,'MATRIZ REQUISITOS ISO'!H$7:H$14,"")) -> 0 | K26: =IF($B26="","",_xlfn.XLOOKUP($B$19,PROCESOS,'MATRIZ REQUISITOS ISO'!I$7:I$14,"")) -> 0 | L26: =IF($B26="","",_xlfn.XLOOKUP($B$19,PROCESOS,'MATRIZ REQUISITOS ISO'!J$7:J$14,"")) -> 0 | M26: =IF($B26="","",_xlfn.XLOOKUP($B$19,PROCESOS,'MATRIZ REQUISITOS ISO'!K$7:K$14,"")) -> 3 | ... AG26: =IF($B26="","",_xlfn.XLOOKUP($B$19,PROCESOS,'MATRIZ REQUISITOS ISO'!AE$7:AE$14,"")) -> 3 | AH26: =$B$19 -> Mantenimiento_y_Calibración
B27: Seguridad Industrial | C27: Administrativa | D27: OOMPIS-01 OOMPIS-04 | F27: =IF($B27="","",_xlfn.XLOOKUP($B$19,PROCESOS,'MATRIZ REQUISITOS ISO'!D$7:D$14,"")) -> 0 | G27: =IF($B27="","",_xlfn.XLOOKUP($B$19,PROCESOS,'MATRIZ REQUISITOS ISO'!E$7:E$14,"")) -> 0 | H27: =IF($B27="","",_xlfn.XLOOKUP($B$19,PROCESOS,'MATRIZ REQUISITOS ISO'!F$7:F$14,"")) -> 0 | I27: =IF($B27="","",_xlfn.XLOOKUP($B$19,PROCESOS,'MATRIZ REQUISITOS ISO'!G$7:G$14,"")) -> 3 | J27: =IF($B27="","",_xlfn.XLOOKUP($B$19,PROCESOS,'MATRIZ REQUISITOS ISO'!H$7:H$14,"")) -> 0 | K27: =IF($B27="","",_xlfn.XLOOKUP($B$19,PROCESOS,'MATRIZ REQUISITOS ISO'!I$7:I$14,"")) -> 0 | L27: =IF($B27="","",_xlfn.XLOOKUP($B$19,PROCESOS,'MATRIZ REQUISITOS ISO'!J$7:J$14,"")) -> 0 | M27: =IF($B27="","",_xlfn.XLOOKUP($B$19,PROCESOS,'MATRIZ REQUISITOS ISO'!K$7:K$14,"")) -> 3 | ... AG27: =IF($B27="","",_xlfn.XLOOKUP($B$19,PROCESOS,'MATRIZ REQUISITOS ISO'!AE$7:AE$14,"")) -> 3 | AH27: =$B$19 -> Mantenimiento_y_Calibración
B28: Suburbano Técnico | C28: Técnica | D28: OOMPTS-03 OOMPTS-05 OOMPTS-06 OOMPTS-07 OOMPTS-13 OOMPTS-15 OOMPTS-16 OOMPTS-18 | F28: =IF($B28="","",_xlfn.XLOOKUP($B$19,PROCESOS,'MATRIZ REQUISITOS ISO'!D$7:D$14,"")) -> 0 | G28: =IF($B28="","",_xlfn.XLOOKUP($B$19,PROCESOS,'MATRIZ REQUISITOS ISO'!E$7:E$14,"")) -> 0 | H28: =IF($B28="","",_xlfn.XLOOKUP($B$19,PROCESOS,'MATRIZ REQUISITOS ISO'!F$7:F$14,"")) -> 0 | I28: =IF($B28="","",_xlfn.XLOOKUP($B$19,PROCESOS,'MATRIZ REQUISITOS ISO'!G$7:G$14,"")) -> 3 | J28: =IF($B28="","",_xlfn.XLOOKUP($B$19,PROCESOS,'MATRIZ REQUISITOS ISO'!H$7:H$14,"")) -> 0 | K28: =IF($B28="","",_xlfn.XLOOKUP($B$19,PROCESOS,'MATRIZ REQUISITOS ISO'!I$7:I$14,"")) -> 0 | L28: =IF($B28="","",_xlfn.XLOOKUP($B$19,PROCESOS,'MATRIZ REQUISITOS ISO'!J$7:J$14,"")) -> 0 | M28: =IF($B28="","",_xlfn.XLOOKUP($B$19,PROCESOS,'MATRIZ REQUISITOS ISO'!K$7:K$14,"")) -> 3 | ... AG28: =IF($B28="","",_xlfn.XLOOKUP($B$19,PROCESOS,'MATRIZ REQUISITOS ISO'!AE$7:AE$14,"")) -> 3 | AH28: =$B$19 -> Mantenimiento_y_Calibración
F29: =IF($B29="","",_xlfn.XLOOKUP($B$19,PROCESOS,'MATRIZ REQUISITOS ISO'!D$7:D$14,"")) | G29: =IF($B29="","",_xlfn.XLOOKUP($B$19,PROCESOS,'MATRIZ REQUISITOS ISO'!E$7:E$14,"")) | H29: =IF($B29="","",_xlfn.XLOOKUP($B$19,PROCESOS,'MATRIZ REQUISITOS ISO'!F$7:F$14,"")) | I29: =IF($B29="","",_xlfn.XLOOKUP($B$19,PROCESOS,'MATRIZ REQUISITOS ISO'!G$7:G$14,"")) | J29: =IF($B29="","",_xlfn.XLOOKUP($B$19,PROCESOS,'MATRIZ REQUISITOS ISO'!H$7:H$14,"")) | K29: =IF($B29="","",_xlfn.XLOOKUP($B$19,PROCESOS,'MATRIZ REQUISITOS ISO'!I$7:I$14,"")) | L29: =IF($B29="","",_xlfn.XLOOKUP($B$19,PROCESOS,'MATRIZ REQUISITOS ISO'!J$7:J$14,"")) | M29: =IF($B29="","",_xlfn.XLOOKUP($B$19,PROCESOS,'MATRIZ REQUISITOS ISO'!K$7:K$14,"")) | ... AG29: =IF($B29="","",_xlfn.XLOOKUP($B$19,PROCESOS,'MATRIZ REQUISITOS ISO'!AE$7:AE$14,"")) | AH29: =$B$19 -> Mantenimiento_y_Calibración
F30: =IF($B30="","",_xlfn.XLOOKUP($B$19,PROCESOS,'MATRIZ REQUISITOS ISO'!D$7:D$14,"")) | G30: =IF($B30="","",_xlfn.XLOOKUP($B$19,PROCESOS,'MATRIZ REQUISITOS ISO'!E$7:E$14,"")) | H30: =IF($B30="","",_xlfn.XLOOKUP($B$19,PROCESOS,'MATRIZ REQUISITOS ISO'!F$7:F$14,"")) | I30: =IF($B30="","",_xlfn.XLOOKUP($B$19,PROCESOS,'MATRIZ REQUISITOS ISO'!G$7:G$14,"")) | J30: =IF($B30="","",_xlfn.XLOOKUP($B$19,PROCESOS,'MATRIZ REQUISITOS ISO'!H$7:H$14,"")) | K30: =IF($B30="","",_xlfn.XLOOKUP($B$19,PROCESOS,'MATRIZ REQUISITOS ISO'!I$7:I$14,"")) | L30: =IF($B30="","",_xlfn.XLOOKUP($B$19,PROCESOS,'MATRIZ REQUISITOS ISO'!J$7:J$14,"")) | M30: =IF($B30="","",_xlfn.XLOOKUP($B$19,PROCESOS,'MATRIZ REQUISITOS ISO'!K$7:K$14,"")) | ... AG30: =IF($B30="","",_xlfn.XLOOKUP($B$19,PROCESOS,'MATRIZ REQUISITOS ISO'!AE$7:AE$14,"")) | AH30: =$B$19 -> Mantenimiento_y_Calibración
F31: =IF($B31="","",_xlfn.XLOOKUP($B$19,PROCESOS,'MATRIZ REQUISITOS ISO'!D$7:D$14,"")) | G31: =IF($B31="","",_xlfn.XLOOKUP($B$19,PROCESOS,'MATRIZ REQUISITOS ISO'!E$7:E$14,"")) | H31: =IF($B31="","",_xlfn.XLOOKUP($B$19,PROCESOS,'MATRIZ REQUISITOS ISO'!F$7:F$14,"")) | I31: =IF($B31="","",_xlfn.XLOOKUP($B$19,PROCESOS,'MATRIZ REQUISITOS ISO'!G$7:G$14,"")) | J31: =IF($B31="","",_xlfn.XLOOKUP($B$19,PROCESOS,'MATRIZ REQUISITOS ISO'!H$7:H$14,"")) | K31: =IF($B31="","",_xlfn.XLOOKUP($B$19,PROCESOS,'MATRIZ REQUISITOS ISO'!I$7:I$14,"")) | L31: =IF($B31="","",_xlfn.XLOOKUP($B$19,PROCESOS,'MATRIZ REQUISITOS ISO'!J$7:J$14,"")) | M31: =IF($B31="","",_xlfn.XLOOKUP($B$19,PROCESOS,'MATRIZ REQUISITOS ISO'!K$7:K$14,"")) | ... AG31: =IF($B31="","",_xlfn.XLOOKUP($B$19,PROCESOS,'MATRIZ REQUISITOS ISO'!AE$7:AE$14,"")) | AH31: =$B$19 -> Mantenimiento_y_Calibración
B32: Comercialización | E32: REQUISITOS NORMA ISO 9001/2015
B33: ÁREAS QUE INTEGRAN EL PROCESO: | C33: Dirección: | D33: Procedimientos involucrados: | E33: participación DIRECTA (D) INDIRECTA (I) | F33: 4.1 | G33: 4.2 | H33: 4.3 | I33: 4.4 | J33: 5.1 | K33: 5.2 | L33: 5.3 | M33: 6.1 | N33: 6.2 | O33: 6.3 | P33: 7.1 | Q33: 7.2 | R33: 7.3 | S33: 7.4 | T33: 7.5 | U33: 8.1 | V33: 8.2 | W33: 8.3 | X33: 8.4 | Y33: 8.5 | Z33: 8.6 | AA33: 8.7 | AB33: 9.1 | AC33: 9.2 | AD33: 9.3 | AE33: 10.1 | AF33: 10.2 | AG33: 10.3 | AH33: CÓDIGO 1
B34: Atención Ciudadana | C34: Comercial | D34: OOMPAC-01 OOMPAC-02 | F34: =IF($B34="","",_xlfn.XLOOKUP($B$32,PROCESOS,'MATRIZ REQUISITOS ISO'!D$7:D$14,"")) -> 0 | G34: =IF($B34="","",_xlfn.XLOOKUP($B$32,PROCESOS,'MATRIZ REQUISITOS ISO'!E$7:E$14,"")) -> 4 | H34: =IF($B34="","",_xlfn.XLOOKUP($B$32,PROCESOS,'MATRIZ REQUISITOS ISO'!F$7:F$14,"")) -> 0 | I34: =IF($B34="","",_xlfn.XLOOKUP($B$32,PROCESOS,'MATRIZ REQUISITOS ISO'!G$7:G$14,"")) -> 4 | J34: =IF($B34="","",_xlfn.XLOOKUP($B$32,PROCESOS,'MATRIZ REQUISITOS ISO'!H$7:H$14,"")) -> 0 | K34: =IF($B34="","",_xlfn.XLOOKUP($B$32,PROCESOS,'MATRIZ REQUISITOS ISO'!I$7:I$14,"")) -> 0 | L34: =IF($B34="","",_xlfn.XLOOKUP($B$32,PROCESOS,'MATRIZ REQUISITOS ISO'!J$7:J$14,"")) -> 0 | M34: =IF($B34="","",_xlfn.XLOOKUP($B$32,PROCESOS,'MATRIZ REQUISITOS ISO'!K$7:K$14,"")) -> 4 | ... AG34: =IF($B34="","",_xlfn.XLOOKUP($B$32,PROCESOS,'MATRIZ REQUISITOS ISO'!AE$7:AE$14,"")) -> 4 | AH34: =$B$32 -> Comercialización
B35: Contratos y Servicios | C35: Comercial | D35: OOMPGC-01 OOMPGC-03 OOMPGC-04 OOMPGC-05 OOMPGC-06 OOMPGC-07 OOMPGC-08 OOMPGC-09 OOMPGC-11 OOMPGC-12 OOMPGC-16 OOMPGC-17 OOMPGC-18 OOMPGC-22 OOMPGC-39 OOMPGC-40 OOMPGC-41 OOMIGC-01 OOMIGC-02 OOMIGC-03 OOMIGC-04 | F35: =IF($B35="","",_xlfn.XLOOKUP($B$32,PROCESOS,'MATRIZ REQUISITOS ISO'!D$7:D$14,"")) -> 0 | G35: =IF($B35="","",_xlfn.XLOOKUP($B$32,PROCESOS,'MATRIZ REQUISITOS ISO'!E$7:E$14,"")) -> 4 | H35: =IF($B35="","",_xlfn.XLOOKUP($B$32,PROCESOS,'MATRIZ REQUISITOS ISO'!F$7:F$14,"")) -> 0 | I35: =IF($B35="","",_xlfn.XLOOKUP($B$32,PROCESOS,'MATRIZ REQUISITOS ISO'!G$7:G$14,"")) -> 4 | J35: =IF($B35="","",_xlfn.XLOOKUP($B$32,PROCESOS,'MATRIZ REQUISITOS ISO'!H$7:H$14,"")) -> 0 | K35: =IF($B35="","",_xlfn.XLOOKUP($B$32,PROCESOS,'MATRIZ REQUISITOS ISO'!I$7:I$14,"")) -> 0 | L35: =IF($B35="","",_xlfn.XLOOKUP($B$32,PROCESOS,'MATRIZ REQUISITOS ISO'!J$7:J$14,"")) -> 0 | M35: =IF($B35="","",_xlfn.XLOOKUP($B$32,PROCESOS,'MATRIZ REQUISITOS ISO'!K$7:K$14,"")) -> 4 | ... AG35: =IF($B35="","",_xlfn.XLOOKUP($B$32,PROCESOS,'MATRIZ REQUISITOS ISO'!AE$7:AE$14,"")) -> 4 | AH35: =$B$32 -> Comercialización
B36: Control y Servicios | C36: Comercial | D36: OOMPCS-01 OOMPCS-02 OOMPCS-05 OOMPCS-09 OOMPCS-10 OOMICS-01 OOMICS-02 OOMICS-03 OOMICS-04 OOMICS-05 | F36: =IF($B36="","",_xlfn.XLOOKUP($B$32,PROCESOS,'MATRIZ REQUISITOS ISO'!D$7:D$14,"")) -> 0 | G36: =IF($B36="","",_xlfn.XLOOKUP($B$32,PROCESOS,'MATRIZ REQUISITOS ISO'!E$7:E$14,"")) -> 4 | H36: =IF($B36="","",_xlfn.XLOOKUP($B$32,PROCESOS,'MATRIZ REQUISITOS ISO'!F$7:F$14,"")) -> 0 | I36: =IF($B36="","",_xlfn.XLOOKUP($B$32,PROCESOS,'MATRIZ REQUISITOS ISO'!G$7:G$14,"")) -> 4 | J36: =IF($B36="","",_xlfn.XLOOKUP($B$32,PROCESOS,'MATRIZ REQUISITOS ISO'!H$7:H$14,"")) -> 0 | K36: =IF($B36="","",_xlfn.XLOOKUP($B$32,PROCESOS,'MATRIZ REQUISITOS ISO'!I$7:I$14,"")) -> 0 | L36: =IF($B36="","",_xlfn.XLOOKUP($B$32,PROCESOS,'MATRIZ REQUISITOS ISO'!J$7:J$14,"")) -> 0 | M36: =IF($B36="","",_xlfn.XLOOKUP($B$32,PROCESOS,'MATRIZ REQUISITOS ISO'!K$7:K$14,"")) -> 4 | ... AG36: =IF($B36="","",_xlfn.XLOOKUP($B$32,PROCESOS,'MATRIZ REQUISITOS ISO'!AE$7:AE$14,"")) -> 4 | AH36: =$B$32 -> Comercialización
B37: Línea OOMAPASC | C37: General | D37: OOMPAT-08 OOMPAT-13 | F37: =IF($B37="","",_xlfn.XLOOKUP($B$32,PROCESOS,'MATRIZ REQUISITOS ISO'!D$7:D$14,"")) -> 0 | G37: =IF($B37="","",_xlfn.XLOOKUP($B$32,PROCESOS,'MATRIZ REQUISITOS ISO'!E$7:E$14,"")) -> 4 | H37: =IF($B37="","",_xlfn.XLOOKUP($B$32,PROCESOS,'MATRIZ REQUISITOS ISO'!F$7:F$14,"")) -> 0 | I37: =IF($B37="","",_xlfn.XLOOKUP($B$32,PROCESOS,'MATRIZ REQUISITOS ISO'!G$7:G$14,"")) -> 4 | J37: =IF($B37="","",_xlfn.XLOOKUP($B$32,PROCESOS,'MATRIZ REQUISITOS ISO'!H$7:H$14,"")) -> 0 | K37: =IF($B37="","",_xlfn.XLOOKUP($B$32,PROCESOS,'MATRIZ REQUISITOS ISO'!I$7:I$14,"")) -> 0 | L37: =IF($B37="","",_xlfn.XLOOKUP($B$32,PROCESOS,'MATRIZ REQUISITOS ISO'!J$7:J$14,"")) -> 0 | M37: =IF($B37="","",_xlfn.XLOOKUP($B$32,PROCESOS,'MATRIZ REQUISITOS ISO'!K$7:K$14,"")) -> 4 | ... AG37: =IF($B37="","",_xlfn.XLOOKUP($B$32,PROCESOS,'MATRIZ REQUISITOS ISO'!AE$7:AE$14,"")) -> 4 | AH37: =$B$32 -> Comercialización
B38: Padrón de Usuarios | C38: Comercial | D38: OOMPGP-01 OOMPGP-02 OOMPGP-04 OOMPGP-06 OOMPGP-07 OOMPGP-08 | F38: =IF($B38="","",_xlfn.XLOOKUP($B$32,PROCESOS,'MATRIZ REQUISITOS ISO'!D$7:D$14,"")) -> 0 | G38: =IF($B38="","",_xlfn.XLOOKUP($B$32,PROCESOS,'MATRIZ REQUISITOS ISO'!E$7:E$14,"")) -> 4 | H38: =IF($B38="","",_xlfn.XLOOKUP($B$32,PROCESOS,'MATRIZ REQUISITOS ISO'!F$7:F$14,"")) -> 0 | I38: =IF($B38="","",_xlfn.XLOOKUP($B$32,PROCESOS,'MATRIZ REQUISITOS ISO'!G$7:G$14,"")) -> 4 | J38: =IF($B38="","",_xlfn.XLOOKUP($B$32,PROCESOS,'MATRIZ REQUISITOS ISO'!H$7:H$14,"")) -> 0 | K38: =IF($B38="","",_xlfn.XLOOKUP($B$32,PROCESOS,'MATRIZ REQUISITOS ISO'!I$7:I$14,"")) -> 0 | L38: =IF($B38="","",_xlfn.XLOOKUP($B$32,PROCESOS,'MATRIZ REQUISITOS ISO'!J$7:J$14,"")) -> 0 | M38: =IF($B38="","",_xlfn.XLOOKUP($B$32,PROCESOS,'MATRIZ REQUISITOS ISO'!K$7:K$14,"")) -> 4 | ... AG38: =IF($B38="","",_xlfn.XLOOKUP($B$32,PROCESOS,'MATRIZ REQUISITOS ISO'!AE$7:AE$14,"")) -> 4 | AH38: =$B$32 -> Comercialización
B39: Programas Sociales | C39: Programas Sociales y cultura del Agua | D39: OOMPPS-01 | F39: =IF($B39="","",_xlfn.XLOOKUP($B$32,PROCESOS,'MATRIZ REQUISITOS ISO'!D$7:D$14,"")) -> 0 | G39: =IF($B39="","",_xlfn.XLOOKUP($B$32,PROCESOS,'MATRIZ REQUISITOS ISO'!E$7:E$14,"")) -> 4 | H39: =IF($B39="","",_xlfn.XLOOKUP($B$32,PROCESOS,'MATRIZ REQUISITOS ISO'!F$7:F$14,"")) -> 0 | I39: =IF($B39="","",_xlfn.XLOOKUP($B$32,PROCESOS,'MATRIZ REQUISITOS ISO'!G$7:G$14,"")) -> 4 | J39: =IF($B39="","",_xlfn.XLOOKUP($B$32,PROCESOS,'MATRIZ REQUISITOS ISO'!H$7:H$14,"")) -> 0 | K39: =IF($B39="","",_xlfn.XLOOKUP($B$32,PROCESOS,'MATRIZ REQUISITOS ISO'!I$7:I$14,"")) -> 0 | L39: =IF($B39="","",_xlfn.XLOOKUP($B$32,PROCESOS,'MATRIZ REQUISITOS ISO'!J$7:J$14,"")) -> 0 | M39: =IF($B39="","",_xlfn.XLOOKUP($B$32,PROCESOS,'MATRIZ REQUISITOS ISO'!K$7:K$14,"")) -> 4 | ... AG39: =IF($B39="","",_xlfn.XLOOKUP($B$32,PROCESOS,'MATRIZ REQUISITOS ISO'!AE$7:AE$14,"")) -> 4 | AH39: =$B$32 -> Comercialización
B40: Suburbano Comercial | C40: Comercial | D40: OOMPAS-01 OOMPAS-02 OOMPAS-03 OOMPAS-04 OOMPAS-05 OOMPAS-06 OOMPAS-07 OOMPAS-08 OOMPAS-09 OOMPAS-10 OOMPAS-11 OOMPAS-12 OOMPAS-13 OOMPAS-14 OOMPAS-16 OOMPAS-18 OOMPAS-19 | F40: =IF($B40="","",_xlfn.XLOOKUP($B$32,PROCESOS,'MATRIZ REQUISITOS ISO'!D$7:D$14,"")) -> 0 | G40: =IF($B40="","",_xlfn.XLOOKUP($B$32,PROCESOS,'MATRIZ REQUISITOS ISO'!E$7:E$14,"")) -> 4 | H40: =IF($B40="","",_xlfn.XLOOKUP($B$32,PROCESOS,'MATRIZ REQUISITOS ISO'!F$7:F$14,"")) -> 0 | I40: =IF($B40="","",_xlfn.XLOOKUP($B$32,PROCESOS,'MATRIZ REQUISITOS ISO'!G$7:G$14,"")) -> 4 | J40: =IF($B40="","",_xlfn.XLOOKUP($B$32,PROCESOS,'MATRIZ REQUISITOS ISO'!H$7:H$14,"")) -> 0 | K40: =IF($B40="","",_xlfn.XLOOKUP($B$32,PROCESOS,'MATRIZ REQUISITOS ISO'!I$7:I$14,"")) -> 0 | L40: =IF($B40="","",_xlfn.XLOOKUP($B$32,PROCESOS,'MATRIZ REQUISITOS ISO'!J$7:J$14,"")) -> 0 | M40: =IF($B40="","",_xlfn.XLOOKUP($B$32,PROCESOS,'MATRIZ REQUISITOS ISO'!K$7:K$14,"")) -> 4 | ... AG40: =IF($B40="","",_xlfn.XLOOKUP($B$32,PROCESOS,'MATRIZ REQUISITOS ISO'!AE$7:AE$14,"")) -> 4 | AH40: =$B$32 -> Comercialización
B41: Trabajo Social | C41: Programas Sociales y Desarrollo Institucional | D41: OOMPSS-01 OOMPSS-03 | F41: =IF($B41="","",_xlfn.XLOOKUP($B$32,PROCESOS,'MATRIZ REQUISITOS ISO'!D$7:D$14,"")) -> 0 | G41: =IF($B41="","",_xlfn.XLOOKUP($B$32,PROCESOS,'MATRIZ REQUISITOS ISO'!E$7:E$14,"")) -> 4 | H41: =IF($B41="","",_xlfn.XLOOKUP($B$32,PROCESOS,'MATRIZ REQUISITOS ISO'!F$7:F$14,"")) -> 0 | I41: =IF($B41="","",_xlfn.XLOOKUP($B$32,PROCESOS,'MATRIZ REQUISITOS ISO'!G$7:G$14,"")) -> 4 | J41: =IF($B41="","",_xlfn.XLOOKUP($B$32,PROCESOS,'MATRIZ REQUISITOS ISO'!H$7:H$14,"")) -> 0 | K41: =IF($B41="","",_xlfn.XLOOKUP($B$32,PROCESOS,'MATRIZ REQUISITOS ISO'!I$7:I$14,"")) -> 0 | L41: =IF($B41="","",_xlfn.XLOOKUP($B$32,PROCESOS,'MATRIZ REQUISITOS ISO'!J$7:J$14,"")) -> 0 | M41: =IF($B41="","",_xlfn.XLOOKUP($B$32,PROCESOS,'MATRIZ REQUISITOS ISO'!K$7:K$14,"")) -> 4 | ... AG41: =IF($B41="","",_xlfn.XLOOKUP($B$32,PROCESOS,'MATRIZ REQUISITOS ISO'!AE$7:AE$14,"")) -> 4 | AH41: =$B$32 -> Comercialización
B42: Verificación y Lectura | C42: Comercial | D42: OOMPVL-02 OOMPVL-03 OOMPVL-06 OOMPVL-07 OOMPVL-09 | F42: =IF($B42="","",_xlfn.XLOOKUP($B$32,PROCESOS,'MATRIZ REQUISITOS ISO'!D$7:D$14,"")) -> 0 | G42: =IF($B42="","",_xlfn.XLOOKUP($B$32,PROCESOS,'MATRIZ REQUISITOS ISO'!E$7:E$14,"")) -> 4 | H42: =IF($B42="","",_xlfn.XLOOKUP($B$32,PROCESOS,'MATRIZ REQUISITOS ISO'!F$7:F$14,"")) -> 0 | I42: =IF($B42="","",_xlfn.XLOOKUP($B$32,PROCESOS,'MATRIZ REQUISITOS ISO'!G$7:G$14,"")) -> 4 | J42: =IF($B42="","",_xlfn.XLOOKUP($B$32,PROCESOS,'MATRIZ REQUISITOS ISO'!H$7:H$14,"")) -> 0 | K42: =IF($B42="","",_xlfn.XLOOKUP($B$32,PROCESOS,'MATRIZ REQUISITOS ISO'!I$7:I$14,"")) -> 0 | L42: =IF($B42="","",_xlfn.XLOOKUP($B$32,PROCESOS,'MATRIZ REQUISITOS ISO'!J$7:J$14,"")) -> 0 | M42: =IF($B42="","",_xlfn.XLOOKUP($B$32,PROCESOS,'MATRIZ REQUISITOS ISO'!K$7:K$14,"")) -> 4 | ... AG42: =IF($B42="","",_xlfn.XLOOKUP($B$32,PROCESOS,'MATRIZ REQUISITOS ISO'!AE$7:AE$14,"")) -> 4 | AH42: =$B$32 -> Comercialización
F43: =IF($B43="","",_xlfn.XLOOKUP($B$32,PROCESOS,'MATRIZ REQUISITOS ISO'!D$7:D$14,"")) | G43: =IF($B43="","",_xlfn.XLOOKUP($B$32,PROCESOS,'MATRIZ REQUISITOS ISO'!E$7:E$14,"")) | H43: =IF($B43="","",_xlfn.XLOOKUP($B$32,PROCESOS,'MATRIZ REQUISITOS ISO'!F$7:F$14,"")) | I43: =IF($B43="","",_xlfn.XLOOKUP($B$32,PROCESOS,'MATRIZ REQUISITOS ISO'!G$7:G$14,"")) | J43: =IF($B43="","",_xlfn.XLOOKUP($B$32,PROCESOS,'MATRIZ REQUISITOS ISO'!H$7:H$14,"")) | K43: =IF($B43="","",_xlfn.XLOOKUP($B$32,PROCESOS,'MATRIZ REQUISITOS ISO'!I$7:I$14,"")) | L43: =IF($B43="","",_xlfn.XLOOKUP($B$32,PROCESOS,'MATRIZ REQUISITOS ISO'!J$7:J$14,"")) | M43: =IF($B43="","",_xlfn.XLOOKUP($B$32,PROCESOS,'MATRIZ REQUISITOS ISO'!K$7:K$14,"")) | ... AG43: =IF($B43="","",_xlfn.XLOOKUP($B$32,PROCESOS,'MATRIZ REQUISITOS ISO'!AE$7:AE$14,"")) | AH43: =$B$32 -> Comercialización
F44: =IF($B44="","",_xlfn.XLOOKUP($B$32,PROCESOS,'MATRIZ REQUISITOS ISO'!D$7:D$14,"")) | G44: =IF($B44="","",_xlfn.XLOOKUP($B$32,PROCESOS,'MATRIZ REQUISITOS ISO'!E$7:E$14,"")) | H44: =IF($B44="","",_xlfn.XLOOKUP($B$32,PROCESOS,'MATRIZ REQUISITOS ISO'!F$7:F$14,"")) | I44: =IF($B44="","",_xlfn.XLOOKUP($B$32,PROCESOS,'MATRIZ REQUISITOS ISO'!G$7:G$14,"")) | J44: =IF($B44="","",_xlfn.XLOOKUP($B$32,PROCESOS,'MATRIZ REQUISITOS ISO'!H$7:H$14,"")) | K44: =IF($B44="","",_xlfn.XLOOKUP($B$32,PROCESOS,'MATRIZ REQUISITOS ISO'!I$7:I$14,"")) | L44: =IF($B44="","",_xlfn.XLOOKUP($B$32,PROCESOS,'MATRIZ REQUISITOS ISO'!J$7:J$14,"")) | M44: =IF($B44="","",_xlfn.XLOOKUP($B$32,PROCESOS,'MATRIZ REQUISITOS ISO'!K$7:K$14,"")) | ... AG44: =IF($B44="","",_xlfn.XLOOKUP($B$32,PROCESOS,'MATRIZ REQUISITOS ISO'!AE$7:AE$14,"")) | AH44: =$B$32 -> Comercialización
B45: Producción | E45: REQUISITOS NORMA ISO 9001/2015
B46: ÁREAS QUE INTEGRAN EL PROCESO: | C46: Dirección: | D46: Procedimientos involucrados: | E46: participación DIRECTA (D) INDIRECTA (I) | F46: 4.1 | G46: 4.2 | H46: 4.3 | I46: 4.4 | J46: 5.1 | K46: 5.2 | L46: 5.3 | M46: 6.1 | N46: 6.2 | O46: 6.3 | P46: 7.1 | Q46: 7.2 | R46: 7.3 | S46: 7.4 | T46: 7.5 | U46: 8.1 | V46: 8.2 | W46: 8.3 | X46: 8.4 | Y46: 8.5 | Z46: 8.6 | AA46: 8.7 | AB46: 9.1 | AC46: 9.2 | AD46: 9.3 | AE46: 10.1 | AF46: 10.2 | AG46: 10.3 | AH46: CÓDIGO 1
B47: Alcantarillado y Saneamiento | C47: Técnica | D47: OOMPGS-04 | F47: =IF($B47="","",_xlfn.XLOOKUP($B$45,PROCESOS,'MATRIZ REQUISITOS ISO'!D$7:D$14,"")) -> 0 | G47: =IF($B47="","",_xlfn.XLOOKUP($B$45,PROCESOS,'MATRIZ REQUISITOS ISO'!E$7:E$14,"")) -> 5 | H47: =IF($B47="","",_xlfn.XLOOKUP($B$45,PROCESOS,'MATRIZ REQUISITOS ISO'!F$7:F$14,"")) -> 0 | I47: =IF($B47="","",_xlfn.XLOOKUP($B$45,PROCESOS,'MATRIZ REQUISITOS ISO'!G$7:G$14,"")) -> 5 | J47: =IF($B47="","",_xlfn.XLOOKUP($B$45,PROCESOS,'MATRIZ REQUISITOS ISO'!H$7:H$14,"")) -> 0 | K47: =IF($B47="","",_xlfn.XLOOKUP($B$45,PROCESOS,'MATRIZ REQUISITOS ISO'!I$7:I$14,"")) -> 0 | L47: =IF($B47="","",_xlfn.XLOOKUP($B$45,PROCESOS,'MATRIZ REQUISITOS ISO'!J$7:J$14,"")) -> 0 | M47: =IF($B47="","",_xlfn.XLOOKUP($B$45,PROCESOS,'MATRIZ REQUISITOS ISO'!K$7:K$14,"")) -> 5 | ... AG47: =IF($B47="","",_xlfn.XLOOKUP($B$45,PROCESOS,'MATRIZ REQUISITOS ISO'!AE$7:AE$14,"")) -> 5 | AH47: =$B$45 -> Producción
B48: Control de Calidad | C48: Técnica | D48: OOMPCC-01 OOMPCC-04 OOMPCC-05 OOMPCC-06 OOMPCC-08 OOMPCC-09 OOMPCC-10 OOMPCC-11 OOMPCC-12 OOMPCC-13 OOMPCC-14 OOMPCC-15 OOMPCC-16 OOMPCC-17 OOMPCC-18 OOMPCC-19 OOMPCC-20 OOMPCC-26 OOMPCC-35 OOMPCC-36 OOMPCC-37 OOMPCC-38 OOMPCC-39 OOMPCC-41 OOMPCC-42 OOMPCC-46 OOMPCC-47 OOMPCC-53 OOMPCC-54 OOMPCC-55 OOMPCC-56 OOMPCC-62 OOMPCC-63 OOMPCC-64 OOMPCC-65 OOMPCC-66 OOMPCC-67 OOMPCC-68 OOMPCC-69 OOMPCC-70 OOMPCC-71 OOMPCC-72 OOMPCC-73 OOMPCC-74 OOMPCC-75 OOMPCC-76 OOMPCC-77 OOMPCC-80 OOMPCC-82 OOMPCC-83 OOMPCC-84 OOMPCC-85 OOMPCC-86 | F48: =IF($B48="","",_xlfn.XLOOKUP($B$45,PROCESOS,'MATRIZ REQUISITOS ISO'!D$7:D$14,"")) -> 0 | G48: =IF($B48="","",_xlfn.XLOOKUP($B$45,PROCESOS,'MATRIZ REQUISITOS ISO'!E$7:E$14,"")) -> 5 | H48: =IF($B48="","",_xlfn.XLOOKUP($B$45,PROCESOS,'MATRIZ REQUISITOS ISO'!F$7:F$14,"")) -> 0 | I48: =IF($B48="","",_xlfn.XLOOKUP($B$45,PROCESOS,'MATRIZ REQUISITOS ISO'!G$7:G$14,"")) -> 5 | J48: =IF($B48="","",_xlfn.XLOOKUP($B$45,PROCESOS,'MATRIZ REQUISITOS ISO'!H$7:H$14,"")) -> 0 | K48: =IF($B48="","",_xlfn.XLOOKUP($B$45,PROCESOS,'MATRIZ REQUISITOS ISO'!I$7:I$14,"")) -> 0 | L48: =IF($B48="","",_xlfn.XLOOKUP($B$45,PROCESOS,'MATRIZ REQUISITOS ISO'!J$7:J$14,"")) -> 0 | M48: =IF($B48="","",_xlfn.XLOOKUP($B$45,PROCESOS,'MATRIZ REQUISITOS ISO'!K$7:K$14,"")) -> 5 | ... AG48: =IF($B48="","",_xlfn.XLOOKUP($B$45,PROCESOS,'MATRIZ REQUISITOS ISO'!AE$7:AE$14,"")) -> 5 | AH48: =$B$45 -> Producción
B49: Plantas Potabilizadoras | C49: Técnica | D49: OOMPPP-01 OOMPPP-02 OOMPPP-03 OOMPPP-04 OOMPPP-05 OOMPPP-06 OOMPPP-07 OOMPPP-08 OOMPPP-09 OOMPPP-10 OOMPPP-11 OOMPPP-12 OOMPPP-13 OOMPPP-15 OOMPPP-16 OOMPPP-17 OOMPPP-18 OOMPPP-19 OOMPPP-20 OOMPPP-21 OOMPPP-22 OOMPPP-23 OOMPPP-24 OOMPPP-25 OOMPPP-26 OOMPPP-27 OOMPPP-28 OOMPPP-33 OOMPPP-36 | F49: =IF($B49="","",_xlfn.XLOOKUP($B$45,PROCESOS,'MATRIZ REQUISITOS ISO'!D$7:D$14,"")) -> 0 | G49: =IF($B49="","",_xlfn.XLOOKUP($B$45,PROCESOS,'MATRIZ REQUISITOS ISO'!E$7:E$14,"")) -> 5 | H49: =IF($B49="","",_xlfn.XLOOKUP($B$45,PROCESOS,'MATRIZ REQUISITOS ISO'!F$7:F$14,"")) -> 0 | I49: =IF($B49="","",_xlfn.XLOOKUP($B$45,PROCESOS,'MATRIZ REQUISITOS ISO'!G$7:G$14,"")) -> 5 | J49: =IF($B49="","",_xlfn.XLOOKUP($B$45,PROCESOS,'MATRIZ REQUISITOS ISO'!H$7:H$14,"")) -> 0 | K49: =IF($B49="","",_xlfn.XLOOKUP($B$45,PROCESOS,'MATRIZ REQUISITOS ISO'!I$7:I$14,"")) -> 0 | L49: =IF($B49="","",_xlfn.XLOOKUP($B$45,PROCESOS,'MATRIZ REQUISITOS ISO'!J$7:J$14,"")) -> 0 | M49: =IF($B49="","",_xlfn.XLOOKUP($B$45,PROCESOS,'MATRIZ REQUISITOS ISO'!K$7:K$14,"")) -> 5 | ... AG49: =IF($B49="","",_xlfn.XLOOKUP($B$45,PROCESOS,'MATRIZ REQUISITOS ISO'!AE$7:AE$14,"")) -> 5 | AH49: =$B$45 -> Producción
B50: Suburbano Técnico | C50: Técnica | D50: OOMPTS-01 OOMPTS-02 OOMPTS-09 OOMPTS-14 OOMPTS-17 OOMPTS-19 OOMPTS-21 | F50: =IF($B50="","",_xlfn.XLOOKUP($B$45,PROCESOS,'MATRIZ REQUISITOS ISO'!D$7:D$14,"")) -> 0 | G50: =IF($B50="","",_xlfn.XLOOKUP($B$45,PROCESOS,'MATRIZ REQUISITOS ISO'!E$7:E$14,"")) -> 5 | H50: =IF($B50="","",_xlfn.XLOOKUP($B$45,PROCESOS,'MATRIZ REQUISITOS ISO'!F$7:F$14,"")) -> 0 | I50: =IF($B50="","",_xlfn.XLOOKUP($B$45,PROCESOS,'MATRIZ REQUISITOS ISO'!G$7:G$14,"")) -> 5 | J50: =IF($B50="","",_xlfn.XLOOKUP($B$45,PROCESOS,'MATRIZ REQUISITOS ISO'!H$7:H$14,"")) -> 0 | K50: =IF($B50="","",_xlfn.XLOOKUP($B$45,PROCESOS,'MATRIZ REQUISITOS ISO'!I$7:I$14,"")) -> 0 | L50: =IF($B50="","",_xlfn.XLOOKUP($B$45,PROCESOS,'MATRIZ REQUISITOS ISO'!J$7:J$14,"")) -> 0 | M50: =IF($B50="","",_xlfn.XLOOKUP($B$45,PROCESOS,'MATRIZ REQUISITOS ISO'!K$7:K$14,"")) -> 5 | ... AG50: =IF($B50="","",_xlfn.XLOOKUP($B$45,PROCESOS,'MATRIZ REQUISITOS ISO'!AE$7:AE$14,"")) -> 5 | AH50: =$B$45 -> Producción
F51: =IF($B51="","",_xlfn.XLOOKUP($B$45,PROCESOS,'MATRIZ REQUISITOS ISO'!D$7:D$14,"")) | G51: =IF($B51="","",_xlfn.XLOOKUP($B$45,PROCESOS,'MATRIZ REQUISITOS ISO'!E$7:E$14,"")) | H51: =IF($B51="","",_xlfn.XLOOKUP($B$45,PROCESOS,'MATRIZ REQUISITOS ISO'!F$7:F$14,"")) | I51: =IF($B51="","",_xlfn.XLOOKUP($B$45,PROCESOS,'MATRIZ REQUISITOS ISO'!G$7:G$14,"")) | J51: =IF($B51="","",_xlfn.XLOOKUP($B$45,PROCESOS,'MATRIZ REQUISITOS ISO'!H$7:H$14,"")) | K51: =IF($B51="","",_xlfn.XLOOKUP($B$45,PROCESOS,'MATRIZ REQUISITOS ISO'!I$7:I$14,"")) | L51: =IF($B51="","",_xlfn.XLOOKUP($B$45,PROCESOS,'MATRIZ REQUISITOS ISO'!J$7:J$14,"")) | M51: =IF($B51="","",_xlfn.XLOOKUP($B$45,PROCESOS,'MATRIZ REQUISITOS ISO'!K$7:K$14,"")) | ... AG51: =IF($B51="","",_xlfn.XLOOKUP($B$45,PROCESOS,'MATRIZ REQUISITOS ISO'!AE$7:AE$14,"")) | AH51: =$B$45 -> Producción
F52: =IF($B52="","",_xlfn.XLOOKUP($B$45,PROCESOS,'MATRIZ REQUISITOS ISO'!D$7:D$14,"")) | G52: =IF($B52="","",_xlfn.XLOOKUP($B$45,PROCESOS,'MATRIZ REQUISITOS ISO'!E$7:E$14,"")) | H52: =IF($B52="","",_xlfn.XLOOKUP($B$45,PROCESOS,'MATRIZ REQUISITOS ISO'!F$7:F$14,"")) | I52: =IF($B52="","",_xlfn.XLOOKUP($B$45,PROCESOS,'MATRIZ REQUISITOS ISO'!G$7:G$14,"")) | J52: =IF($B52="","",_xlfn.XLOOKUP($B$45,PROCESOS,'MATRIZ REQUISITOS ISO'!H$7:H$14,"")) | K52: =IF($B52="","",_xlfn.XLOOKUP($B$45,PROCESOS,'MATRIZ REQUISITOS ISO'!I$7:I$14,"")) | L52: =IF($B52="","",_xlfn.XLOOKUP($B$45,PROCESOS,'MATRIZ REQUISITOS ISO'!J$7:J$14,"")) | M52: =IF($B52="","",_xlfn.XLOOKUP($B$45,PROCESOS,'MATRIZ REQUISITOS ISO'!K$7:K$14,"")) | ... AG52: =IF($B52="","",_xlfn.XLOOKUP($B$45,PROCESOS,'MATRIZ REQUISITOS ISO'!AE$7:AE$14,"")) | AH52: =$B$45 -> Producción
F53: =IF($B53="","",_xlfn.XLOOKUP($B$45,PROCESOS,'MATRIZ REQUISITOS ISO'!D$7:D$14,"")) | G53: =IF($B53="","",_xlfn.XLOOKUP($B$45,PROCESOS,'MATRIZ REQUISITOS ISO'!E$7:E$14,"")) | H53: =IF($B53="","",_xlfn.XLOOKUP($B$45,PROCESOS,'MATRIZ REQUISITOS ISO'!F$7:F$14,"")) | I53: =IF($B53="","",_xlfn.XLOOKUP($B$45,PROCESOS,'MATRIZ REQUISITOS ISO'!G$7:G$14,"")) | J53: =IF($B53="","",_xlfn.XLOOKUP($B$45,PROCESOS,'MATRIZ REQUISITOS ISO'!H$7:H$14,"")) | K53: =IF($B53="","",_xlfn.XLOOKUP($B$45,PROCESOS,'MATRIZ REQUISITOS ISO'!I$7:I$14,"")) | L53: =IF($B53="","",_xlfn.XLOOKUP($B$45,PROCESOS,'MATRIZ REQUISITOS ISO'!J$7:J$14,"")) | M53: =IF($B53="","",_xlfn.XLOOKUP($B$45,PROCESOS,'MATRIZ REQUISITOS ISO'!K$7:K$14,"")) | ... AG53: =IF($B53="","",_xlfn.XLOOKUP($B$45,PROCESOS,'MATRIZ REQUISITOS ISO'!AE$7:AE$14,"")) | AH53: =$B$45 -> Producción
B54: Medición_Análisis_y_Mejora | E54: REQUISITOS NORMA ISO 9001/2015
B55: ÁREAS QUE INTEGRAN EL PROCESO: | C55: Dirección: | D55: Procedimientos involucrados: | E55: participación DIRECTA (D) INDIRECTA (I) | F55: 4.1 | G55: 4.2 | H55: 4.3 | I55: 4.4 | J55: 5.1 | K55: 5.2 | L55: 5.3 | M55: 6.1 | N55: 6.2 | O55: 6.3 | P55: 7.1 | Q55: 7.2 | R55: 7.3 | S55: 7.4 | T55: 7.5 | U55: 8.1 | V55: 8.2 | W55: 8.3 | X55: 8.4 | Y55: 8.5 | Z55: 8.6 | AA55: 8.7 | AB55: 9.1 | AC55: 9.2 | AD55: 9.3 | AE55: 10.1 | AF55: 10.2 | AG55: 10.3 | AH55: CÓDIGO 1
B56: Alcantarillado y Saneamiento | C56: Técnica | D56: OOMPGS-01 OOMPGS-04 OOMPGS-06 | E56: I | F56: =IF($B56="","",_xlfn.XLOOKUP($B$54,PROCESOS,'MATRIZ REQUISITOS ISO'!D$7:D$14,"")) -> 6 | G56: =IF($B56="","",_xlfn.XLOOKUP($B$54,PROCESOS,'MATRIZ REQUISITOS ISO'!E$7:E$14,"")) -> 6 | H56: =IF($B56="","",_xlfn.XLOOKUP($B$54,PROCESOS,'MATRIZ REQUISITOS ISO'!F$7:F$14,"")) -> 0 | I56: =IF($B56="","",_xlfn.XLOOKUP($B$54,PROCESOS,'MATRIZ REQUISITOS ISO'!G$7:G$14,"")) -> 6 | J56: =IF($B56="","",_xlfn.XLOOKUP($B$54,PROCESOS,'MATRIZ REQUISITOS ISO'!H$7:H$14,"")) -> 0 | K56: =IF($B56="","",_xlfn.XLOOKUP($B$54,PROCESOS,'MATRIZ REQUISITOS ISO'!I$7:I$14,"")) -> 0 | L56: =IF($B56="","",_xlfn.XLOOKUP($B$54,PROCESOS,'MATRIZ REQUISITOS ISO'!J$7:J$14,"")) -> 0 | M56: =IF($B56="","",_xlfn.XLOOKUP($B$54,PROCESOS,'MATRIZ REQUISITOS ISO'!K$7:K$14,"")) -> 6 | ... AG56: =IF($B56="","",_xlfn.XLOOKUP($B$54,PROCESOS,'MATRIZ REQUISITOS ISO'!AE$7:AE$14,"")) -> 6 | AH56: =$B$54 -> Medición_Análisis_y_Mejora
B57: Atención Ciudadana | C57: Comercial | D57: OOMPAC-01 | E57: I | F57: =IF($B57="","",_xlfn.XLOOKUP($B$54,PROCESOS,'MATRIZ REQUISITOS ISO'!D$7:D$14,"")) -> 6 | G57: =IF($B57="","",_xlfn.XLOOKUP($B$54,PROCESOS,'MATRIZ REQUISITOS ISO'!E$7:E$14,"")) -> 6 | H57: =IF($B57="","",_xlfn.XLOOKUP($B$54,PROCESOS,'MATRIZ REQUISITOS ISO'!F$7:F$14,"")) -> 0 | I57: =IF($B57="","",_xlfn.XLOOKUP($B$54,PROCESOS,'MATRIZ REQUISITOS ISO'!G$7:G$14,"")) -> 6 | J57: =IF($B57="","",_xlfn.XLOOKUP($B$54,PROCESOS,'MATRIZ REQUISITOS ISO'!H$7:H$14,"")) -> 0 | K57: =IF($B57="","",_xlfn.XLOOKUP($B$54,PROCESOS,'MATRIZ REQUISITOS ISO'!I$7:I$14,"")) -> 0 | L57: =IF($B57="","",_xlfn.XLOOKUP($B$54,PROCESOS,'MATRIZ REQUISITOS ISO'!J$7:J$14,"")) -> 0 | M57: =IF($B57="","",_xlfn.XLOOKUP($B$54,PROCESOS,'MATRIZ REQUISITOS ISO'!K$7:K$14,"")) -> 6 | ... AG57: =IF($B57="","",_xlfn.XLOOKUP($B$54,PROCESOS,'MATRIZ REQUISITOS ISO'!AE$7:AE$14,"")) -> 6 | AH57: =$B$54 -> Medición_Análisis_y_Mejora
B58: Comunicación e Imagen Institucional | C58: Administrativa | D58: OOMPCI-01 OOMPCI-04 OOMPCI-06 | E58: I | F58: =IF($B58="","",_xlfn.XLOOKUP($B$54,PROCESOS,'MATRIZ REQUISITOS ISO'!D$7:D$14,"")) -> 6 | G58: =IF($B58="","",_xlfn.XLOOKUP($B$54,PROCESOS,'MATRIZ REQUISITOS ISO'!E$7:E$14,"")) -> 6 | H58: =IF($B58="","",_xlfn.XLOOKUP($B$54,PROCESOS,'MATRIZ REQUISITOS ISO'!F$7:F$14,"")) -> 0 | I58: =IF($B58="","",_xlfn.XLOOKUP($B$54,PROCESOS,'MATRIZ REQUISITOS ISO'!G$7:G$14,"")) -> 6 | J58: =IF($B58="","",_xlfn.XLOOKUP($B$54,PROCESOS,'MATRIZ REQUISITOS ISO'!H$7:H$14,"")) -> 0 | K58: =IF($B58="","",_xlfn.XLOOKUP($B$54,PROCESOS,'MATRIZ REQUISITOS ISO'!I$7:I$14,"")) -> 0 | L58: =IF($B58="","",_xlfn.XLOOKUP($B$54,PROCESOS,'MATRIZ REQUISITOS ISO'!J$7:J$14,"")) -> 0 | M58: =IF($B58="","",_xlfn.XLOOKUP($B$54,PROCESOS,'MATRIZ REQUISITOS ISO'!K$7:K$14,"")) -> 6 | ... AG58: =IF($B58="","",_xlfn.XLOOKUP($B$54,PROCESOS,'MATRIZ REQUISITOS ISO'!AE$7:AE$14,"")) -> 6 | AH58: =$B$54 -> Medición_Análisis_y_Mejora
B59: Contabilidad | C59: Administrativa | D59: OOMPCO-02 | E59: I | F59: =IF($B59="","",_xlfn.XLOOKUP($B$54,PROCESOS,'MATRIZ REQUISITOS ISO'!D$7:D$14,"")) -> 6 | G59: =IF($B59="","",_xlfn.XLOOKUP($B$54,PROCESOS,'MATRIZ REQUISITOS ISO'!E$7:E$14,"")) -> 6 | H59: =IF($B59="","",_xlfn.XLOOKUP($B$54,PROCESOS,'MATRIZ REQUISITOS ISO'!F$7:F$14,"")) -> 0 | I59: =IF($B59="","",_xlfn.XLOOKUP($B$54,PROCESOS,'MATRIZ REQUISITOS ISO'!G$7:G$14,"")) -> 6 | J59: =IF($B59="","",_xlfn.XLOOKUP($B$54,PROCESOS,'MATRIZ REQUISITOS ISO'!H$7:H$14,"")) -> 0 | K59: =IF($B59="","",_xlfn.XLOOKUP($B$54,PROCESOS,'MATRIZ REQUISITOS ISO'!I$7:I$14,"")) -> 0 | L59: =IF($B59="","",_xlfn.XLOOKUP($B$54,PROCESOS,'MATRIZ REQUISITOS ISO'!J$7:J$14,"")) -> 0 | M59: =IF($B59="","",_xlfn.XLOOKUP($B$54,PROCESOS,'MATRIZ REQUISITOS ISO'!K$7:K$14,"")) -> 6 | ... AG59: =IF($B59="","",_xlfn.XLOOKUP($B$54,PROCESOS,'MATRIZ REQUISITOS ISO'!AE$7:AE$14,"")) -> 6 | AH59: =$B$54 -> Medición_Análisis_y_Mejora
B60: Contratos y Servicios | C60: Comercial | D60: OOMPGC-02 | E60: I | F60: =IF($B60="","",_xlfn.XLOOKUP($B$54,PROCESOS,'MATRIZ REQUISITOS ISO'!D$7:D$14,"")) -> 6 | G60: =IF($B60="","",_xlfn.XLOOKUP($B$54,PROCESOS,'MATRIZ REQUISITOS ISO'!E$7:E$14,"")) -> 6 | H60: =IF($B60="","",_xlfn.XLOOKUP($B$54,PROCESOS,'MATRIZ REQUISITOS ISO'!F$7:F$14,"")) -> 0 | I60: =IF($B60="","",_xlfn.XLOOKUP($B$54,PROCESOS,'MATRIZ REQUISITOS ISO'!G$7:G$14,"")) -> 6 | J60: =IF($B60="","",_xlfn.XLOOKUP($B$54,PROCESOS,'MATRIZ REQUISITOS ISO'!H$7:H$14,"")) -> 0 | K60: =IF($B60="","",_xlfn.XLOOKUP($B$54,PROCESOS,'MATRIZ REQUISITOS ISO'!I$7:I$14,"")) -> 0 | L60: =IF($B60="","",_xlfn.XLOOKUP($B$54,PROCESOS,'MATRIZ REQUISITOS ISO'!J$7:J$14,"")) -> 0 | M60: =IF($B60="","",_xlfn.XLOOKUP($B$54,PROCESOS,'MATRIZ REQUISITOS ISO'!K$7:K$14,"")) -> 6 | ... AG60: =IF($B60="","",_xlfn.XLOOKUP($B$54,PROCESOS,'MATRIZ REQUISITOS ISO'!AE$7:AE$14,"")) -> 6 | AH60: =$B$54 -> Medición_Análisis_y_Mejora
B61: Control de Calidad | C61: Técnica | D61: OOMPCC-01 OOMPCC-04 OOMPCC-06 OOMPCC-27 OOMPCC-47 | E61: I | F61: =IF($B61="","",_xlfn.XLOOKUP($B$54,PROCESOS,'MATRIZ REQUISITOS ISO'!D$7:D$14,"")) -> 6 | G61: =IF($B61="","",_xlfn.XLOOKUP($B$54,PROCESOS,'MATRIZ REQUISITOS ISO'!E$7:E$14,"")) -> 6 | H61: =IF($B61="","",_xlfn.XLOOKUP($B$54,PROCESOS,'MATRIZ REQUISITOS ISO'!F$7:F$14,"")) -> 0 | I61: =IF($B61="","",_xlfn.XLOOKUP($B$54,PROCESOS,'MATRIZ REQUISITOS ISO'!G$7:G$14,"")) -> 6 | J61: =IF($B61="","",_xlfn.XLOOKUP($B$54,PROCESOS,'MATRIZ REQUISITOS ISO'!H$7:H$14,"")) -> 0 | K61: =IF($B61="","",_xlfn.XLOOKUP($B$54,PROCESOS,'MATRIZ REQUISITOS ISO'!I$7:I$14,"")) -> 0 | L61: =IF($B61="","",_xlfn.XLOOKUP($B$54,PROCESOS,'MATRIZ REQUISITOS ISO'!J$7:J$14,"")) -> 0 | M61: =IF($B61="","",_xlfn.XLOOKUP($B$54,PROCESOS,'MATRIZ REQUISITOS ISO'!K$7:K$14,"")) -> 6 | ... AG61: =IF($B61="","",_xlfn.XLOOKUP($B$54,PROCESOS,'MATRIZ REQUISITOS ISO'!AE$7:AE$14,"")) -> 6 | AH61: =$B$54 -> Medición_Análisis_y_Mejora
B62: Control y Servicios | C62: Comercial | D62: OOMPCS-01 OOMPCS-02 OOMPCS-05 OOMPCS-10 | E62: I | F62: =IF($B62="","",_xlfn.XLOOKUP($B$54,PROCESOS,'MATRIZ REQUISITOS ISO'!D$7:D$14,"")) -> 6 | G62: =IF($B62="","",_xlfn.XLOOKUP($B$54,PROCESOS,'MATRIZ REQUISITOS ISO'!E$7:E$14,"")) -> 6 | H62: =IF($B62="","",_xlfn.XLOOKUP($B$54,PROCESOS,'MATRIZ REQUISITOS ISO'!F$7:F$14,"")) -> 0 | I62: =IF($B62="","",_xlfn.XLOOKUP($B$54,PROCESOS,'MATRIZ REQUISITOS ISO'!G$7:G$14,"")) -> 6 | J62: =IF($B62="","",_xlfn.XLOOKUP($B$54,PROCESOS,'MATRIZ REQUISITOS ISO'!H$7:H$14,"")) -> 0 | K62: =IF($B62="","",_xlfn.XLOOKUP($B$54,PROCESOS,'MATRIZ REQUISITOS ISO'!I$7:I$14,"")) -> 0 | L62: =IF($B62="","",_xlfn.XLOOKUP($B$54,PROCESOS,'MATRIZ REQUISITOS ISO'!J$7:J$14,"")) -> 0 | M62: =IF($B62="","",_xlfn.XLOOKUP($B$54,PROCESOS,'MATRIZ REQUISITOS ISO'!K$7:K$14,"")) -> 6 | ... AG62: =IF($B62="","",_xlfn.XLOOKUP($B$54,PROCESOS,'MATRIZ REQUISITOS ISO'!AE$7:AE$14,"")) -> 6 | AH62: =$B$54 -> Medición_Análisis_y_Mejora
B63: Cultura del Agua | C63: Programas Sociales y cultura del Agua | D63: OOMPCU-01 | F63: =IF($B63="","",_xlfn.XLOOKUP($B$54,PROCESOS,'MATRIZ REQUISITOS ISO'!D$7:D$14,"")) -> 6 | G63: =IF($B63="","",_xlfn.XLOOKUP($B$54,PROCESOS,'MATRIZ REQUISITOS ISO'!E$7:E$14,"")) -> 6 | H63: =IF($B63="","",_xlfn.XLOOKUP($B$54,PROCESOS,'MATRIZ REQUISITOS ISO'!F$7:F$14,"")) -> 0 | I63: =IF($B63="","",_xlfn.XLOOKUP($B$54,PROCESOS,'MATRIZ REQUISITOS ISO'!G$7:G$14,"")) -> 6 | J63: =IF($B63="","",_xlfn.XLOOKUP($B$54,PROCESOS,'MATRIZ REQUISITOS ISO'!H$7:H$14,"")) -> 0 | K63: =IF($B63="","",_xlfn.XLOOKUP($B$54,PROCESOS,'MATRIZ REQUISITOS ISO'!I$7:I$14,"")) -> 0 | L63: =IF($B63="","",_xlfn.XLOOKUP($B$54,PROCESOS,'MATRIZ REQUISITOS ISO'!J$7:J$14,"")) -> 0 | M63: =IF($B63="","",_xlfn.XLOOKUP($B$54,PROCESOS,'MATRIZ REQUISITOS ISO'!K$7:K$14,"")) -> 6 | ... AG63: =IF($B63="","",_xlfn.XLOOKUP($B$54,PROCESOS,'MATRIZ REQUISITOS ISO'!AE$7:AE$14,"")) -> 6 | AH63: =$B$54 -> Medición_Análisis_y_Mejora
B64: Dirección Administrativa | C64: Administrativa | D64: OOMPDA-01 | F64: =IF($B64="","",_xlfn.XLOOKUP($B$54,PROCESOS,'MATRIZ REQUISITOS ISO'!D$7:D$14,"")) -> 6 | G64: =IF($B64="","",_xlfn.XLOOKUP($B$54,PROCESOS,'MATRIZ REQUISITOS ISO'!E$7:E$14,"")) -> 6 | H64: =IF($B64="","",_xlfn.XLOOKUP($B$54,PROCESOS,'MATRIZ REQUISITOS ISO'!F$7:F$14,"")) -> 0 | I64: =IF($B64="","",_xlfn.XLOOKUP($B$54,PROCESOS,'MATRIZ REQUISITOS ISO'!G$7:G$14,"")) -> 6 | J64: =IF($B64="","",_xlfn.XLOOKUP($B$54,PROCESOS,'MATRIZ REQUISITOS ISO'!H$7:H$14,"")) -> 0 | K64: =IF($B64="","",_xlfn.XLOOKUP($B$54,PROCESOS,'MATRIZ REQUISITOS ISO'!I$7:I$14,"")) -> 0 | L64: =IF($B64="","",_xlfn.XLOOKUP($B$54,PROCESOS,'MATRIZ REQUISITOS ISO'!J$7:J$14,"")) -> 0 | M64: =IF($B64="","",_xlfn.XLOOKUP($B$54,PROCESOS,'MATRIZ REQUISITOS ISO'!K$7:K$14,"")) -> 6 | ... AG64: =IF($B64="","",_xlfn.XLOOKUP($B$54,PROCESOS,'MATRIZ REQUISITOS ISO'!AE$7:AE$14,"")) -> 6 | AH64: =$B$54 -> Medición_Análisis_y_Mejora
B65: Informática | C65: Administrativa | D65: OOMPGI-04 OOMPGI-06 OOMPGI-07 | E65: I | F65: =IF($B65="","",_xlfn.XLOOKUP($B$54,PROCESOS,'MATRIZ REQUISITOS ISO'!D$7:D$14,"")) -> 6 | G65: =IF($B65="","",_xlfn.XLOOKUP($B$54,PROCESOS,'MATRIZ REQUISITOS ISO'!E$7:E$14,"")) -> 6 | H65: =IF($B65="","",_xlfn.XLOOKUP($B$54,PROCESOS,'MATRIZ REQUISITOS ISO'!F$7:F$14,"")) -> 0 | I65: =IF($B65="","",_xlfn.XLOOKUP($B$54,PROCESOS,'MATRIZ REQUISITOS ISO'!G$7:G$14,"")) -> 6 | J65: =IF($B65="","",_xlfn.XLOOKUP($B$54,PROCESOS,'MATRIZ REQUISITOS ISO'!H$7:H$14,"")) -> 0 | K65: =IF($B65="","",_xlfn.XLOOKUP($B$54,PROCESOS,'MATRIZ REQUISITOS ISO'!I$7:I$14,"")) -> 0 | L65: =IF($B65="","",_xlfn.XLOOKUP($B$54,PROCESOS,'MATRIZ REQUISITOS ISO'!J$7:J$14,"")) -> 0 | M65: =IF($B65="","",_xlfn.XLOOKUP($B$54,PROCESOS,'MATRIZ REQUISITOS ISO'!K$7:K$14,"")) -> 6 | ... AG65: =IF($B65="","",_xlfn.XLOOKUP($B$54,PROCESOS,'MATRIZ REQUISITOS ISO'!AE$7:AE$14,"")) -> 6 | AH65: =$B$54 -> Medición_Análisis_y_Mejora
B66: Jurídico | C66: Jurídica | D66: OOMPJU-01 OOMPJU-02 OOMPJU-03 OOMPJU-04 OOMPJU-05 OOMPJU-06 OOMPJU-07 OOMPJU-08 OOMPJU-09 OOMPJU-10 OOMPJU-11 OOMPJU-13 OOMPJU-14 OOMPJU-15 | E66: I | F66: =IF($B66="","",_xlfn.XLOOKUP($B$54,PROCESOS,'MATRIZ REQUISITOS ISO'!D$7:D$14,"")) -> 6 | G66: =IF($B66="","",_xlfn.XLOOKUP($B$54,PROCESOS,'MATRIZ REQUISITOS ISO'!E$7:E$14,"")) -> 6 | H66: =IF($B66="","",_xlfn.XLOOKUP($B$54,PROCESOS,'MATRIZ REQUISITOS ISO'!F$7:F$14,"")) -> 0 | I66: =IF($B66="","",_xlfn.XLOOKUP($B$54,PROCESOS,'MATRIZ REQUISITOS ISO'!G$7:G$14,"")) -> 6 | J66: =IF($B66="","",_xlfn.XLOOKUP($B$54,PROCESOS,'MATRIZ REQUISITOS ISO'!H$7:H$14,"")) -> 0 | K66: =IF($B66="","",_xlfn.XLOOKUP($B$54,PROCESOS,'MATRIZ REQUISITOS ISO'!I$7:I$14,"")) -> 0 | L66: =IF($B66="","",_xlfn.XLOOKUP($B$54,PROCESOS,'MATRIZ REQUISITOS ISO'!J$7:J$14,"")) -> 0 | M66: =IF($B66="","",_xlfn.XLOOKUP($B$54,PROCESOS,'MATRIZ REQUISITOS ISO'!K$7:K$14,"")) -> 6 | ... AG66: =IF($B66="","",_xlfn.XLOOKUP($B$54,PROCESOS,'MATRIZ REQUISITOS ISO'!AE$7:AE$14,"")) -> 6 | AH66: =$B$54 -> Medición_Análisis_y_Mejora
B67: Licitaciones | C67: Administrativa | D67: OOMPCL-01 OOMPCL-02 | E67: I | F67: =IF($B67="","",_xlfn.XLOOKUP($B$54,PROCESOS,'MATRIZ REQUISITOS ISO'!D$7:D$14,"")) -> 6 | G67: =IF($B67="","",_xlfn.XLOOKUP($B$54,PROCESOS,'MATRIZ REQUISITOS ISO'!E$7:E$14,"")) -> 6 | H67: =IF($B67="","",_xlfn.XLOOKUP($B$54,PROCESOS,'MATRIZ REQUISITOS ISO'!F$7:F$14,"")) -> 0 | I67: =IF($B67="","",_xlfn.XLOOKUP($B$54,PROCESOS,'MATRIZ REQUISITOS ISO'!G$7:G$14,"")) -> 6 | J67: =IF($B67="","",_xlfn.XLOOKUP($B$54,PROCESOS,'MATRIZ REQUISITOS ISO'!H$7:H$14,"")) -> 0 | K67: =IF($B67="","",_xlfn.XLOOKUP($B$54,PROCESOS,'MATRIZ REQUISITOS ISO'!I$7:I$14,"")) -> 0 | L67: =IF($B67="","",_xlfn.XLOOKUP($B$54,PROCESOS,'MATRIZ REQUISITOS ISO'!J$7:J$14,"")) -> 0 | M67: =IF($B67="","",_xlfn.XLOOKUP($B$54,PROCESOS,'MATRIZ REQUISITOS ISO'!K$7:K$14,"")) -> 6 | ... AG67: =IF($B67="","",_xlfn.XLOOKUP($B$54,PROCESOS,'MATRIZ REQUISITOS ISO'!AE$7:AE$14,"")) -> 6 | AH67: =$B$54 -> Medición_Análisis_y_Mejora
B68: Línea OOMAPASC | C68: General | D68: OOMPAT-09 OOMPAT-13 | E68: I | F68: =IF($B68="","",_xlfn.XLOOKUP($B$54,PROCESOS,'MATRIZ REQUISITOS ISO'!D$7:D$14,"")) -> 6 | G68: =IF($B68="","",_xlfn.XLOOKUP($B$54,PROCESOS,'MATRIZ REQUISITOS ISO'!E$7:E$14,"")) -> 6 | H68: =IF($B68="","",_xlfn.XLOOKUP($B$54,PROCESOS,'MATRIZ REQUISITOS ISO'!F$7:F$14,"")) -> 0 | I68: =IF($B68="","",_xlfn.XLOOKUP($B$54,PROCESOS,'MATRIZ REQUISITOS ISO'!G$7:G$14,"")) -> 6 | J68: =IF($B68="","",_xlfn.XLOOKUP($B$54,PROCESOS,'MATRIZ REQUISITOS ISO'!H$7:H$14,"")) -> 0 | K68: =IF($B68="","",_xlfn.XLOOKUP($B$54,PROCESOS,'MATRIZ REQUISITOS ISO'!I$7:I$14,"")) -> 0 | L68: =IF($B68="","",_xlfn.XLOOKUP($B$54,PROCESOS,'MATRIZ REQUISITOS ISO'!J$7:J$14,"")) -> 0 | M68: =IF($B68="","",_xlfn.XLOOKUP($B$54,PROCESOS,'MATRIZ REQUISITOS ISO'!K$7:K$14,"")) -> 6 | ... AG68: =IF($B68="","",_xlfn.XLOOKUP($B$54,PROCESOS,'MATRIZ REQUISITOS ISO'!AE$7:AE$14,"")) -> 6 | AH68: =$B$54 -> Medición_Análisis_y_Mejora
B69: Mantenimiento de Redes | C69: Técnica | D69: OOMPMR-01 | E69: I | F69: =IF($B69="","",_xlfn.XLOOKUP($B$54,PROCESOS,'MATRIZ REQUISITOS ISO'!D$7:D$14,"")) -> 6 | G69: =IF($B69="","",_xlfn.XLOOKUP($B$54,PROCESOS,'MATRIZ REQUISITOS ISO'!E$7:E$14,"")) -> 6 | H69: =IF($B69="","",_xlfn.XLOOKUP($B$54,PROCESOS,'MATRIZ REQUISITOS ISO'!F$7:F$14,"")) -> 0 | I69: =IF($B69="","",_xlfn.XLOOKUP($B$54,PROCESOS,'MATRIZ REQUISITOS ISO'!G$7:G$14,"")) -> 6 | J69: =IF($B69="","",_xlfn.XLOOKUP($B$54,PROCESOS,'MATRIZ REQUISITOS ISO'!H$7:H$14,"")) -> 0 | K69: =IF($B69="","",_xlfn.XLOOKUP($B$54,PROCESOS,'MATRIZ REQUISITOS ISO'!I$7:I$14,"")) -> 0 | L69: =IF($B69="","",_xlfn.XLOOKUP($B$54,PROCESOS,'MATRIZ REQUISITOS ISO'!J$7:J$14,"")) -> 0 | M69: =IF($B69="","",_xlfn.XLOOKUP($B$54,PROCESOS,'MATRIZ REQUISITOS ISO'!K$7:K$14,"")) -> 6 | ... AG69: =IF($B69="","",_xlfn.XLOOKUP($B$54,PROCESOS,'MATRIZ REQUISITOS ISO'!AE$7:AE$14,"")) -> 6 | AH69: =$B$54 -> Medición_Análisis_y_Mejora
B70: Mantenimiento y Servicios Generales | C70: Administrativa | D70: OOMPMS-01 OOMPMS-02 OOMPMS-03 OOMPMS-04 | E70: I | F70: =IF($B70="","",_xlfn.XLOOKUP($B$54,PROCESOS,'MATRIZ REQUISITOS ISO'!D$7:D$14,"")) -> 6 | G70: =IF($B70="","",_xlfn.XLOOKUP($B$54,PROCESOS,'MATRIZ REQUISITOS ISO'!E$7:E$14,"")) -> 6 | H70: =IF($B70="","",_xlfn.XLOOKUP($B$54,PROCESOS,'MATRIZ REQUISITOS ISO'!F$7:F$14,"")) -> 0 | I70: =IF($B70="","",_xlfn.XLOOKUP($B$54,PROCESOS,'MATRIZ REQUISITOS ISO'!G$7:G$14,"")) -> 6 | J70: =IF($B70="","",_xlfn.XLOOKUP($B$54,PROCESOS,'MATRIZ REQUISITOS ISO'!H$7:H$14,"")) -> 0 | K70: =IF($B70="","",_xlfn.XLOOKUP($B$54,PROCESOS,'MATRIZ REQUISITOS ISO'!I$7:I$14,"")) -> 0 | L70: =IF($B70="","",_xlfn.XLOOKUP($B$54,PROCESOS,'MATRIZ REQUISITOS ISO'!J$7:J$14,"")) -> 0 | M70: =IF($B70="","",_xlfn.XLOOKUP($B$54,PROCESOS,'MATRIZ REQUISITOS ISO'!K$7:K$14,"")) -> 6 | ... AG70: =IF($B70="","",_xlfn.XLOOKUP($B$54,PROCESOS,'MATRIZ REQUISITOS ISO'!AE$7:AE$14,"")) -> 6 | AH70: =$B$54 -> Medición_Análisis_y_Mejora
B71: Órgano de Control Interno | C71: Órgano de control interno | D71: OOMPOC-01 OOMPOC-02 OOMPOC-03 OOMPOC-05 | E71: I | F71: =IF($B71="","",_xlfn.XLOOKUP($B$54,PROCESOS,'MATRIZ REQUISITOS ISO'!D$7:D$14,"")) -> 6 | G71: =IF($B71="","",_xlfn.XLOOKUP($B$54,PROCESOS,'MATRIZ REQUISITOS ISO'!E$7:E$14,"")) -> 6 | H71: =IF($B71="","",_xlfn.XLOOKUP($B$54,PROCESOS,'MATRIZ REQUISITOS ISO'!F$7:F$14,"")) -> 0 | I71: =IF($B71="","",_xlfn.XLOOKUP($B$54,PROCESOS,'MATRIZ REQUISITOS ISO'!G$7:G$14,"")) -> 6 | J71: =IF($B71="","",_xlfn.XLOOKUP($B$54,PROCESOS,'MATRIZ REQUISITOS ISO'!H$7:H$14,"")) -> 0 | K71: =IF($B71="","",_xlfn.XLOOKUP($B$54,PROCESOS,'MATRIZ REQUISITOS ISO'!I$7:I$14,"")) -> 0 | L71: =IF($B71="","",_xlfn.XLOOKUP($B$54,PROCESOS,'MATRIZ REQUISITOS ISO'!J$7:J$14,"")) -> 0 | M71: =IF($B71="","",_xlfn.XLOOKUP($B$54,PROCESOS,'MATRIZ REQUISITOS ISO'!K$7:K$14,"")) -> 6 | ... AG71: =IF($B71="","",_xlfn.XLOOKUP($B$54,PROCESOS,'MATRIZ REQUISITOS ISO'!AE$7:AE$14,"")) -> 6 | AH71: =$B$54 -> Medición_Análisis_y_Mejora
B72: Padrón de Usuarios | C72: Comercial | D72: OOMPGP-01 | E72: I | F72: =IF($B72="","",_xlfn.XLOOKUP($B$54,PROCESOS,'MATRIZ REQUISITOS ISO'!D$7:D$14,"")) -> 6 | G72: =IF($B72="","",_xlfn.XLOOKUP($B$54,PROCESOS,'MATRIZ REQUISITOS ISO'!E$7:E$14,"")) -> 6 | H72: =IF($B72="","",_xlfn.XLOOKUP($B$54,PROCESOS,'MATRIZ REQUISITOS ISO'!F$7:F$14,"")) -> 0 | I72: =IF($B72="","",_xlfn.XLOOKUP($B$54,PROCESOS,'MATRIZ REQUISITOS ISO'!G$7:G$14,"")) -> 6 | J72: =IF($B72="","",_xlfn.XLOOKUP($B$54,PROCESOS,'MATRIZ REQUISITOS ISO'!H$7:H$14,"")) -> 0 | K72: =IF($B72="","",_xlfn.XLOOKUP($B$54,PROCESOS,'MATRIZ REQUISITOS ISO'!I$7:I$14,"")) -> 0 | L72: =IF($B72="","",_xlfn.XLOOKUP($B$54,PROCESOS,'MATRIZ REQUISITOS ISO'!J$7:J$14,"")) -> 0 | M72: =IF($B72="","",_xlfn.XLOOKUP($B$54,PROCESOS,'MATRIZ REQUISITOS ISO'!K$7:K$14,"")) -> 6 | ... AG72: =IF($B72="","",_xlfn.XLOOKUP($B$54,PROCESOS,'MATRIZ REQUISITOS ISO'!AE$7:AE$14,"")) -> 6 | AH72: =$B$54 -> Medición_Análisis_y_Mejora
B73: Plantas Potabilizadoras | C73: Técnica | D73: OOMPPP-01 OOMPPP-02 OOMPPP-03 OOMPPP-04 OOMPPP-05 OOMPPP-06 OOMPPP-07 OOMPPP-08 OOMPPP-09 OOMPPP-10 OOMPPP-11 OOMPPP-12 OOMPPP-13 OOMPPP-15 OOMPPP-16 OOMPPP-17 OOMPPP-18 OOMPPP-19 OOMPPP-20 OOMPPP-21 OOMPPP-22 OOMPPP-23 OOMPPP-24 OOMPPP-25 OOMPPP-26 OOMPPP-27 OOMPPP-28 OOMPPP-29 OOMPPP-30 OOMPPP-31 OOMPPP-32 OOMPPP-33 OOMPPP-34 OOMPPP-36 | E73: I | F73: =IF($B73="","",_xlfn.XLOOKUP($B$54,PROCESOS,'MATRIZ REQUISITOS ISO'!D$7:D$14,"")) -> 6 | G73: =IF($B73="","",_xlfn.XLOOKUP($B$54,PROCESOS,'MATRIZ REQUISITOS ISO'!E$7:E$14,"")) -> 6 | H73: =IF($B73="","",_xlfn.XLOOKUP($B$54,PROCESOS,'MATRIZ REQUISITOS ISO'!F$7:F$14,"")) -> 0 | I73: =IF($B73="","",_xlfn.XLOOKUP($B$54,PROCESOS,'MATRIZ REQUISITOS ISO'!G$7:G$14,"")) -> 6 | J73: =IF($B73="","",_xlfn.XLOOKUP($B$54,PROCESOS,'MATRIZ REQUISITOS ISO'!H$7:H$14,"")) -> 0 | K73: =IF($B73="","",_xlfn.XLOOKUP($B$54,PROCESOS,'MATRIZ REQUISITOS ISO'!I$7:I$14,"")) -> 0 | L73: =IF($B73="","",_xlfn.XLOOKUP($B$54,PROCESOS,'MATRIZ REQUISITOS ISO'!J$7:J$14,"")) -> 0 | M73: =IF($B73="","",_xlfn.XLOOKUP($B$54,PROCESOS,'MATRIZ REQUISITOS ISO'!K$7:K$14,"")) -> 6 | ... AG73: =IF($B73="","",_xlfn.XLOOKUP($B$54,PROCESOS,'MATRIZ REQUISITOS ISO'!AE$7:AE$14,"")) -> 6 | AH73: =$B$54 -> Medición_Análisis_y_Mejora
B74: Proyectos e Infraestructura | C74: Técnica | D74: OOMPPI-01 OOMPPI-02 OOMPPI-03 OOMPPI-04 | E74: I | F74: =IF($B74="","",_xlfn.XLOOKUP($B$54,PROCESOS,'MATRIZ REQUISITOS ISO'!D$7:D$14,"")) -> 6 | G74: =IF($B74="","",_xlfn.XLOOKUP($B$54,PROCESOS,'MATRIZ REQUISITOS ISO'!E$7:E$14,"")) -> 6 | H74: =IF($B74="","",_xlfn.XLOOKUP($B$54,PROCESOS,'MATRIZ REQUISITOS ISO'!F$7:F$14,"")) -> 0 | I74: =IF($B74="","",_xlfn.XLOOKUP($B$54,PROCESOS,'MATRIZ REQUISITOS ISO'!G$7:G$14,"")) -> 6 | J74: =IF($B74="","",_xlfn.XLOOKUP($B$54,PROCESOS,'MATRIZ REQUISITOS ISO'!H$7:H$14,"")) -> 0 | K74: =IF($B74="","",_xlfn.XLOOKUP($B$54,PROCESOS,'MATRIZ REQUISITOS ISO'!I$7:I$14,"")) -> 0 | L74: =IF($B74="","",_xlfn.XLOOKUP($B$54,PROCESOS,'MATRIZ REQUISITOS ISO'!J$7:J$14,"")) -> 0 | M74: =IF($B74="","",_xlfn.XLOOKUP($B$54,PROCESOS,'MATRIZ REQUISITOS ISO'!K$7:K$14,"")) -> 6 | ... AG74: =IF($B74="","",_xlfn.XLOOKUP($B$54,PROCESOS,'MATRIZ REQUISITOS ISO'!AE$7:AE$14,"")) -> 6 | AH74: =$B$54 -> Medición_Análisis_y_Mejora
B75: Recursos Humanos | C75: Administrativa | D75: OOMPRH-01 OOMPRH-04 OOMPRH-09 | E75: I | F75: =IF($B75="","",_xlfn.XLOOKUP($B$54,PROCESOS,'MATRIZ REQUISITOS ISO'!D$7:D$14,"")) -> 6 | G75: =IF($B75="","",_xlfn.XLOOKUP($B$54,PROCESOS,'MATRIZ REQUISITOS ISO'!E$7:E$14,"")) -> 6 | H75: =IF($B75="","",_xlfn.XLOOKUP($B$54,PROCESOS,'MATRIZ REQUISITOS ISO'!F$7:F$14,"")) -> 0 | I75: =IF($B75="","",_xlfn.XLOOKUP($B$54,PROCESOS,'MATRIZ REQUISITOS ISO'!G$7:G$14,"")) -> 6 | J75: =IF($B75="","",_xlfn.XLOOKUP($B$54,PROCESOS,'MATRIZ REQUISITOS ISO'!H$7:H$14,"")) -> 0 | K75: =IF($B75="","",_xlfn.XLOOKUP($B$54,PROCESOS,'MATRIZ REQUISITOS ISO'!I$7:I$14,"")) -> 0 | L75: =IF($B75="","",_xlfn.XLOOKUP($B$54,PROCESOS,'MATRIZ REQUISITOS ISO'!J$7:J$14,"")) -> 0 | M75: =IF($B75="","",_xlfn.XLOOKUP($B$54,PROCESOS,'MATRIZ REQUISITOS ISO'!K$7:K$14,"")) -> 6 | ... AG75: =IF($B75="","",_xlfn.XLOOKUP($B$54,PROCESOS,'MATRIZ REQUISITOS ISO'!AE$7:AE$14,"")) -> 6 | AH75: =$B$54 -> Medición_Análisis_y_Mejora
B76: Recursos Materiales | C76: Administrativa | D76: OOMPRM-01 OOMPRM-03 | E76: I | F76: =IF($B76="","",_xlfn.XLOOKUP($B$54,PROCESOS,'MATRIZ REQUISITOS ISO'!D$7:D$14,"")) -> 6 | G76: =IF($B76="","",_xlfn.XLOOKUP($B$54,PROCESOS,'MATRIZ REQUISITOS ISO'!E$7:E$14,"")) -> 6 | H76: =IF($B76="","",_xlfn.XLOOKUP($B$54,PROCESOS,'MATRIZ REQUISITOS ISO'!F$7:F$14,"")) -> 0 | I76: =IF($B76="","",_xlfn.XLOOKUP($B$54,PROCESOS,'MATRIZ REQUISITOS ISO'!G$7:G$14,"")) -> 6 | J76: =IF($B76="","",_xlfn.XLOOKUP($B$54,PROCESOS,'MATRIZ REQUISITOS ISO'!H$7:H$14,"")) -> 0 | K76: =IF($B76="","",_xlfn.XLOOKUP($B$54,PROCESOS,'MATRIZ REQUISITOS ISO'!I$7:I$14,"")) -> 0 | L76: =IF($B76="","",_xlfn.XLOOKUP($B$54,PROCESOS,'MATRIZ REQUISITOS ISO'!J$7:J$14,"")) -> 0 | M76: =IF($B76="","",_xlfn.XLOOKUP($B$54,PROCESOS,'MATRIZ REQUISITOS ISO'!K$7:K$14,"")) -> 6 | ... AG76: =IF($B76="","",_xlfn.XLOOKUP($B$54,PROCESOS,'MATRIZ REQUISITOS ISO'!AE$7:AE$14,"")) -> 6 | AH76: =$B$54 -> Medición_Análisis_y_Mejora
B77: Sectorización hidrométrica e innovación | C77: Técnica | D77: OOMPSH-01 OOMPSH-05 | F77: =IF($B77="","",_xlfn.XLOOKUP($B$54,PROCESOS,'MATRIZ REQUISITOS ISO'!D$7:D$14,"")) -> 6 | G77: =IF($B77="","",_xlfn.XLOOKUP($B$54,PROCESOS,'MATRIZ REQUISITOS ISO'!E$7:E$14,"")) -> 6 | H77: =IF($B77="","",_xlfn.XLOOKUP($B$54,PROCESOS,'MATRIZ REQUISITOS ISO'!F$7:F$14,"")) -> 0 | I77: =IF($B77="","",_xlfn.XLOOKUP($B$54,PROCESOS,'MATRIZ REQUISITOS ISO'!G$7:G$14,"")) -> 6 | J77: =IF($B77="","",_xlfn.XLOOKUP($B$54,PROCESOS,'MATRIZ REQUISITOS ISO'!H$7:H$14,"")) -> 0 | K77: =IF($B77="","",_xlfn.XLOOKUP($B$54,PROCESOS,'MATRIZ REQUISITOS ISO'!I$7:I$14,"")) -> 0 | L77: =IF($B77="","",_xlfn.XLOOKUP($B$54,PROCESOS,'MATRIZ REQUISITOS ISO'!J$7:J$14,"")) -> 0 | M77: =IF($B77="","",_xlfn.XLOOKUP($B$54,PROCESOS,'MATRIZ REQUISITOS ISO'!K$7:K$14,"")) -> 6 | ... AG77: =IF($B77="","",_xlfn.XLOOKUP($B$54,PROCESOS,'MATRIZ REQUISITOS ISO'!AE$7:AE$14,"")) -> 6 | AH77: =$B$54 -> Medición_Análisis_y_Mejora
B78: Seguridad Industrial | C78: Administrativa | D78: OOMPIS-01 OOMPIS-05 | E78: I | F78: =IF($B78="","",_xlfn.XLOOKUP($B$54,PROCESOS,'MATRIZ REQUISITOS ISO'!D$7:D$14,"")) -> 6 | G78: =IF($B78="","",_xlfn.XLOOKUP($B$54,PROCESOS,'MATRIZ REQUISITOS ISO'!E$7:E$14,"")) -> 6 | H78: =IF($B78="","",_xlfn.XLOOKUP($B$54,PROCESOS,'MATRIZ REQUISITOS ISO'!F$7:F$14,"")) -> 0 | I78: =IF($B78="","",_xlfn.XLOOKUP($B$54,PROCESOS,'MATRIZ REQUISITOS ISO'!G$7:G$14,"")) -> 6 | J78: =IF($B78="","",_xlfn.XLOOKUP($B$54,PROCESOS,'MATRIZ REQUISITOS ISO'!H$7:H$14,"")) -> 0 | K78: =IF($B78="","",_xlfn.XLOOKUP($B$54,PROCESOS,'MATRIZ REQUISITOS ISO'!I$7:I$14,"")) -> 0 | L78: =IF($B78="","",_xlfn.XLOOKUP($B$54,PROCESOS,'MATRIZ REQUISITOS ISO'!J$7:J$14,"")) -> 0 | M78: =IF($B78="","",_xlfn.XLOOKUP($B$54,PROCESOS,'MATRIZ REQUISITOS ISO'!K$7:K$14,"")) -> 6 | ... AG78: =IF($B78="","",_xlfn.XLOOKUP($B$54,PROCESOS,'MATRIZ REQUISITOS ISO'!AE$7:AE$14,"")) -> 6 | AH78: =$B$54 -> Medición_Análisis_y_Mejora
B79: Sistema de Gestión de Calidad | C79: General | D79: OOMPSC-04 OOMPSC-05 OOMPSC-08 OOMPSC-09 OOMPSC-11 OOMPSC-12 OOMPSC-14 OOMPSC-16 | E79: D | F79: =IF($B79="","",_xlfn.XLOOKUP($B$54,PROCESOS,'MATRIZ REQUISITOS ISO'!D$7:D$14,"")) -> 6 | G79: =IF($B79="","",_xlfn.XLOOKUP($B$54,PROCESOS,'MATRIZ REQUISITOS ISO'!E$7:E$14,"")) -> 6 | H79: =IF($B79="","",_xlfn.XLOOKUP($B$54,PROCESOS,'MATRIZ REQUISITOS ISO'!F$7:F$14,"")) -> 0 | I79: =IF($B79="","",_xlfn.XLOOKUP($B$54,PROCESOS,'MATRIZ REQUISITOS ISO'!G$7:G$14,"")) -> 6 | J79: =IF($B79="","",_xlfn.XLOOKUP($B$54,PROCESOS,'MATRIZ REQUISITOS ISO'!H$7:H$14,"")) -> 0 | K79: =IF($B79="","",_xlfn.XLOOKUP($B$54,PROCESOS,'MATRIZ REQUISITOS ISO'!I$7:I$14,"")) -> 0 | L79: =IF($B79="","",_xlfn.XLOOKUP($B$54,PROCESOS,'MATRIZ REQUISITOS ISO'!J$7:J$14,"")) -> 0 | M79: =IF($B79="","",_xlfn.XLOOKUP($B$54,PROCESOS,'MATRIZ REQUISITOS ISO'!K$7:K$14,"")) -> 6 | ... AG79: =IF($B79="","",_xlfn.XLOOKUP($B$54,PROCESOS,'MATRIZ REQUISITOS ISO'!AE$7:AE$14,"")) -> 6 | AH79: =$B$54 -> Medición_Análisis_y_Mejora
B80: Suburbano Comercial | C80: Comercial | D80: OOMPAS-11 OOMPAS-17 OOMPAS-18 OOMPAS-19 | E80: I | F80: =IF($B80="","",_xlfn.XLOOKUP($B$54,PROCESOS,'MATRIZ REQUISITOS ISO'!D$7:D$14,"")) -> 6 | G80: =IF($B80="","",_xlfn.XLOOKUP($B$54,PROCESOS,'MATRIZ REQUISITOS ISO'!E$7:E$14,"")) -> 6 | H80: =IF($B80="","",_xlfn.XLOOKUP($B$54,PROCESOS,'MATRIZ REQUISITOS ISO'!F$7:F$14,"")) -> 0 | I80: =IF($B80="","",_xlfn.XLOOKUP($B$54,PROCESOS,'MATRIZ REQUISITOS ISO'!G$7:G$14,"")) -> 6 | J80: =IF($B80="","",_xlfn.XLOOKUP($B$54,PROCESOS,'MATRIZ REQUISITOS ISO'!H$7:H$14,"")) -> 0 | K80: =IF($B80="","",_xlfn.XLOOKUP($B$54,PROCESOS,'MATRIZ REQUISITOS ISO'!I$7:I$14,"")) -> 0 | L80: =IF($B80="","",_xlfn.XLOOKUP($B$54,PROCESOS,'MATRIZ REQUISITOS ISO'!J$7:J$14,"")) -> 0 | M80: =IF($B80="","",_xlfn.XLOOKUP($B$54,PROCESOS,'MATRIZ REQUISITOS ISO'!K$7:K$14,"")) -> 6 | ... AG80: =IF($B80="","",_xlfn.XLOOKUP($B$54,PROCESOS,'MATRIZ REQUISITOS ISO'!AE$7:AE$14,"")) -> 6 | AH80: =$B$54 -> Medición_Análisis_y_Mejora
B81: Suburbano Técnico | C81: Técnica | D81: OOMPTS-01 OOMPTS-02 OOMPTS-03 OOMPTS-04 OOMPTS-06 OOMPTS-07 OOMPTS-15 | E81: I | F81: =IF($B81="","",_xlfn.XLOOKUP($B$54,PROCESOS,'MATRIZ REQUISITOS ISO'!D$7:D$14,"")) -> 6 | G81: =IF($B81="","",_xlfn.XLOOKUP($B$54,PROCESOS,'MATRIZ REQUISITOS ISO'!E$7:E$14,"")) -> 6 | H81: =IF($B81="","",_xlfn.XLOOKUP($B$54,PROCESOS,'MATRIZ REQUISITOS ISO'!F$7:F$14,"")) -> 0 | I81: =IF($B81="","",_xlfn.XLOOKUP($B$54,PROCESOS,'MATRIZ REQUISITOS ISO'!G$7:G$14,"")) -> 6 | J81: =IF($B81="","",_xlfn.XLOOKUP($B$54,PROCESOS,'MATRIZ REQUISITOS ISO'!H$7:H$14,"")) -> 0 | K81: =IF($B81="","",_xlfn.XLOOKUP($B$54,PROCESOS,'MATRIZ REQUISITOS ISO'!I$7:I$14,"")) -> 0 | L81: =IF($B81="","",_xlfn.XLOOKUP($B$54,PROCESOS,'MATRIZ REQUISITOS ISO'!J$7:J$14,"")) -> 0 | M81: =IF($B81="","",_xlfn.XLOOKUP($B$54,PROCESOS,'MATRIZ REQUISITOS ISO'!K$7:K$14,"")) -> 6 | ... AG81: =IF($B81="","",_xlfn.XLOOKUP($B$54,PROCESOS,'MATRIZ REQUISITOS ISO'!AE$7:AE$14,"")) -> 6 | AH81: =$B$54 -> Medición_Análisis_y_Mejora
B82: Supervisión y Control de Obras | C82: Técnica | D82: OOMPSO-01 | E82: I | F82: =IF($B82="","",_xlfn.XLOOKUP($B$54,PROCESOS,'MATRIZ REQUISITOS ISO'!D$7:D$14,"")) -> 6 | G82: =IF($B82="","",_xlfn.XLOOKUP($B$54,PROCESOS,'MATRIZ REQUISITOS ISO'!E$7:E$14,"")) -> 6 | H82: =IF($B82="","",_xlfn.XLOOKUP($B$54,PROCESOS,'MATRIZ REQUISITOS ISO'!F$7:F$14,"")) -> 0 | I82: =IF($B82="","",_xlfn.XLOOKUP($B$54,PROCESOS,'MATRIZ REQUISITOS ISO'!G$7:G$14,"")) -> 6 | J82: =IF($B82="","",_xlfn.XLOOKUP($B$54,PROCESOS,'MATRIZ REQUISITOS ISO'!H$7:H$14,"")) -> 0 | K82: =IF($B82="","",_xlfn.XLOOKUP($B$54,PROCESOS,'MATRIZ REQUISITOS ISO'!I$7:I$14,"")) -> 0 | L82: =IF($B82="","",_xlfn.XLOOKUP($B$54,PROCESOS,'MATRIZ REQUISITOS ISO'!J$7:J$14,"")) -> 0 | M82: =IF($B82="","",_xlfn.XLOOKUP($B$54,PROCESOS,'MATRIZ REQUISITOS ISO'!K$7:K$14,"")) -> 6 | ... AG82: =IF($B82="","",_xlfn.XLOOKUP($B$54,PROCESOS,'MATRIZ REQUISITOS ISO'!AE$7:AE$14,"")) -> 6 | AH82: =$B$54 -> Medición_Análisis_y_Mejora
B83: Trabajo Social | C83: Programas Sociales y Desarrollo Institucional | D83: OOMPSS-01 | E83: I | F83: =IF($B83="","",_xlfn.XLOOKUP($B$54,PROCESOS,'MATRIZ REQUISITOS ISO'!D$7:D$14,"")) -> 6 | G83: =IF($B83="","",_xlfn.XLOOKUP($B$54,PROCESOS,'MATRIZ REQUISITOS ISO'!E$7:E$14,"")) -> 6 | H83: =IF($B83="","",_xlfn.XLOOKUP($B$54,PROCESOS,'MATRIZ REQUISITOS ISO'!F$7:F$14,"")) -> 0 | I83: =IF($B83="","",_xlfn.XLOOKUP($B$54,PROCESOS,'MATRIZ REQUISITOS ISO'!G$7:G$14,"")) -> 6 | J83: =IF($B83="","",_xlfn.XLOOKUP($B$54,PROCESOS,'MATRIZ REQUISITOS ISO'!H$7:H$14,"")) -> 0 | K83: =IF($B83="","",_xlfn.XLOOKUP($B$54,PROCESOS,'MATRIZ REQUISITOS ISO'!I$7:I$14,"")) -> 0 | L83: =IF($B83="","",_xlfn.XLOOKUP($B$54,PROCESOS,'MATRIZ REQUISITOS ISO'!J$7:J$14,"")) -> 0 | M83: =IF($B83="","",_xlfn.XLOOKUP($B$54,PROCESOS,'MATRIZ REQUISITOS ISO'!K$7:K$14,"")) -> 6 | ... AG83: =IF($B83="","",_xlfn.XLOOKUP($B$54,PROCESOS,'MATRIZ REQUISITOS ISO'!AE$7:AE$14,"")) -> 6 | AH83: =$B$54 -> Medición_Análisis_y_Mejora
B84: Trámites Técnicos | C84: Técnica | D84: OOMPTT-02 OOMPTT-05 | E84: I | F84: =IF($B84="","",_xlfn.XLOOKUP($B$54,PROCESOS,'MATRIZ REQUISITOS ISO'!D$7:D$14,"")) -> 6 | G84: =IF($B84="","",_xlfn.XLOOKUP($B$54,PROCESOS,'MATRIZ REQUISITOS ISO'!E$7:E$14,"")) -> 6 | H84: =IF($B84="","",_xlfn.XLOOKUP($B$54,PROCESOS,'MATRIZ REQUISITOS ISO'!F$7:F$14,"")) -> 0 | I84: =IF($B84="","",_xlfn.XLOOKUP($B$54,PROCESOS,'MATRIZ REQUISITOS ISO'!G$7:G$14,"")) -> 6 | J84: =IF($B84="","",_xlfn.XLOOKUP($B$54,PROCESOS,'MATRIZ REQUISITOS ISO'!H$7:H$14,"")) -> 0 | K84: =IF($B84="","",_xlfn.XLOOKUP($B$54,PROCESOS,'MATRIZ REQUISITOS ISO'!I$7:I$14,"")) -> 0 | L84: =IF($B84="","",_xlfn.XLOOKUP($B$54,PROCESOS,'MATRIZ REQUISITOS ISO'!J$7:J$14,"")) -> 0 | M84: =IF($B84="","",_xlfn.XLOOKUP($B$54,PROCESOS,'MATRIZ REQUISITOS ISO'!K$7:K$14,"")) -> 6 | ... AG84: =IF($B84="","",_xlfn.XLOOKUP($B$54,PROCESOS,'MATRIZ REQUISITOS ISO'!AE$7:AE$14,"")) -> 6 | AH84: =$B$54 -> Medición_Análisis_y_Mejora
B85: Verificación y Lectura | C85: Comercial | D85: OOMPVL-02 OOMPVL-03 OOMPVL-06 OOMPVL-07 | E85: I | F85: =IF($B85="","",_xlfn.XLOOKUP($B$54,PROCESOS,'MATRIZ REQUISITOS ISO'!D$7:D$14,"")) -> 6 | G85: =IF($B85="","",_xlfn.XLOOKUP($B$54,PROCESOS,'MATRIZ REQUISITOS ISO'!E$7:E$14,"")) -> 6 | H85: =IF($B85="","",_xlfn.XLOOKUP($B$54,PROCESOS,'MATRIZ REQUISITOS ISO'!F$7:F$14,"")) -> 0 | I85: =IF($B85="","",_xlfn.XLOOKUP($B$54,PROCESOS,'MATRIZ REQUISITOS ISO'!G$7:G$14,"")) -> 6 | J85: =IF($B85="","",_xlfn.XLOOKUP($B$54,PROCESOS,'MATRIZ REQUISITOS ISO'!H$7:H$14,"")) -> 0 | K85: =IF($B85="","",_xlfn.XLOOKUP($B$54,PROCESOS,'MATRIZ REQUISITOS ISO'!I$7:I$14,"")) -> 0 | L85: =IF($B85="","",_xlfn.XLOOKUP($B$54,PROCESOS,'MATRIZ REQUISITOS ISO'!J$7:J$14,"")) -> 0 | M85: =IF($B85="","",_xlfn.XLOOKUP($B$54,PROCESOS,'MATRIZ REQUISITOS ISO'!K$7:K$14,"")) -> 6 | ... AG85: =IF($B85="","",_xlfn.XLOOKUP($B$54,PROCESOS,'MATRIZ REQUISITOS ISO'!AE$7:AE$14,"")) -> 6 | AH85: =$B$54 -> Medición_Análisis_y_Mejora
F86: =IF($B86="","",_xlfn.XLOOKUP($B$54,PROCESOS,'MATRIZ REQUISITOS ISO'!D$7:D$14,"")) | G86: =IF($B86="","",_xlfn.XLOOKUP($B$54,PROCESOS,'MATRIZ REQUISITOS ISO'!E$7:E$14,"")) | H86: =IF($B86="","",_xlfn.XLOOKUP($B$54,PROCESOS,'MATRIZ REQUISITOS ISO'!F$7:F$14,"")) | I86: =IF($B86="","",_xlfn.XLOOKUP($B$54,PROCESOS,'MATRIZ REQUISITOS ISO'!G$7:G$14,"")) | J86: =IF($B86="","",_xlfn.XLOOKUP($B$54,PROCESOS,'MATRIZ REQUISITOS ISO'!H$7:H$14,"")) | K86: =IF($B86="","",_xlfn.XLOOKUP($B$54,PROCESOS,'MATRIZ REQUISITOS ISO'!I$7:I$14,"")) | L86: =IF($B86="","",_xlfn.XLOOKUP($B$54,PROCESOS,'MATRIZ REQUISITOS ISO'!J$7:J$14,"")) | M86: =IF($B86="","",_xlfn.XLOOKUP($B$54,PROCESOS,'MATRIZ REQUISITOS ISO'!K$7:K$14,"")) | ... AG86: =IF($B86="","",_xlfn.XLOOKUP($B$54,PROCESOS,'MATRIZ REQUISITOS ISO'!AE$7:AE$14,"")) | AH86: =$B$54 -> Medición_Análisis_y_Mejora
B87: Proyectos_e_Infraestructura | E87: REQUISITOS NORMA ISO 9001/2015
B88: ÁREAS QUE INTEGRAN EL PROCESO: | C88: Dirección: | D88: Procedimientos involucrados: | E88: participación DIRECTA (D) INDIRECTA (I) | F88: 4.1 | G88: 4.2 | H88: 4.3 | I88: 4.4 | J88: 5.1 | K88: 5.2 | L88: 5.3 | M88: 6.1 | N88: 6.2 | O88: 6.3 | P88: 7.1 | Q88: 7.2 | R88: 7.3 | S88: 7.4 | T88: 7.5 | U88: 8.1 | V88: 8.2 | W88: 8.3 | X88: 8.4 | Y88: 8.5 | Z88: 8.6 | AA88: 8.7 | AB88: 9.1 | AC88: 9.2 | AD88: 9.3 | AE88: 10.1 | AF88: 10.2 | AG88: 10.3 | AH88: CÓDIGO 1
B89: Proyectos e Infraestructura | C89: Técnica | D89: OOMPPI-01 OOMPPI-02 OOMPPI-03 OOMPPI-04 OOMPPI-05 | F89: =IF($B89="","",_xlfn.XLOOKUP($B$87,PROCESOS,'MATRIZ REQUISITOS ISO'!D$7:D$14,"")) -> 0 | G89: =IF($B89="","",_xlfn.XLOOKUP($B$87,PROCESOS,'MATRIZ REQUISITOS ISO'!E$7:E$14,"")) -> 7 | H89: =IF($B89="","",_xlfn.XLOOKUP($B$87,PROCESOS,'MATRIZ REQUISITOS ISO'!F$7:F$14,"")) -> 0 | I89: =IF($B89="","",_xlfn.XLOOKUP($B$87,PROCESOS,'MATRIZ REQUISITOS ISO'!G$7:G$14,"")) -> 7 | J89: =IF($B89="","",_xlfn.XLOOKUP($B$87,PROCESOS,'MATRIZ REQUISITOS ISO'!H$7:H$14,"")) -> 0 | K89: =IF($B89="","",_xlfn.XLOOKUP($B$87,PROCESOS,'MATRIZ REQUISITOS ISO'!I$7:I$14,"")) -> 0 | L89: =IF($B89="","",_xlfn.XLOOKUP($B$87,PROCESOS,'MATRIZ REQUISITOS ISO'!J$7:J$14,"")) -> 0 | M89: =IF($B89="","",_xlfn.XLOOKUP($B$87,PROCESOS,'MATRIZ REQUISITOS ISO'!K$7:K$14,"")) -> 7 | ... AG89: =IF($B89="","",_xlfn.XLOOKUP($B$87,PROCESOS,'MATRIZ REQUISITOS ISO'!AE$7:AE$14,"")) -> 7 | AH89: =$B$87 -> Proyectos_e_Infraestructura
B90: Sectorización hidrométrica e innovación | C90: Técnica | D90: OOMPSH-01 OOMPSH-02 OOMPSH-03 OOMPSH-05 OOMPSH-06 | F90: =IF($B90="","",_xlfn.XLOOKUP($B$87,PROCESOS,'MATRIZ REQUISITOS ISO'!D$7:D$14,"")) -> 0 | G90: =IF($B90="","",_xlfn.XLOOKUP($B$87,PROCESOS,'MATRIZ REQUISITOS ISO'!E$7:E$14,"")) -> 7 | H90: =IF($B90="","",_xlfn.XLOOKUP($B$87,PROCESOS,'MATRIZ REQUISITOS ISO'!F$7:F$14,"")) -> 0 | I90: =IF($B90="","",_xlfn.XLOOKUP($B$87,PROCESOS,'MATRIZ REQUISITOS ISO'!G$7:G$14,"")) -> 7 | J90: =IF($B90="","",_xlfn.XLOOKUP($B$87,PROCESOS,'MATRIZ REQUISITOS ISO'!H$7:H$14,"")) -> 0 | K90: =IF($B90="","",_xlfn.XLOOKUP($B$87,PROCESOS,'MATRIZ REQUISITOS ISO'!I$7:I$14,"")) -> 0 | L90: =IF($B90="","",_xlfn.XLOOKUP($B$87,PROCESOS,'MATRIZ REQUISITOS ISO'!J$7:J$14,"")) -> 0 | M90: =IF($B90="","",_xlfn.XLOOKUP($B$87,PROCESOS,'MATRIZ REQUISITOS ISO'!K$7:K$14,"")) -> 7 | ... AG90: =IF($B90="","",_xlfn.XLOOKUP($B$87,PROCESOS,'MATRIZ REQUISITOS ISO'!AE$7:AE$14,"")) -> 7 | AH90: =$B$87 -> Proyectos_e_Infraestructura
B91: Supervisión y Control de Obras | C91: Técnica | D91: OOMPSO-01 OOMPSO-02 OOMPSO-03 OOMPSO-04 | F91: =IF($B91="","",_xlfn.XLOOKUP($B$87,PROCESOS,'MATRIZ REQUISITOS ISO'!D$7:D$14,"")) -> 0 | G91: =IF($B91="","",_xlfn.XLOOKUP($B$87,PROCESOS,'MATRIZ REQUISITOS ISO'!E$7:E$14,"")) -> 7 | H91: =IF($B91="","",_xlfn.XLOOKUP($B$87,PROCESOS,'MATRIZ REQUISITOS ISO'!F$7:F$14,"")) -> 0 | I91: =IF($B91="","",_xlfn.XLOOKUP($B$87,PROCESOS,'MATRIZ REQUISITOS ISO'!G$7:G$14,"")) -> 7 | J91: =IF($B91="","",_xlfn.XLOOKUP($B$87,PROCESOS,'MATRIZ REQUISITOS ISO'!H$7:H$14,"")) -> 0 | K91: =IF($B91="","",_xlfn.XLOOKUP($B$87,PROCESOS,'MATRIZ REQUISITOS ISO'!I$7:I$14,"")) -> 0 | L91: =IF($B91="","",_xlfn.XLOOKUP($B$87,PROCESOS,'MATRIZ REQUISITOS ISO'!J$7:J$14,"")) -> 0 | M91: =IF($B91="","",_xlfn.XLOOKUP($B$87,PROCESOS,'MATRIZ REQUISITOS ISO'!K$7:K$14,"")) -> 7 | ... AG91: =IF($B91="","",_xlfn.XLOOKUP($B$87,PROCESOS,'MATRIZ REQUISITOS ISO'!AE$7:AE$14,"")) -> 7 | AH91: =$B$87 -> Proyectos_e_Infraestructura
B92: Trámites Técnicos | C92: Técnica | D92: OOMPTT-01 OOMPTT-02 OOMPTT-04 | F92: =IF($B92="","",_xlfn.XLOOKUP($B$87,PROCESOS,'MATRIZ REQUISITOS ISO'!D$7:D$14,"")) -> 0 | G92: =IF($B92="","",_xlfn.XLOOKUP($B$87,PROCESOS,'MATRIZ REQUISITOS ISO'!E$7:E$14,"")) -> 7 | H92: =IF($B92="","",_xlfn.XLOOKUP($B$87,PROCESOS,'MATRIZ REQUISITOS ISO'!F$7:F$14,"")) -> 0 | I92: =IF($B92="","",_xlfn.XLOOKUP($B$87,PROCESOS,'MATRIZ REQUISITOS ISO'!G$7:G$14,"")) -> 7 | J92: =IF($B92="","",_xlfn.XLOOKUP($B$87,PROCESOS,'MATRIZ REQUISITOS ISO'!H$7:H$14,"")) -> 0 | K92: =IF($B92="","",_xlfn.XLOOKUP($B$87,PROCESOS,'MATRIZ REQUISITOS ISO'!I$7:I$14,"")) -> 0 | L92: =IF($B92="","",_xlfn.XLOOKUP($B$87,PROCESOS,'MATRIZ REQUISITOS ISO'!J$7:J$14,"")) -> 0 | M92: =IF($B92="","",_xlfn.XLOOKUP($B$87,PROCESOS,'MATRIZ REQUISITOS ISO'!K$7:K$14,"")) -> 7 | ... AG92: =IF($B92="","",_xlfn.XLOOKUP($B$87,PROCESOS,'MATRIZ REQUISITOS ISO'!AE$7:AE$14,"")) -> 7 | AH92: =$B$87 -> Proyectos_e_Infraestructura
F93: =IF($B93="","",_xlfn.XLOOKUP($B$87,PROCESOS,'MATRIZ REQUISITOS ISO'!D$7:D$14,"")) | G93: =IF($B93="","",_xlfn.XLOOKUP($B$87,PROCESOS,'MATRIZ REQUISITOS ISO'!E$7:E$14,"")) | H93: =IF($B93="","",_xlfn.XLOOKUP($B$87,PROCESOS,'MATRIZ REQUISITOS ISO'!F$7:F$14,"")) | I93: =IF($B93="","",_xlfn.XLOOKUP($B$87,PROCESOS,'MATRIZ REQUISITOS ISO'!G$7:G$14,"")) | J93: =IF($B93="","",_xlfn.XLOOKUP($B$87,PROCESOS,'MATRIZ REQUISITOS ISO'!H$7:H$14,"")) | K93: =IF($B93="","",_xlfn.XLOOKUP($B$87,PROCESOS,'MATRIZ REQUISITOS ISO'!I$7:I$14,"")) | L93: =IF($B93="","",_xlfn.XLOOKUP($B$87,PROCESOS,'MATRIZ REQUISITOS ISO'!J$7:J$14,"")) | M93: =IF($B93="","",_xlfn.XLOOKUP($B$87,PROCESOS,'MATRIZ REQUISITOS ISO'!K$7:K$14,"")) | ... AG93: =IF($B93="","",_xlfn.XLOOKUP($B$87,PROCESOS,'MATRIZ REQUISITOS ISO'!AE$7:AE$14,"")) | AH93: =$B$87 -> Proyectos_e_Infraestructura
F94: =IF($B94="","",_xlfn.XLOOKUP($B$87,PROCESOS,'MATRIZ REQUISITOS ISO'!D$7:D$14,"")) | G94: =IF($B94="","",_xlfn.XLOOKUP($B$87,PROCESOS,'MATRIZ REQUISITOS ISO'!E$7:E$14,"")) | H94: =IF($B94="","",_xlfn.XLOOKUP($B$87,PROCESOS,'MATRIZ REQUISITOS ISO'!F$7:F$14,"")) | I94: =IF($B94="","",_xlfn.XLOOKUP($B$87,PROCESOS,'MATRIZ REQUISITOS ISO'!G$7:G$14,"")) | J94: =IF($B94="","",_xlfn.XLOOKUP($B$87,PROCESOS,'MATRIZ REQUISITOS ISO'!H$7:H$14,"")) | K94: =IF($B94="","",_xlfn.XLOOKUP($B$87,PROCESOS,'MATRIZ REQUISITOS ISO'!I$7:I$14,"")) | L94: =IF($B94="","",_xlfn.XLOOKUP($B$87,PROCESOS,'MATRIZ REQUISITOS ISO'!J$7:J$14,"")) | M94: =IF($B94="","",_xlfn.XLOOKUP($B$87,PROCESOS,'MATRIZ REQUISITOS ISO'!K$7:K$14,"")) | ... AG94: =IF($B94="","",_xlfn.XLOOKUP($B$87,PROCESOS,'MATRIZ REQUISITOS ISO'!AE$7:AE$14,"")) | AH94: =$B$87 -> Proyectos_e_Infraestructura
B95: Comunicación | E95: REQUISITOS NORMA ISO 9001/2015
B96: ÁREAS QUE INTEGRAN EL PROCESO: | C96: Dirección: | D96: Procedimientos involucrados: | E96: participación DIRECTA (D) INDIRECTA (I) | F96: 4.1 | G96: 4.2 | H96: 4.3 | I96: 4.4 | J96: 5.1 | K96: 5.2 | L96: 5.3 | M96: 6.1 | N96: 6.2 | O96: 6.3 | P96: 7.1 | Q96: 7.2 | R96: 7.3 | S96: 7.4 | T96: 7.5 | U96: 8.1 | V96: 8.2 | W96: 8.3 | X96: 8.4 | Y96: 8.5 | Z96: 8.6 | AA96: 8.7 | AB96: 9.1 | AC96: 9.2 | AD96: 9.3 | AE96: 10.1 | AF96: 10.2 | AG96: 10.3 | AH96: CÓDIGO 1
B97: Alta Dirección | C97: General | F97: =IF($B97="","",_xlfn.XLOOKUP($B$95,PROCESOS,'MATRIZ REQUISITOS ISO'!D$7:D$14,"")) -> 8 | G97: =IF($B97="","",_xlfn.XLOOKUP($B$95,PROCESOS,'MATRIZ REQUISITOS ISO'!E$7:E$14,"")) -> 8 | H97: =IF($B97="","",_xlfn.XLOOKUP($B$95,PROCESOS,'MATRIZ REQUISITOS ISO'!F$7:F$14,"")) -> 0 | I97: =IF($B97="","",_xlfn.XLOOKUP($B$95,PROCESOS,'MATRIZ REQUISITOS ISO'!G$7:G$14,"")) -> 8 | J97: =IF($B97="","",_xlfn.XLOOKUP($B$95,PROCESOS,'MATRIZ REQUISITOS ISO'!H$7:H$14,"")) -> 0 | K97: =IF($B97="","",_xlfn.XLOOKUP($B$95,PROCESOS,'MATRIZ REQUISITOS ISO'!I$7:I$14,"")) -> 0 | L97: =IF($B97="","",_xlfn.XLOOKUP($B$95,PROCESOS,'MATRIZ REQUISITOS ISO'!J$7:J$14,"")) -> 0 | M97: =IF($B97="","",_xlfn.XLOOKUP($B$95,PROCESOS,'MATRIZ REQUISITOS ISO'!K$7:K$14,"")) -> 8 | ... AG97: =IF($B97="","",_xlfn.XLOOKUP($B$95,PROCESOS,'MATRIZ REQUISITOS ISO'!AE$7:AE$14,"")) -> 8 | AH97: =$B$95 -> Comunicación
B98: Cultura del Agua | C98: Programas Sociales y cultura del Agua | D98: OOMPCU-01 | F98: =IF($B98="","",_xlfn.XLOOKUP($B$95,PROCESOS,'MATRIZ REQUISITOS ISO'!D$7:D$14,"")) -> 8 | G98: =IF($B98="","",_xlfn.XLOOKUP($B$95,PROCESOS,'MATRIZ REQUISITOS ISO'!E$7:E$14,"")) -> 8 | H98: =IF($B98="","",_xlfn.XLOOKUP($B$95,PROCESOS,'MATRIZ REQUISITOS ISO'!F$7:F$14,"")) -> 0 | I98: =IF($B98="","",_xlfn.XLOOKUP($B$95,PROCESOS,'MATRIZ REQUISITOS ISO'!G$7:G$14,"")) -> 8 | J98: =IF($B98="","",_xlfn.XLOOKUP($B$95,PROCESOS,'MATRIZ REQUISITOS ISO'!H$7:H$14,"")) -> 0 | K98: =IF($B98="","",_xlfn.XLOOKUP($B$95,PROCESOS,'MATRIZ REQUISITOS ISO'!I$7:I$14,"")) -> 0 | L98: =IF($B98="","",_xlfn.XLOOKUP($B$95,PROCESOS,'MATRIZ REQUISITOS ISO'!J$7:J$14,"")) -> 0 | M98: =IF($B98="","",_xlfn.XLOOKUP($B$95,PROCESOS,'MATRIZ REQUISITOS ISO'!K$7:K$14,"")) -> 8 | ... AG98: =IF($B98="","",_xlfn.XLOOKUP($B$95,PROCESOS,'MATRIZ REQUISITOS ISO'!AE$7:AE$14,"")) -> 8 | AH98: =$B$95 -> Comunicación
B99: Comunicación e Imagen Institucional | C99: Administrativa | D99: OOMPCI-01 OOMPCI-04 OOMPCI-06 | F99: =IF($B99="","",_xlfn.XLOOKUP($B$95,PROCESOS,'MATRIZ REQUISITOS ISO'!D$7:D$14,"")) -> 8 | G99: =IF($B99="","",_xlfn.XLOOKUP($B$95,PROCESOS,'MATRIZ REQUISITOS ISO'!E$7:E$14,"")) -> 8 | H99: =IF($B99="","",_xlfn.XLOOKUP($B$95,PROCESOS,'MATRIZ REQUISITOS ISO'!F$7:F$14,"")) -> 0 | I99: =IF($B99="","",_xlfn.XLOOKUP($B$95,PROCESOS,'MATRIZ REQUISITOS ISO'!G$7:G$14,"")) -> 8 | J99: =IF($B99="","",_xlfn.XLOOKUP($B$95,PROCESOS,'MATRIZ REQUISITOS ISO'!H$7:H$14,"")) -> 0 | K99: =IF($B99="","",_xlfn.XLOOKUP($B$95,PROCESOS,'MATRIZ REQUISITOS ISO'!I$7:I$14,"")) -> 0 | L99: =IF($B99="","",_xlfn.XLOOKUP($B$95,PROCESOS,'MATRIZ REQUISITOS ISO'!J$7:J$14,"")) -> 0 | M99: =IF($B99="","",_xlfn.XLOOKUP($B$95,PROCESOS,'MATRIZ REQUISITOS ISO'!K$7:K$14,"")) -> 8 | ... AG99: =IF($B99="","",_xlfn.XLOOKUP($B$95,PROCESOS,'MATRIZ REQUISITOS ISO'!AE$7:AE$14,"")) -> 8 | AH99: =$B$95 -> Comunicación
B100: Mandos Medios y Personal Operativo del Organismo | C100: General | F100: =IF($B100="","",_xlfn.XLOOKUP($B$95,PROCESOS,'MATRIZ REQUISITOS ISO'!D$7:D$14,"")) -> 8 | G100: =IF($B100="","",_xlfn.XLOOKUP($B$95,PROCESOS,'MATRIZ REQUISITOS ISO'!E$7:E$14,"")) -> 8 | H100: =IF($B100="","",_xlfn.XLOOKUP($B$95,PROCESOS,'MATRIZ REQUISITOS ISO'!F$7:F$14,"")) -> 0 | I100: =IF($B100="","",_xlfn.XLOOKUP($B$95,PROCESOS,'MATRIZ REQUISITOS ISO'!G$7:G$14,"")) -> 8 | J100: =IF($B100="","",_xlfn.XLOOKUP($B$95,PROCESOS,'MATRIZ REQUISITOS ISO'!H$7:H$14,"")) -> 0 | K100: =IF($B100="","",_xlfn.XLOOKUP($B$95,PROCESOS,'MATRIZ REQUISITOS ISO'!I$7:I$14,"")) -> 0 | L100: =IF($B100="","",_xlfn.XLOOKUP($B$95,PROCESOS,'MATRIZ REQUISITOS ISO'!J$7:J$14,"")) -> 0 | M100: =IF($B100="","",_xlfn.XLOOKUP($B$95,PROCESOS,'MATRIZ REQUISITOS ISO'!K$7:K$14,"")) -> 8 | ... AG100: =IF($B100="","",_xlfn.XLOOKUP($B$95,PROCESOS,'MATRIZ REQUISITOS ISO'!AE$7:AE$14,"")) -> 8 | AH100: =$B$95 -> Comunicación
B101: Recursos Humanos | C101: Administrativa | D101: OOMPRH-01 OOMPRH-04 OOMPRH-08 OOMPRH-16 | F101: =IF($B101="","",_xlfn.XLOOKUP($B$95,PROCESOS,'MATRIZ REQUISITOS ISO'!D$7:D$14,"")) -> 8 | G101: =IF($B101="","",_xlfn.XLOOKUP($B$95,PROCESOS,'MATRIZ REQUISITOS ISO'!E$7:E$14,"")) -> 8 | H101: =IF($B101="","",_xlfn.XLOOKUP($B$95,PROCESOS,'MATRIZ REQUISITOS ISO'!F$7:F$14,"")) -> 0 | I101: =IF($B101="","",_xlfn.XLOOKUP($B$95,PROCESOS,'MATRIZ REQUISITOS ISO'!G$7:G$14,"")) -> 8 | J101: =IF($B101="","",_xlfn.XLOOKUP($B$95,PROCESOS,'MATRIZ REQUISITOS ISO'!H$7:H$14,"")) -> 0 | K101: =IF($B101="","",_xlfn.XLOOKUP($B$95,PROCESOS,'MATRIZ REQUISITOS ISO'!I$7:I$14,"")) -> 0 | L101: =IF($B101="","",_xlfn.XLOOKUP($B$95,PROCESOS,'MATRIZ REQUISITOS ISO'!J$7:J$14,"")) -> 0 | M101: =IF($B101="","",_xlfn.XLOOKUP($B$95,PROCESOS,'MATRIZ REQUISITOS ISO'!K$7:K$14,"")) -> 8 | ... AG101: =IF($B101="","",_xlfn.XLOOKUP($B$95,PROCESOS,'MATRIZ REQUISITOS ISO'!AE$7:AE$14,"")) -> 8 | AH101: =$B$95 -> Comunicación
...
